Workbook

Sheet Contracted Suppliers_Live
B1: Contracted Supplier Tracking Sheet
B3: COLOMBIA - VENEZUELA
A4: Vendor account | B4: Supplier name | C4: Type of contract | D4: Contract Start Date | E4: Contract End Date | F4: Notice date (days) | G4: ATC status | H4: ATC clearance expiration date | I4: Site | J4: ATC | K4: Contract Reference | L4: Category of Goods or Services | M4: Contact Person | N4: Contact Phone/Fax Numbers | O4: Contact Email Address | P4: Ownership or Leadership Information | Q4: Name of Financial Institution (for bank-to-bank transactations only) | R4: Name of Account Holder (for bank-to-bank transactations only) | S4: Notes | T4: Valor Gastado COP | U4: Valor Gastado USD | V4: Vendor anticipated spend USD | W4: Number of Amendments | X4: Valor gastado USD | Z4: ATC | AA4: Notification to SC | AB4: Notification to Supplier | AC4: Amendments
A5: 10000514 | B5: =VLOOKUP(A5,'All vendors'!A:Z,2,0) -> Atlantic Tactical Group SAS | C5: MPA | D5: 44860 | E5: 45707 | F5: 30 | G5: =VLOOKUP(A5,'All vendors'!B:E,4,0) -> #N/A | H5: =VLOOKUP(A5,'All vendors'!B:E,3,0) -> #N/A | I5: COL-Bogotá | J5: =VLOOKUP(A5,'All vendors'!A:Z,13,0) -> 45654.504 | K5: MPA/2022/022 | L5: Supply of goods | M5: =VLOOKUP(A5,'All vendors'!A:Z,11,0) -> Juan Diego Chaparro Bayona | N5: =VLOOKUP(A5,'All vendors'!A:Z,12,0) -> +573158829720 | O5: =VLOOKUP(A5,'All vendors'!A:Z,15,0) -> ventas1@rescateydefensa.com | P5: Erika Viviana Zambrano | Q5: Banco de Bogotá | R5: Asia Trading Group SAS | S5: Sin Observaciones. Se renovara | T5: 0 | U5: =T5/4000 -> 0 | V5: =VLOOKUP(A5,'All vendors'!A:Z,17,0) -> 999999999 | W5: 0 | Z5: =IF(H5>E5,"No actions","Update ATC") -> #N/A | AA5: =IF(E5<(TODAY()+90),"Send email to SC","No actions") -> Send email to SC | AB5: =IF(E5<=(TODAY()+F5),"Send notification to supplier","No actions") -> Send notification to supplier | AC5: =IF((E5-D5)>720,W5>0, "No actions") -> FALSE | AD5: 999999999 | AE5: 45590
A6: 10000519 | B6: =VLOOKUP(A6,'All vendors'!A:Z,2,0) -> Comercializadora Y Distribuidora Raygo S.A.S | C6: MPA | D6: 44860 | E6: 45590 | F6: 30 | G6: =VLOOKUP(A6,'All vendors'!B:E,4,0) -> #N/A | H6: =VLOOKUP(A6,'All vendors'!B:E,3,0) -> #N/A | I6: COL-Bogotá | J6: =VLOOKUP(A6,'All vendors'!A:Z,13,0) -> 45658.695 | K6: MPA/2020/024 | L6: Supply of goods | M6: =VLOOKUP(A6,'All vendors'!A:Z,11,0) -> Patricia Gonzalez Velasquez | N6: =VLOOKUP(A6,'All vendors'!A:Z,12,0) -> +573005821543 | O6: =VLOOKUP(A6,'All vendors'!A:Z,15,0) -> comercializadoraraygosas@hotmai.com | P6: Patricia Gonzalez | Q6: Davivienda | R6: COMERCIALIZADORA Y DISTRIBUIDORA RAYGO SAS | S6: Sin Observaciones. No se Renovara | T6: 0 | U6: =T6/4000 -> 0 | V6: =VLOOKUP(A6,'All vendors'!A:Z,17,0) -> 999999999 | W6: 0 | Z6: =IF(H6>E6,"No actions","Update ATC") -> #N/A | AA6: =IF(E6<(TODAY()+90),"Send email to SC","No actions") -> Send email to SC | AB6: =IF(E6<=(TODAY()+F6),"Send notification to supplier","No actions") -> Send notification to supplier | AC6: =IF((E6-D6)>720,W6>0, "No actions") -> FALSE | AD6: 999999999 | AE6: 45590
A7: 10019523 | B7: =VLOOKUP(A7,'All vendors'!A:Z,2,0) -> Suarez Silva & Asociados | C7: Serv Agreem | D7: 45231 | E7: 45595 | F7: 30 | G7: =VLOOKUP(A7,'All vendors'!B:E,4,0) -> #N/A | H7: =VLOOKUP(A7,'All vendors'!B:E,3,0) -> #N/A | I7: VEN-Caracas | J7: =VLOOKUP(A7,'All vendors'!A:Z,13,0) -> 45609.292 | K7: SC+2500/2022/057 | L7: Legal Services | M7: =VLOOKUP(A7,'All vendors'!A:Z,11,0) -> Alejandra Suarez Silva | N7: =VLOOKUP(A7,'All vendors'!A:Z,12,0) -> +584144662227 | O7: =VLOOKUP(A7,'All vendors'!A:Z,15,0) -> Suarezsilvaasociados@gmail.com | P7: Claudia Patricia Flórez | Q7: Davivienda | R7: Movlife SAS | S7: En proceso de renovación | T7: 0 | U7: =T7/4000 -> 0 | V7: =VLOOKUP(A7,'All vendors'!A:Z,17,0) -> 999999999 | W7: 0 | AD7: 999999999 | AE7: 45595
A8: 10001556 | B8: =VLOOKUP(A8,'All vendors'!A:Z,2,0) -> Soluciones Empresariales Horizonte S.A.S. B.I.C. | C8: MSA | D8: 44834 | E8: 45597 | F8: 30 | G8: =VLOOKUP(A8,'All vendors'!B:E,4,0) -> #N/A | H8: =VLOOKUP(A8,'All vendors'!B:E,3,0) -> #N/A | I8: COL-Bogotá | J8: =VLOOKUP(A8,'All vendors'!A:Z,13,0) -> 45762.049 | K8: MSA/2022/036 | L8: Accounting services | M8: =VLOOKUP(A8,'All vendors'!A:Z,11,0) -> Miguel Garavito | N8: =VLOOKUP(A8,'All vendors'!A:Z,12,0) -> +573209040453 | O8: =VLOOKUP(A8,'All vendors'!A:Z,15,0) -> nomina1bogota@gsh.com.co | R8: Darlyng Xiomara Aceros | S8: Sin Observaciones | T8: 0 | U8: =T8/4000 -> 0 | V8: =VLOOKUP(A8,'All vendors'!A:Z,17,0) -> 999999999 | W8: 0 | Z8: =IF(H8>E8,"No actions","Update ATC") -> #N/A | AA8: =IF(E8<(TODAY()+90),"Send email to SC","No actions") -> Send email to SC | AB8: =IF(E8<=(TODAY()+F8),"Send notification to supplier","No actions") -> Send notification to supplier | AC8: =IF((E8-D8)>720,W8>0, "No actions") -> FALSE | AD8: 999999999 | AE8: 45597
A9: 10000341 | B9: =VLOOKUP(A9,'All vendors'!A:Z,2,0) -> Del Mar Abogados SAS | C9: MSA | D9: 43612 | E9: 45597 | F9: 30 | G9: =VLOOKUP(A9,'All vendors'!B:E,4,0) -> #N/A | H9: =VLOOKUP(A9,'All vendors'!B:E,3,0) -> #N/A | I9: COL-Bogotá | J9: =VLOOKUP(A9,'All vendors'!A:Z,13,0) -> 45846.268 | K9: SERV/PF/BOG/005-19 | L9: Legal Services | M9: =VLOOKUP(A9,'All vendors'!A:Z,11,0) -> Caroline Del Mar Gallardo Rojas | N9: =VLOOKUP(A9,'All vendors'!A:Z,12,0) -> +5713221386 | O9: =VLOOKUP(A9,'All vendors'!A:Z,15,0) -> caroline@grupodelmar.com | P9: Julio Gallardo Rojas | Q9: Davivienda | R9: DEL MAR ABOGADOS ASOCIADOS LTDA | S9: Sin Observaciones | T9: 0 | U9: =T9/4000 -> 0 | V9: =VLOOKUP(A9,'All vendors'!A:Z,17,0) -> 999999999 | W9: 0 | Z9: =IF(H9>E9,"No actions","Update ATC") -> #N/A | AA9: =IF(E9<(TODAY()+90),"Send email to SC","No actions") -> Send email to SC | AB9: =IF(E9<=(TODAY()+F9),"Send notification to supplier","No actions") -> Send notification to supplier | AC9: =IF((E9-D9)>720,W9>0, "No actions") -> FALSE | AD9: 999999999 | AE9: 45597
A10: 10017179 | B10: =VLOOKUP(A10,'All vendors'!A:Z,2,0) -> Leidy Mildreth Tobar Pinilla | C10: MSA | D10: 22-07-2024 | E10: 45627 | F10: 30 | G10: =VLOOKUP(A10,'All vendors'!B:E,4,0) -> #N/A | H10: =VLOOKUP(A10,'All vendors'!B:E,3,0) -> #N/A | I10: COL-Bogotá | J10: =VLOOKUP(A10,'All vendors'!A:Z,13,0) -> 45776.351 | K10: MPA_COL-VEN_2024-034 | L10: Legal Services | M10: =VLOOKUP(A10,'All vendors'!A:Z,11,0) -> Leidy Mildreth Tobar Pinilla | N10: =VLOOKUP(A10,'All vendors'!A:Z,12,0) -> +573112131650 | O10: =VLOOKUP(A10,'All vendors'!A:Z,15,0) -> customproductoscreativos@gmail.com | P10: Julio Gallardo Rojas | Q10: Davivienda | R10: DEL MAR ABOGADOS ASOCIADOS LTDA | S10: Sin Observaciones | T10: 0 | U10: =T10/4000 -> 0 | V10: =VLOOKUP(A10,'All vendors'!A:Z,17,0) -> 85000 | W10: 0 | AD10: 85000 | AE10: 45627
A11: 10050645 | B11: =VLOOKUP(A11,'All vendors'!A:Z,2,0) -> Iquartil SAS | C11: Serv Agreem | D11: 41769 | E11: 45650 | F11: 30 | G11: =VLOOKUP(A11,'All vendors'!B:E,4,0) -> #N/A | H11: =VLOOKUP(A11,'All vendors'!B:E,3,0) -> #N/A | I11: COL-Bogotá | J11: No tiene ATC | K11: SC+2500/2024/127 | L11: Recolección de Datos | M11: =VLOOKUP(A11,'All vendors'!A:Z,11,0) -> Beatriz Helena Cuervo Amore | N11: =VLOOKUP(A11,'All vendors'!A:Z,12,0) -> +573102361652 | O11: =VLOOKUP(A11,'All vendors'!A:Z,15,0) -> Beatriz.cuervo@iquartil.net | P11: Julio Gallardo Rojas | Q11: Davivienda | R11: DEL MAR ABOGADOS ASOCIADOS LTDA | S11: Sin Observaciones | T11: 0 | U11: =T11/4000 -> 0 | V11: =VLOOKUP(A11,'All vendors'!A:Z,17,0) -> 20000 | W11: 0 | Z11: =IF(H11>E11,"No actions","Update ATC") -> #N/A | AA11: =IF(E11<(TODAY()+90),"Send email to SC","No actions") -> Send email to SC | AB11: =IF(E11<=(TODAY()+F11),"Send notification to supplier","No actions") -> Send notification to supplier | AC11: =IF((E11-D11)>720,W11>0, "No actions") -> FALSE | AD11: 20000 | AE11: 45650
A12: 10000331 | B12: =VLOOKUP(A12,'All vendors'!A:Z,2,0) -> ATG Action Translation Group SAS | C12: MSA | D12: 44922 | E12: 45652 | F12: 30 | G12: =VLOOKUP(A12,'All vendors'!B:E,4,0) -> #N/A | H12: =VLOOKUP(A12,'All vendors'!B:E,3,0) -> #N/A | I12: COL-Bogotá | J12: =VLOOKUP(A12,'All vendors'!A:Z,13,0) -> 45775.112 | K12: MSA/2022/050 | L12: Translations | M12: =VLOOKUP(A12,'All vendors'!A:Z,11,0) -> Carlos Javier Rivera Rojas | N12: =VLOOKUP(A12,'All vendors'!A:Z,12,0) -> +573005630873 | O12: =VLOOKUP(A12,'All vendors'!A:Z,15,0) -> atgtraducciones@gmail.com | P12: Javier Rivera | Q12: Bancolombia | R12: ATG ACTION TRANSLATION GROUP SAS | S12: Sin Observaciones | T12: 0 | U12: =T12/4000 -> 0 | V12: =VLOOKUP(A12,'All vendors'!A:Z,17,0) -> 999999999 | W12: 0 | Z12: =IF(H12>E12,"No actions","Update ATC") -> #N/A | AA12: =IF(E12<(TODAY()+90),"Send email to SC","No actions") -> Send email to SC | AB12: =IF(E12<=(TODAY()+F12),"Send notification to supplier","No actions") -> Send notification to supplier | AC12: =IF((E12-D12)>720,W12>0, "No actions") -> FALSE | AD12: 999999999 | AE12: 45652
A13: 10022709 | B13: =VLOOKUP(A13,'All vendors'!A:Z,2,0) -> Blu Interpreter SAS | C13: MSA | D13: 44922 | E13: 45652 | F13: 30 | G13: =VLOOKUP(A13,'All vendors'!B:E,4,0) -> #N/A | H13: =VLOOKUP(A13,'All vendors'!B:E,3,0) -> #N/A | I13: COL-Bogotá | J13: =VLOOKUP(A13,'All vendors'!A:Z,13,0) -> 45835.716 | K13: MSA/2022/054 | L13: Translations | M13: =VLOOKUP(A13,'All vendors'!A:Z,11,0) -> Andrew Ebenezer Giraldo Pulido | N13: =VLOOKUP(A13,'All vendors'!A:Z,12,0) -> +573162062244 | O13: =VLOOKUP(A13,'All vendors'!A:Z,15,0) -> agiraldo@bluinterpreter.com | P13: Andrew Giraldo | Q13: Bancolombia | R13: BLU INTERPRETER SAS | S13: Sin Observaciones | T13: 0 | U13: =T13/4000 -> 0 | V13: =VLOOKUP(A13,'All vendors'!A:Z,17,0) -> 999999999 | W13: 0 | Z13: =IF(H13>E13,"No actions","Update ATC") -> #N/A | AA13: =IF(E13<(TODAY()+90),"Send email to SC","No actions") -> Send email to SC | AB13: =IF(E13<=(TODAY()+F13),"Send notification to supplier","No actions") -> Send notification to supplier | AC13: =IF((E13-D13)>720,W13>0, "No actions") -> FALSE | AD13: 999999999 | AE13: 45652
A14: 10050877 | B14: =VLOOKUP(A14,'All vendors'!A:Z,2,0) -> Seguridad Atlas Ltd. | C14: Serv Agreem | D14: 45475 | E14: 45653 | F14: 30 | G14: =VLOOKUP(A14,'All vendors'!B:E,4,0) -> #N/A | H14: =VLOOKUP(A14,'All vendors'!B:E,3,0) -> #N/A | I14: COL-Bogotá | J14: =VLOOKUP(A14,'All vendors'!A:Z,13,0) -> 45800.205 | K14: SC+2500/2024/119 | L14: Sagrilaf | M14: =VLOOKUP(A14,'All vendors'!A:Z,11,0) -> Diana Christina Harrera Gomez | N14: =VLOOKUP(A14,'All vendors'!A:Z,12,0) -> +573186127209 | O14: =VLOOKUP(A14,'All vendors'!A:Z,15,0) -> 0 | P14: Andrew Giraldo | Q14: Bancolombia | R14: BLU INTERPRETER SAS | S14: Sin Observaciones | T14: 0 | U14: =T14/4000 -> 0 | V14: =VLOOKUP(A14,'All vendors'!A:Z,17,0) -> 20000 | W14: 0 | AD14: 20000 | AE14: 45653
A15: 10005464 | B15: =VLOOKUP(A15,'All vendors'!A:Z,2,0) -> Telecomunicaciones TPB C.A. | C15: Serv Agreem | D15: 45474 | E15: 45657 | F15: 15 | G15: =VLOOKUP(A15,'All vendors'!B:E,4,0) -> #N/A | H15: =VLOOKUP(A15,'All vendors'!B:E,3,0) -> #N/A | I15: VEN-San Cristobal | J15: No tiene ATC | K15: SsC-2500/COL-VEN/2024/063 | L15: Internet Services | M15: =VLOOKUP(A15,'All vendors'!A:Z,11,0) -> Miguel Angel Rodriguez | N15: =VLOOKUP(A15,'All vendors'!A:Z,12,0) -> +584120584358 | O15: =VLOOKUP(A15,'All vendors'!A:Z,15,0) -> GestionTPB@colombiaconexiones.com | S15: Tope: 2.499 USD | T15: NA | U15: 0 | V15: =VLOOKUP(A15,'All vendors'!A:Z,17,0) -> 2400 | W15: 0 | Z15: =IF(H15>E15,"No actions","Update ATC") -> #N/A | AA15: =IF(E15<(TODAY()+90),"Send email to SC","No actions") -> Send email to SC | AB15: =IF(E15<=(TODAY()+F15),"Send notification to supplier","No actions") -> Send notification to supplier | AC15: =IF((E15-D15)>720,W15>0, "No actions") -> No actions | AD15: 2400 | AE15: 45657
A16: 10052988 | B16: =VLOOKUP(A16,'All vendors'!A:Z,2,0) -> Diana Cecilia Navarrete Canchón | C16: Serv Agreem | D16: 45570 | E16: 45657 | F16: 30 | G16: =VLOOKUP(A16,'All vendors'!B:E,4,0) -> #N/A | H16: =VLOOKUP(A16,'All vendors'!B:E,3,0) -> #N/A | I16: COL-Bogotá | J16: No tiene ATC | K16: SsC+2500_COL-VEN_2024_135 | L16: Nutrition Consultants | M16: =VLOOKUP(A16,'All vendors'!A:Z,11,0) -> Diana Cecilia Navarrete Canchón | N16: =VLOOKUP(A16,'All vendors'!A:Z,12,0) -> +573196743603 | O16: dcnavarretec08@gmail.com | S16: Tope:19000 USD | T16: NA | U16: 0 | V16: =VLOOKUP(A16,'All vendors'!A:Z,17,0) -> 19000 | W16: 0 | AD16: 19000 | AE16: 45657
A17: 10000333 | B17: =VLOOKUP(A17,'All vendors'!A:Z,2,0) -> Blanco Santana Montiel & Rincón | C17: Serv Agreem | D17: 45293 | E17: 45658 | F17: 30 | G17: =VLOOKUP(A17,'All vendors'!B:E,4,0) -> #N/A | H17: =VLOOKUP(A17,'All vendors'!B:E,3,0) -> #N/A | I17: VEN-Caracas | J17: =VLOOKUP(A17,'All vendors'!A:Z,13,0) -> 45867.716 | K17: SC+2500/2023/074 | L17: Legal Services | M17: =VLOOKUP(A17,'All vendors'!A:Z,11,0) -> Maria Alejandra Blanco Blanco | N17: =VLOOKUP(A17,'All vendors'!A:Z,12,0) -> +5824242506417 | O17: =VLOOKUP(A17,'All vendors'!A:Z,15,0) -> mablanco@bsmr.com.ve | Q17: Banesco S.A | R17: Blanco, Santana, Montiel & Rincòn Abogados | S17: Tope: 20.000 USD | T17: NA | U17: 0 | V17: =VLOOKUP(A17,'All vendors'!A:Z,17,0) -> 999999999 | W17: 0 | Z17: =IF(H17>E17,"No actions","Update ATC") -> #N/A | AA17: =IF(E17<(TODAY()+90),"Send email to SC","No actions") -> Send email to SC | AB17: =IF(E17<=(TODAY()+F17),"Send notification to supplier","No actions") -> Send notification to supplier | AC17: =IF((E17-D17)>720,W17>0, "No actions") -> No actions | AD17: 999999999 | AE17: 45658
A18: 10048679 | B18: =VLOOKUP(A18,'All vendors'!A:Z,2,0) -> Libia Johanna Leon Talero | C18: Serv Agreem | D18: 45297 | E18: 45662 | F18: 30 | G18: =VLOOKUP(A18,'All vendors'!B:E,4,0) -> #N/A | H18: =VLOOKUP(A18,'All vendors'!B:E,3,0) -> #N/A | I18: COL-Bogotá | J18: No tiene ATC | K18: SsC-2500-2024-041 | L18: English class Services | M18: =VLOOKUP(A18,'All vendors'!A:Z,11,0) -> Libia Johanna Leon Talero | N18: =VLOOKUP(A18,'All vendors'!A:Z,12,0) -> +573183028399 | O18: =VLOOKUP(A18,'All vendors'!A:Z,15,0) -> libilibileontalero@gmail.com | P18: Mercedez Espinoza | S18: Tope: 9.996.000 COP | T18: 0 | U18: =T18/4000 -> 0 | V18: =VLOOKUP(A18,'All vendors'!A:Z,17,0) -> 2450 | W18: 0 | AD18: 2450 | AE18: 45662
A19: 10013314 | B19: =VLOOKUP(A19,'All vendors'!A:Z,2,0) -> Transporte & Inversiones Filinto Gonzalez dba Filinto Antonio González Silva | C19: Serv Agreem | D19: 44935 | E19: 45666 | F19: 30 | G19: =VLOOKUP(A19,'All vendors'!B:E,4,0) -> #N/A | H19: =VLOOKUP(A19,'All vendors'!B:E,3,0) -> #N/A | I19: VEN-Maracaibo | J19: =VLOOKUP(A19,'All vendors'!A:Z,13,0) -> 45755.594 | K19: SC+2500/2023/065 | L19: Transportation | M19: =VLOOKUP(A19,'All vendors'!A:Z,11,0) -> Filinto Antonio González Silva | N19: =VLOOKUP(A19,'All vendors'!A:Z,12,0) -> +584122622049 | O19: =VLOOKUP(A19,'All vendors'!A:Z,15,0) -> Filintogonzalez1@hotmail.com | P19: Filinto Antonio Gonzalez | Q19: Bank of America | R19: Filinto Antonio Gonzalez | S19: Tope: 20.000 USD | T19: NA | U19: 0 | V19: =VLOOKUP(A19,'All vendors'!A:Z,17,0) -> 50000 | W19: 0 | Z19: =IF(H19>E19,"No actions","Update ATC") -> #N/A | AA19: =IF(E19<(TODAY()+90),"Send email to SC","No actions") -> Send email to SC | AB19: =IF(E19<=(TODAY()+F19),"Send notification to supplier","No actions") -> Send notification to supplier | AC19: =IF((E19-D19)>720,W19>0, "No actions") -> FALSE | AD19: 50000 | AE19: 45666
A20: 10048646 | B20: =VLOOKUP(A20,'All vendors'!A:Z,2,0) -> Servicios & Servicios Integrales s.a.s | C20: Serv Agreem | D20: 45308 | E20: 45673 | F20: 30 | G20: =VLOOKUP(A20,'All vendors'!B:E,4,0) -> #N/A | H20: =VLOOKUP(A20,'All vendors'!B:E,3,0) -> #N/A | I20: COL-Bogotá | J20: No tiene ATC | K20: SsC-2500-2024-042 | L20: Sanitation Services | M20: =VLOOKUP(A20,'All vendors'!A:Z,11,0) -> Alexandra Panqueva Espinoza | N20: =VLOOKUP(A20,'All vendors'!A:Z,12,0) -> +573183498423 | O20: =VLOOKUP(A20,'All vendors'!A:Z,15,0) -> alexandra.panqueva@prohygiene.com | P20: Mercedez Espinoza | S20: Tope: 9.996.000 COP | T20: 0 | U20: =T20/4000 -> 0 | V20: =VLOOKUP(A20,'All vendors'!A:Z,17,0) -> 2499 | W20: 0 | Z20: =IF(H20>E20,"No actions","Update ATC") -> #N/A | AA20: =IF(E20<(TODAY()+90),"Send email to SC","No actions") -> Send email to SC | AB20: =IF(E20<=(TODAY()+F20),"Send notification to supplier","No actions") -> Send notification to supplier | AC20: =IF((E20-D20)>720,W20>0, "No actions") -> No actions | AD20: 2499 | AE20: 45673
A21: 10026777 | B21: =VLOOKUP(A21,'All vendors'!A:Z,2,0) -> DATASAFECOLOMBIA LIMITADA | C21: Serv Agreem | D21: 45315 | E21: 45680 | F21: 30 | G21: =VLOOKUP(A21,'All vendors'!B:E,4,0) -> #N/A | H21: =VLOOKUP(A21,'All vendors'!B:E,3,0) -> #N/A | I21: COL-Bogotá | J21: No tiene ATC | K21: SsC-2500-2022-016 | L21: Office Services | M21: =VLOOKUP(A21,'All vendors'!A:Z,11,0) -> Gustavo Ortiz | N21: =VLOOKUP(A21,'All vendors'!A:Z,12,0) -> +573234365413 | O21: =VLOOKUP(A21,'All vendors'!A:Z,15,0) -> gerencia@datasafecolombia.com | P21: Adriana Villa | Q21: Davivienda | R21: Data Safe Colombia LTDA | S21: Tope: 2.499 USD | T21: 0 | U21: =T21/4000 -> 0 | V21: =VLOOKUP(A21,'All vendors'!A:Z,17,0) -> 2499 | W21: 0 | Z21: =IF(H21>E21,"No actions","Update ATC") -> #N/A | AA21: =IF(E21<(TODAY()+90),"Send email to SC","No actions") -> Send email to SC | AB21: =IF(E21<=(TODAY()+F21),"Send notification to supplier","No actions") -> Send notification to supplier | AC21: =IF((E21-D21)>720,W21>0, "No actions") -> No actions | AD21: 2499 | AE21: 45680
A22: 10025130 | B22: =VLOOKUP(A22,'All vendors'!A:Z,2,0) -> Servicios De Profesionales En Limpieza, C.A. | C22: Serv Agreem | D22: 44958 | E22: 45687 | F22: 30 | G22: =VLOOKUP(A22,'All vendors'!B:E,4,0) -> #N/A | H22: =VLOOKUP(A22,'All vendors'!B:E,3,0) -> #N/A | I22: VEN-Maracaibo | J22: =VLOOKUP(A22,'All vendors'!A:Z,13,0) -> 45666.257 | K22: SC+2500/2023/066 | L22: Cleaning services | M22: =VLOOKUP(A22,'All vendors'!A:Z,11,0) -> Yoxely Josefina Gonzalez Almarza | N22: =VLOOKUP(A22,'All vendors'!A:Z,12,0) -> +584246320253 | O22: =VLOOKUP(A22,'All vendors'!A:Z,15,0) -> Info@Seprolimca.com | P22: Yoxely Josefina Gonzalez | Q22: Well Fargo | R22: SEPROLIMCALLC | S22: Tope: 20.000 USD | T22: NA | U22: 0 | V22: =VLOOKUP(A22,'All vendors'!A:Z,17,0) -> 19000 | W22: 0 | Z22: =IF(H22>E22,"No actions","Update ATC") -> #N/A | AA22: =IF(E22<(TODAY()+90),"Send email to SC","No actions") -> Send email to SC | AB22: =IF(E22<=(TODAY()+F22),"Send notification to supplier","No actions") -> Send notification to supplier | AC22: =IF((E22-D22)>720,W22>0, "No actions") -> FALSE | AD22: 19000 | AE22: 45687
A23: 10027388 | B23: Gestora Estratégica Colombia S.A.S | C23: Serv Agreem | D23: 45323 | E23: 45688 | F23: 30 | G23: =VLOOKUP(A23,'All vendors'!B:E,4,0) -> #N/A | H23: =VLOOKUP(A23,'All vendors'!B:E,3,0) -> #N/A | I23: COL-Bogotá | J23: =VLOOKUP(A23,'All vendors'!A:Z,13,0) -> 45714.65 | K23: SC+2500/2024/110 | L23: Recargas de líneas telefónicas | M23: =VLOOKUP(A23,'All vendors'!A:Z,11,0) -> Yeny Andrea Vasquez Gutierrez | N23: =VLOOKUP(A23,'All vendors'!A:Z,12,0) -> +573112104884 | O23: =VLOOKUP(A23,'All vendors'!A:Z,15,0) -> administracion@gestrategica.com.co | P23: Mercedez Espinoza | S23: Tope: 20.000 USD | T23: 0 | U23: =T23/4000 -> 0 | V23: =VLOOKUP(A23,'All vendors'!A:Z,17,0) -> 999999999 | W23: 0 | AD23: 999999999 | AE23: 45688
A24: 10049307 | B24: =VLOOKUP(A24,'All vendors'!A:Z,2,0) -> Claudia Patricia Alvarez Ayure | C24: Serv Agreem | D24: 45323 | E24: 45323 | F24: 30 | G24: =VLOOKUP(A24,'All vendors'!B:E,4,0) -> #N/A | H24: =VLOOKUP(A24,'All vendors'!B:E,3,0) -> #N/A | I24: COL-Bogotá | J24: No tiene ATC | K24: SsC-2500-2024-043 | L24: English class Services | M24: =VLOOKUP(A24,'All vendors'!A:Z,11,0) -> Claudia Patricia Alvarez Ayure | N24: =VLOOKUP(A24,'All vendors'!A:Z,12,0) -> +573115953085 | O24: =VLOOKUP(A24,'All vendors'!A:Z,15,0) -> pattalvarez@gmail.com | S24: Tope:19000 USD | T24: NA | U24: 0 | V24: =VLOOKUP(A24,'All vendors'!A:Z,17,0) -> 19000 | W24: 0 | AD24: 19000 | AE24: 45323
A25: 10003142 | B25: =VLOOKUP(A25,'All vendors'!A:Z,2,0) -> Gestor Consultores S.A.S. | C25: MSA | D25: 44963 | E25: 45694 | F25: 30 | G25: =VLOOKUP(A25,'All vendors'!B:E,4,0) -> #N/A | H25: =VLOOKUP(A25,'All vendors'!B:E,3,0) -> #N/A | I25: COL-Bogotá | J25: =VLOOKUP(A25,'All vendors'!A:Z,13,0) -> 45659.677 | K25: MSA/2022/052 | L25: Coaching Services | M25: =VLOOKUP(A25,'All vendors'!A:Z,11,0) -> Juan Ricardo Orduz Garcia | N25: =VLOOKUP(A25,'All vendors'!A:Z,12,0) -> +573153872966 | O25: =VLOOKUP(A25,'All vendors'!A:Z,15,0) -> juano@gestorconsultores.com | P25: Juan Orduz | Q25: itau | R25: Gestor Consultores SAS | S25: Tiene una enmienda del 2024 | T25: 0 | U25: =T25/4000 -> 0 | V25: =VLOOKUP(A25,'All vendors'!A:Z,17,0) -> 999999999 | W25: 0 | Z25: =IF(H25>E25,"No actions","Update ATC") -> #N/A | AA25: =IF(E25<(TODAY()+90),"Send email to SC","No actions") -> Send email to SC | AB25: =IF(E25<=(TODAY()+F25),"Send notification to supplier","No actions") -> Send notification to supplier | AC25: =IF((E25-D25)>720,W25>0, "No actions") -> FALSE | AD25: 999999999 | AE25: 45694
A26: 10022620 | B26: =VLOOKUP(A26,'All vendors'!A:Z,2,0) -> B&B Consultoría y Asesoría Empresarial SAS | C26: MSA | D26: 44964 | E26: 45694 | F26: 30 | G26: =VLOOKUP(A26,'All vendors'!B:E,4,0) -> #N/A | H26: =VLOOKUP(A26,'All vendors'!B:E,3,0) -> #N/A | I26: COL-Bogotá | J26: =VLOOKUP(A26,'All vendors'!A:Z,13,0) -> 45654.504 | K26: MSA/2022/053 | L26: Coaching Services | M26: =VLOOKUP(A26,'All vendors'!A:Z,11,0) -> William Yesid Bejarano Cano | N26: =VLOOKUP(A26,'All vendors'!A:Z,12,0) -> +573118990147 | O26: =VLOOKUP(A26,'All vendors'!A:Z,15,0) -> yesid.bejarano@gmail.com | P26: William Yesid Bejarano | Q26: Bancolombia | R26: B&B CONSULTORIA Y ASESORIA EMPRESARIAL SAS | S26: Tiene una enmienda del 2024 | T26: 0 | U26: =T26/4000 -> 0 | V26: =VLOOKUP(A26,'All vendors'!A:Z,17,0) -> 999999999 | W26: 0 | Z26: =IF(H26>E26,"No actions","Update ATC") -> #N/A | AA26: =IF(E26<(TODAY()+90),"Send email to SC","No actions") -> Send email to SC | AB26: =IF(E26<=(TODAY()+F26),"Send notification to supplier","No actions") -> Send notification to supplier | AC26: =IF((E26-D26)>720,W26>0, "No actions") -> FALSE | AD26: 999999999 | AE26: 45694
A27: 10048253 | B27: Arckideas S.A.S. | C27: Serv Agreem | D27: 45338 | E27: 45703 | F27: 30 | G27: =VLOOKUP(A27,'All vendors'!B:E,4,0) -> #N/A | H27: =VLOOKUP(A27,'All vendors'!B:E,3,0) -> #N/A | I27: COL-Cúcuta | J27: No tiene ATC | K27: SsC-2500-2024-039 | L27: Parking Services | M27: =VLOOKUP(A27,'All vendors'!A:Z,11,0) -> Paola Peñaloza | N27: =VLOOKUP(A27,'All vendors'!A:Z,12,0) -> +573206712095 | O27: =VLOOKUP(A27,'All vendors'!A:Z,15,0) -> arckideasparkingservices@gmail.com | P27: William Yesid Bejarano | Q27: Bancolombia | R27: B&B CONSULTORIA Y ASESORIA EMPRESARIAL SAS | S27: Tope $5.000.000 COP | T27: 0 | U27: =T27/4000 -> 0 | V27: =VLOOKUP(A27,'All vendors'!A:Z,17,0) -> 2400 | W27: 0 | Z27: =IF(H27>E27,"No actions","Update ATC") -> #N/A | AA27: =IF(E27<(TODAY()+90),"Send email to SC","No actions") -> Send email to SC | AB27: =IF(E27<=(TODAY()+F27),"Send notification to supplier","No actions") -> Send notification to supplier | AC27: =IF((E27-D27)>720,W27>0, "No actions") -> No actions | AD27: 2400 | AE27: 45703
A28: 10000428 | B28: =VLOOKUP(A28,'All vendors'!A:Z,2,0) -> Rastrack SAS | C28: Serv Agreem | D28: 44974 | E28: 45704 | F28: 30 | G28: =VLOOKUP(A28,'All vendors'!B:E,4,0) -> #N/A | H28: =VLOOKUP(A28,'All vendors'!B:E,3,0) -> #N/A | I28: COL-Bogotá | J28: =VLOOKUP(A28,'All vendors'!A:Z,13,0) -> 45838.219 | K28: SC+2500/2023/063 | L28: Security Services | M28: =VLOOKUP(A28,'All vendors'!A:Z,11,0) -> Liliana Trujillo | N28: =VLOOKUP(A28,'All vendors'!A:Z,12,0) -> +573173801025 | O28: =VLOOKUP(A28,'All vendors'!A:Z,15,0) -> negociosespeciales@rastrack.com | P28: David Velazquez | Q28: Bancolombia | R28: Rastrack SAS | S28: Tope: 20.000 USD | T28: 0 | U28: =T28/4000 -> 0 | V28: =VLOOKUP(A28,'All vendors'!A:Z,17,0) -> 999999999 | W28: 0 | Z28: =IF(H28>E28,"No actions","Update ATC") -> #N/A | AA28: =IF(E28<(TODAY()+90),"Send email to SC","No actions") -> Send email to SC | AB28: =IF(E28<=(TODAY()+F28),"Send notification to supplier","No actions") -> Send notification to supplier | AC28: =IF((E28-D28)>720,W28>0, "No actions") -> FALSE | AD28: 999999999 | AE28: 45704
A29: 10045039 | B29: =VLOOKUP(A29,'All vendors'!A:Z,2,0) -> Grupo Polka S.A.S | C29: Serv Agreem | D29: 45348 | E29: 45713 | F29: 30 | G29: =VLOOKUP(A29,'All vendors'!B:E,4,0) -> #N/A | H29: =VLOOKUP(A29,'All vendors'!B:E,3,0) -> #N/A | I29: COL-Bogotá | J29: No tiene ATC | K29: SsC-2500-2024-044 | L29: Refrigerios | M29: =VLOOKUP(A29,'All vendors'!A:Z,11,0) -> Natalia Bohorquez Perry | N29: =VLOOKUP(A29,'All vendors'!A:Z,12,0) -> +573213338434 | O29: =VLOOKUP(A29,'All vendors'!A:Z,15,0) -> pedidos@polkadotpasteleria.com | P29: David Velazquez | Q29: Bancolombia | R29: Rastrack SAS | S29: Tope: 9.000.000 COP | T29: 0 | U29: =T29/4000 -> 0 | V29: =VLOOKUP(A29,'All vendors'!A:Z,17,0) -> 2499 | W29: 0 | Z29: =IF(H29>E29,"No actions","Update ATC") -> #N/A | AA29: =IF(E29<(TODAY()+90),"Send email to SC","No actions") -> Send email to SC | AB29: =IF(E29<=(TODAY()+F29),"Send notification to supplier","No actions") -> Send notification to supplier | AC29: =IF((E29-D29)>720,W29>0, "No actions") -> No actions | AD29: 2499 | AE29: 45713
A30: 10049717 | B30: =VLOOKUP(A30,'All vendors'!A:Z,2,0) -> Salud Ocupacional Horizonte LTDA | C30: Serv Agreem | D30: 45352 | E30: 45716 | F30: 30 | G30: =VLOOKUP(A30,'All vendors'!B:E,4,0) -> #N/A | H30: =VLOOKUP(A30,'All vendors'!B:E,3,0) -> #N/A | I30: COL-Bogotá | J30: =VLOOKUP(A30,'All vendors'!A:Z,13,0) -> 45708.254 | K30: SC+2500/2024/113 | L30: Health Services | M30: =VLOOKUP(A30,'All vendors'!A:Z,11,0) -> Nicolás Villamizar | N30: =VLOOKUP(A30,'All vendors'!A:Z,12,0) -> +573160414402 | O30: =VLOOKUP(A30,'All vendors'!A:Z,15,0) -> nicolas.villamizar@gsh.com.co | P30: David Velazquez | Q30: Bancolombia | R30: Rastrack SAS | S30: Sin Observaciones | T30: 0 | U30: =T30/4000 -> 0 | V30: =VLOOKUP(A30,'All vendors'!A:Z,17,0) -> 20000 | W30: 0 | AD30: 20000 | AE30: 45716
A31: 10019523 | B31: =VLOOKUP(A31,'All vendors'!A:Z,2,0) -> Suarez Silva & Asociados | C31: Serv Agreem | D31: 44866 | E31: 45716 | F31: 30 | I31: VEN-Caracas | J31: =VLOOKUP(A31,'All vendors'!A:Z,13,0) -> 45609.292 | K31: SC+2500/2024/117 | L31: Nomina | M31: =VLOOKUP(A31,'All vendors'!A:Z,11,0) -> Alejandra Suarez Silva | N31: =VLOOKUP(A31,'All vendors'!A:Z,12,0) -> +584144662227 | O31: =VLOOKUP(A31,'All vendors'!A:Z,15,0) -> Suarezsilvaasociados@gmail.com | P31: David Velazquez | Q31: Bancolombia | R31: Rastrack SAS | S31: Sin Observaciones | T31: NA | U31: 0 | V31: =VLOOKUP(A31,'All vendors'!A:Z,17,0) -> 999999999 | W31: 0 | AD31: 999999999 | AE31: 45716
A32: 10025027 | B32: =VLOOKUP(A32,'All vendors'!A:Z,2,0) -> Matteria S.A.S | C32: Serv Agreem | D32: 44986 | E32: 45722 | F32: 5 | G32: =VLOOKUP(A32,'All vendors'!B:E,4,0) -> #N/A | H32: =VLOOKUP(A32,'All vendors'!B:E,3,0) -> #N/A | I32: COL-Bogotá | J32: =VLOOKUP(A32,'All vendors'!A:Z,13,0) -> 45659.684 | K32: SC+2500/2023/068 | L32: Consultant | M32: =VLOOKUP(A32,'All vendors'!A:Z,11,0) -> Fernanda Forero Barbosa | N32: =VLOOKUP(A32,'All vendors'!A:Z,12,0) -> 0 | O32: =VLOOKUP(A32,'All vendors'!A:Z,15,0) -> 0 | P32: Fernanda Forero | S32: Tope: 20.000 USD | T32: 0 | U32: =T32/4000 -> 0 | V32: =VLOOKUP(A32,'All vendors'!A:Z,17,0) -> 999999999 | W32: 0 | Z32: =IF(H32>E32,"No actions","Update ATC") -> #N/A | AA32: =IF(E32<(TODAY()+90),"Send email to SC","No actions") -> Send email to SC | AB32: =IF(E32<=(TODAY()+F32),"Send notification to supplier","No actions") -> No actions | AC32: =IF((E32-D32)>720,W32>0, "No actions") -> FALSE | AD32: 999999999 | AE32: 45722
A33: 10050010 | B33: =VLOOKUP(A33,'All vendors'!A:Z,2,0) -> Empresa de Transporte Radio Taxi Radio SA | C33: Serv Agreem | D33: 45369 | E33: 45733 | F33: 30 | I33: COL-Cúcuta | J33: =VLOOKUP(A33,'All vendors'!A:Z,13,0) -> 45722.684 | K33: SC+2500/2024/115 | L33: Transportation | M33: =VLOOKUP(A33,'All vendors'!A:Z,11,0) -> Gloria Yaneth Jaramillo Garcia | N33: =VLOOKUP(A33,'All vendors'!A:Z,12,0) -> +573212925177 | O33: =VLOOKUP(A33,'All vendors'!A:Z,15,0) -> radiotaxiradio1984@gmail.com | S33: Tope: 20.000 USD | T33: 0 | U33: =T33/4000 -> 0 | V33: =VLOOKUP(A33,'All vendors'!A:Z,17,0) -> 19000 | W33: 0 | AC33: =IF((E33-D33)>720,W33>0, "No actions") -> No actions | AD33: 19000 | AE33: 45733
A34: 10017030 | B34: =VLOOKUP(A34,'All vendors'!A:Z,2,0) -> Real Time Security (Colombia,Peru) SAS | C34: Serv Agreem | D34: 44640 | E34: 45735 | F34: 30 | G34: =VLOOKUP(A34,'All vendors'!B:E,4,0) -> #N/A | H34: =VLOOKUP(A34,'All vendors'!B:E,3,0) -> #N/A | I34: COL-Bogotá | J34: =VLOOKUP(A34,'All vendors'!A:Z,13,0) -> 45688.271 | K34: SsC-2500-2020-004 | L34: Security Services | M34: =VLOOKUP(A34,'All vendors'!A:Z,11,0) -> Christian Javier Estupiñan Córdoba | N34: =VLOOKUP(A34,'All vendors'!A:Z,12,0) -> +573202067849 | O34: =VLOOKUP(A34,'All vendors'!A:Z,15,0) -> cestupinan@realtimesecurity-colombia.com | P34: Christian Javier Estupiñan Cordoba | Q34: Bancolombia | R34: Real Time Security Colombia SAS | S34: El contrato se extendió y se modificó la cobertura, será solo para Colombia . | T34: 0 | U34: =T34/4000 -> 0 | V34: =VLOOKUP(A34,'All vendors'!A:Z,17,0) -> 50000 | W34: 0 | Z34: =IF(H34>E34,"No actions","Update ATC") -> #N/A | AA34: =IF(E34<(TODAY()+90),"Send email to SC","No actions") -> Send email to SC | AB34: =IF(E34<=(TODAY()+F34),"Send notification to supplier","No actions") -> Send notification to supplier | AC34: =IF((E34-D34)>720,W34>0, "No actions") -> FALSE | AD34: 50000 | AE34: 45735
A35: 10050195 | B35: =VLOOKUP(A35,'All vendors'!A:Z,2,0) -> Pluxee Beneficios e Incentivos, C.A. | C35: Serv Agreem | D35: 45378 | E35: 45742 | F35: 30 | G35: =VLOOKUP(A35,'All vendors'!B:E,4,0) -> #N/A | H35: =VLOOKUP(A35,'All vendors'!B:E,3,0) -> #N/A | I35: VEN-Caracas | J35: =VLOOKUP(A35,'All vendors'!A:Z,13,0) -> 45743.299 | K35: Contrato del Proveedor | L35: Tarjeta de Alimentación | M35: =VLOOKUP(A35,'All vendors'!A:Z,11,0) -> Vanessa Sandoval | N35: =VLOOKUP(A35,'All vendors'!A:Z,12,0) -> +584241623183 | O35: =VLOOKUP(A35,'All vendors'!A:Z,15,0) -> Vanessa.sandoval@pluxeegroup.com | P35: Margarita Restrepo | Q35: Bancolombia | R35: Agencia de Viajes y Turismo AVIATUR SAS | S35: Sin Observaciones | T35: NA | U35: 0 | V35: =VLOOKUP(A35,'All vendors'!A:Z,17,0) -> 19000 | W35: 0 | AD35: 19000 | AE35: 45742
A36: 10049688 | B36: =VLOOKUP(A36,'All vendors'!A:Z,2,0) -> Servicios Colomven S.A.S | C36: Serv Agreem | D36: 45317 | E36: 45747 | F36: 30 | G36: =VLOOKUP(A36,'All vendors'!B:E,4,0) -> #N/A | H36: =VLOOKUP(A36,'All vendors'!B:E,3,0) -> #N/A | I36: COL-Cúcuta | J36: =VLOOKUP(A36,'All vendors'!A:Z,13,0) -> 45707.271 | K36: SC+2500/2024/111 | L36: Cleaning services | M36: =VLOOKUP(A36,'All vendors'!A:Z,11,0) -> Jose Reinel Tami | N36: =VLOOKUP(A36,'All vendors'!A:Z,12,0) -> +573106495406 | O36: =VLOOKUP(A36,'All vendors'!A:Z,15,0) -> servicioscolomvensas@gmail.com | P36: Mariana Saenz | Q36: Banco de Bogotá | R36: Corporación Vínculos | S36: Tope 15.000.000 COP. Se realizara renovación | T36: 0 | U36: =T36/4000 -> 0 | V36: =VLOOKUP(A36,'All vendors'!A:Z,17,0) -> 4000 | W36: 0 | Z36: =IF(H36>E36,"No actions","Update ATC") -> #N/A | AA36: =IF(E36<(TODAY()+90),"Send email to SC","No actions") -> Send email to SC | AB36: =IF(E36<=(TODAY()+F36),"Send notification to supplier","No actions") -> No actions | AC36: =IF((E36-D36)>720,W36>0, "No actions") -> No actions | AD36: 4000 | AE36: 45747
A37: 10000391 | B37: =VLOOKUP(A37,'All vendors'!A:Z,2,0) -> Agencia De Viajes Y Turismo Aviatur SAS | C37: MSA | D37: 45017 | E37: 45747 | F37: 30 | G37: =VLOOKUP(A37,'All vendors'!B:E,4,0) -> #N/A | H37: =VLOOKUP(A37,'All vendors'!B:E,3,0) -> #N/A | I37: COL-Bogotá | J37: =VLOOKUP(A37,'All vendors'!A:Z,13,0) -> 45848.441 | K37: MSA/2022/051 | L37: Travel Agency | M37: =VLOOKUP(A37,'All vendors'!A:Z,11,0) -> Margarita Restrepo | N37: =VLOOKUP(A37,'All vendors'!A:Z,12,0) -> +573153493584 | O37: =VLOOKUP(A37,'All vendors'!A:Z,15,0) -> magarita.restrepo@aviatur.com | P37: Margarita Restrepo | Q37: Bancolombia | R37: Agencia de Viajes y Turismo AVIATUR SAS | S37: Sin Observaciones | T37: 0 | U37: =T37/4000 -> 0 | V37: =VLOOKUP(A37,'All vendors'!A:Z,17,0) -> 999999999 | W37: 0 | Z37: =IF(H37>E37,"No actions","Update ATC") -> #N/A | AA37: =IF(E37<(TODAY()+90),"Send email to SC","No actions") -> Send email to SC | AB37: =IF(E37<=(TODAY()+F37),"Send notification to supplier","No actions") -> No actions | AC37: =IF((E37-D37)>720,W37>0, "No actions") -> FALSE | AD37: 999999999 | AE37: 45747
A38: 10001345 | B38: =VLOOKUP(A38,'All vendors'!A:Z,2,0) -> Movlife S.A.S | C38: MSA | D38: 44652 | E38: 45747 | F38: 30 | G38: =VLOOKUP(A38,'All vendors'!B:E,4,0) -> #N/A | H38: =VLOOKUP(A38,'All vendors'!B:E,3,0) -> #N/A | I38: COL-Bogotá | J38: =VLOOKUP(A38,'All vendors'!A:Z,13,0) -> 45709.487 | K38: MSA/2022/037 | L38: Transportation | M38: =VLOOKUP(A38,'All vendors'!A:Z,11,0) -> Astrid Melissa Gómez Flórez | N38: =VLOOKUP(A38,'All vendors'!A:Z,12,0) -> +573123103269 | O38: =VLOOKUP(A38,'All vendors'!A:Z,15,0) -> melissa.gomez@movlife.co | P38: Claudia Patricia Flórez | Q38: Davivienda | R38: Movlife SAS | S38: Tiene una enmienda del 2024 | T38: 0 | U38: =T38/4000 -> 0 | V38: =VLOOKUP(A38,'All vendors'!A:Z,17,0) -> 999999999 | W38: 0 | Z38: =IF(H38>E38,"No actions","Update ATC") -> #N/A | AA38: =IF(E38<(TODAY()+90),"Send email to SC","No actions") -> Send email to SC | AB38: =IF(E38<=(TODAY()+F38),"Send notification to supplier","No actions") -> No actions | AC38: =IF((E38-D38)>720,W38>0, "No actions") -> FALSE | AD38: 999999999 | AE38: 45747
A39: 10050094 | B39: =VLOOKUP(A39,'All vendors'!A:Z,2,0) -> Graficalez SAS | C39: Purch Agreem | D39: 45383 | E39: 45747 | F39: 30 | G39: =VLOOKUP(A39,'All vendors'!B:E,4,0) -> #N/A | H39: =VLOOKUP(A39,'All vendors'!B:E,3,0) -> #N/A | I39: COL-Bogotá | J39: =VLOOKUP(A39,'All vendors'!A:Z,13,0) -> 45735.493 | K39: SC+2500/2024/112 | L39: Visibility | M39: =VLOOKUP(A39,'All vendors'!A:Z,11,0) -> Francys Lizeth Gonzalez Castillo | N39: =VLOOKUP(A39,'All vendors'!A:Z,12,0) -> +573123107175 | O39: =VLOOKUP(A39,'All vendors'!A:Z,15,0) -> comercialgraficalez@gmail.com | P39: Claudia Patricia Flórez | Q39: Davivienda | R39: Movlife SAS | S39: Sin Observaciones | T39: 0 | U39: =T39/4000 -> 0 | V39: =VLOOKUP(A39,'All vendors'!A:Z,17,0) -> 19000 | W39: 0 | Z39: =IF(H39>E39,"No actions","Update ATC") -> #N/A | AA39: =IF(E39<(TODAY()+90),"Send email to SC","No actions") -> Send email to SC | AB39: =IF(E39<=(TODAY()+F39),"Send notification to supplier","No actions") -> No actions | AC39: =IF((E39-D39)>720,W39>0, "No actions") -> No actions | AD39: 19000 | AE39: 45747
A40: 10050034 | B40: =VLOOKUP(A40,'All vendors'!A:Z,2,0) -> Antonia Trinidad Herrera Chirinos | C40: Purch Agreem | D40: 45383 | E40: 45747 | F40: 30 | G40: =VLOOKUP(A40,'All vendors'!B:E,4,0) -> #N/A | H40: =VLOOKUP(A40,'All vendors'!B:E,3,0) -> #N/A | I40: COL-Bogotá | J40: No tiene ATC | K40: SsC-2500-2024-051 | L40: Refrigerios | M40: =VLOOKUP(A40,'All vendors'!A:Z,11,0) -> Antonia Trinidad Herrera Chirinos | N40: =VLOOKUP(A40,'All vendors'!A:Z,12,0) -> +573142103152 | O40: =VLOOKUP(A40,'All vendors'!A:Z,15,0) -> anthoniach1402@gmail.com | P40: Claudia Patricia Flórez | Q40: Davivienda | R40: Movlife SAS | S40: Sin Observaciones | T40: 0 | U40: =T40/4000 -> 0 | V40: =VLOOKUP(A40,'All vendors'!A:Z,17,0) -> 2400 | W40: 0 | Z40: =IF(H40>E40,"No actions","Update ATC") -> #N/A | AA40: =IF(E40<(TODAY()+90),"Send email to SC","No actions") -> Send email to SC | AB40: =IF(E40<=(TODAY()+F40),"Send notification to supplier","No actions") -> No actions | AC40: =IF((E40-D40)>720,W40>0, "No actions") -> No actions | AD40: 2400 | AE40: 45747
A41: 10000402 | B41: =VLOOKUP(A41,'All vendors'!A:Z,2,0) -> Tigers Job Ltda | C41: Serv Agreem | D41: 45383 | E41: 45747 | F41: 30 | G41: =VLOOKUP(A41,'All vendors'!B:E,4,0) -> #N/A | H41: =VLOOKUP(A41,'All vendors'!B:E,3,0) -> #N/A | I41: COL-Cúcuta | J41: =VLOOKUP(A41,'All vendors'!A:Z,13,0) -> 45654.532 | K41: SC+2500/2024/118 | L41: Private Security | M41: =VLOOKUP(A41,'All vendors'!A:Z,11,0) -> Angelica Guerrero Gonzalez | N41: =VLOOKUP(A41,'All vendors'!A:Z,12,0) -> +573152350459 | O41: =VLOOKUP(A41,'All vendors'!A:Z,15,0) -> comercial@tigerjob.com.co | P41: Maria del Carmen Delgado | Q41: Banco de Bogotá | R41: TIGERS JOB Ltda | S41: Sin Observaciones | T41: 0 | U41: =T41/4000 -> 0 | V41: =VLOOKUP(A41,'All vendors'!A:Z,17,0) -> 999999999 | W41: 0 | Y41: =IF(H41>E41,"No actions","Update ATC") -> #N/A | Z41: =IF(E41<(TODAY()+90),"Send email to SC","No actions") -> Send email to SC | AA41: =IF(E41<=(TODAY()+F41),"Send notification to supplier","No actions") -> No actions | AB41: =IF((E41-D41)>720,U41>0, "No actions") -> No actions | AD41: 999999999 | AE41: 45747
A42: 10050321 | B42: =VLOOKUP(A42,'All vendors'!A:Z,2,0) -> Jose Reinel Mendez Tique | C42: Purch Agreem | D42: 45386 | E42: 45750 | F42: 30 | G42: =VLOOKUP(A42,'All vendors'!B:E,4,0) -> #N/A | H42: =VLOOKUP(A42,'All vendors'!B:E,3,0) -> #N/A | I42: COL-Bogotá | J42: No tiene ATC | K42: SsC-2500-2024-055 | L42: Café | M42: =VLOOKUP(A42,'All vendors'!A:Z,11,0) -> Jose Reinel Mendez Tique | N42: =VLOOKUP(A42,'All vendors'!A:Z,12,0) -> +573234780735 | O42: =VLOOKUP(A42,'All vendors'!A:Z,15,0) -> josereinelmendeztique@gmail.com | P42: Claudia Patricia Flórez | Q42: Davivienda | R42: Movlife SAS | S42: Sin Observaciones | T42: 0 | U42: =T42/4000 -> 0 | V42: =VLOOKUP(A42,'All vendors'!A:Z,17,0) -> 2500 | W42: 0 | Z42: =IF(H42>E42,"No actions","Update ATC") -> #N/A | AA42: =IF(E42<(TODAY()+90),"Send email to SC","No actions") -> Send email to SC | AB42: =IF(E42<=(TODAY()+F42),"Send notification to supplier","No actions") -> No actions | AC42: =IF((E42-D42)>720,W42>0, "No actions") -> No actions | AD42: 2500 | AE42: 45750
A43: 10050322 | B43: =VLOOKUP(A43,'All vendors'!A:Z,2,0) -> Big Pass S.A.S | C43: Serv Agreem | D43: 45397 | E43: 45761 | F43: 30 | G43: =VLOOKUP(A43,'All vendors'!B:E,4,0) -> #N/A | H43: =VLOOKUP(A43,'All vendors'!B:E,3,0) -> #N/A | I43: COL-Bogotá | J43: No tiene ATC | K43: SsC-2500-2024-062 | L43: Dotación | M43: =VLOOKUP(A43,'All vendors'!A:Z,11,0) -> Beatriz Elena Torres Alvarez | N43: =VLOOKUP(A43,'All vendors'!A:Z,12,0) -> +573132100950 | O43: =VLOOKUP(A43,'All vendors'!A:Z,15,0) -> Beatriz.torres1@edenred.com | P43: Claudia Patricia Flórez | Q43: Davivienda | R43: Movlife SAS | S43: Sin Observaciones | T43: 0 | U43: =T43/4000 -> 0 | V43: =VLOOKUP(A43,'All vendors'!A:Z,17,0) -> 2500 | W43: 0 | AD43: 2500 | AE43: 45761
A44: 10050600 | B44: =VLOOKUP(A44,'All vendors'!A:Z,2,0) -> Diana Maria Perez Rodriquez | C44: Serv Agreem | D44: 45412 | E44: 45776 | F44: 30 | G44: =VLOOKUP(A44,'All vendors'!B:E,4,0) -> #N/A | H44: =VLOOKUP(A44,'All vendors'!B:E,3,0) -> #N/A | I44: COL-Bogotá | J44: =VLOOKUP(A44,'All vendors'!A:Z,13,0) -> 45776.619 | K44: SC+2500/2024/124 | L44: Coaching Services | M44: =VLOOKUP(A44,'All vendors'!A:Z,11,0) -> Diana Maria Perez Rodriquez | N44: =VLOOKUP(A44,'All vendors'!A:Z,12,0) -> +573124827984 | O44: =VLOOKUP(A44,'All vendors'!A:Z,15,0) -> 0 | P44: Claudia Patricia Flórez | Q44: Davivienda | R44: Movlife SAS | S44: Sin Observaciones | T44: 0 | U44: =T44/4000 -> 0 | V44: =VLOOKUP(A44,'All vendors'!A:Z,17,0) -> 20000 | W44: 0 | AD44: 20000 | AE44: 45776
A45: 10036684 | B45: =VLOOKUP(A45,'All vendors'!A:Z,2,0) -> Inntegroup S.A.S | C45: Purch Agreem | D45: 45413 | E45: 45777 | F45: 30 | G45: =VLOOKUP(A45,'All vendors'!B:E,4,0) -> #N/A | H45: =VLOOKUP(A45,'All vendors'!B:E,3,0) -> #N/A | I45: COL-Bogotá | J45: No tiene ATC | K45: SsC-2500-2024-061 | L45: Supply of goods | M45: =VLOOKUP(A45,'All vendors'!A:Z,11,0) -> Oscar Eduardo | N45: =VLOOKUP(A45,'All vendors'!A:Z,12,0) -> +573138673124 | O45: =VLOOKUP(A45,'All vendors'!A:Z,15,0) -> inntegroup@gmail.com | P45: Claudia Patricia Flórez | Q45: Davivienda | R45: Movlife SAS | S45: Sin Observaciones | T45: 0 | U45: =T45/4000 -> 0 | V45: =VLOOKUP(A45,'All vendors'!A:Z,17,0) -> 20000 | W45: 0 | AD45: 20000 | AE45: 45777
A46: 10003138 | B46: =VLOOKUP(A46,'All vendors'!A:Z,2,0) -> Easy Taxi S.A.S | C46: Serv Agreem | D46: 45415 | E46: 45779 | F46: 30 | G46: =VLOOKUP(A46,'All vendors'!B:E,4,0) -> #N/A | H46: =VLOOKUP(A46,'All vendors'!B:E,3,0) -> #N/A | I46: COL-Bogotá | J46: =VLOOKUP(A46,'All vendors'!A:Z,13,0) -> 45729.233 | K46: SC+2500/2024/125 | L46: Transportation | M46: =VLOOKUP(A46,'All vendors'!A:Z,11,0) -> Laura Moreno Ruiz | N46: =VLOOKUP(A46,'All vendors'!A:Z,12,0) -> +573152873445 | O46: =VLOOKUP(A46,'All vendors'!A:Z,15,0) -> laura.moreno@cabify.com | P46: Manuel torres | S46: Sin Observaciones | T46: 0 | U46: =T46/4000 -> 0 | V46: =VLOOKUP(A46,'All vendors'!A:Z,17,0) -> 999999999 | W46: 0 | Z46: =IF(H46>E46,"No actions","Update ATC") -> #N/A | AA46: =IF(E46<(TODAY()+90),"Send email to SC","No actions") -> Send email to SC | AB46: =IF(E46<=(TODAY()+F46),"Send notification to supplier","No actions") -> No actions | AC46: =IF((E46-D46)>720,W46>0, "No actions") -> No actions | AD46: 999999999 | AE46: 45779
A47: 10000769 | B47: =VLOOKUP(A47,'All vendors'!A:Z,2,0) -> Cabify Empresarial S.A.S | C47: Serv Agreem | D47: 45415 | E47: 45779 | F47: 30 | G47: =VLOOKUP(A47,'All vendors'!B:E,4,0) -> #N/A | H47: =VLOOKUP(A47,'All vendors'!B:E,3,0) -> #N/A | I47: COL-Bogotá | J47: =VLOOKUP(A47,'All vendors'!A:Z,13,0) -> 45730.5 | K47: SC+2500/2024/126 | L47: Transportation | M47: =VLOOKUP(A47,'All vendors'!A:Z,11,0) -> Laura Moreno Ruiz | N47: =VLOOKUP(A47,'All vendors'!A:Z,12,0) -> +573124002631 | O47: =VLOOKUP(A47,'All vendors'!A:Z,15,0) -> laura.moreno@cabify.com | P47: Manuel José Torres | Q47: Banco AV Villas | R47: CABIFY TRANSPORTES S.A.S | S47: Sin Observaciones | T47: 0 | U47: =T47/4000 -> 0 | V47: =VLOOKUP(A47,'All vendors'!A:Z,17,0) -> 999999999 | W47: 0 | Z47: =IF(H47>E47,"No actions","Update ATC") -> #N/A | AA47: =IF(E47<(TODAY()+90),"Send email to SC","No actions") -> Send email to SC | AB47: =IF(E47<=(TODAY()+F47),"Send notification to supplier","No actions") -> No actions | AC47: =IF((E47-D47)>720,W47>0, "No actions") -> No actions | AD47: 999999999 | AE47: 45779
A48: 10050330 | B48: =VLOOKUP(A48,'All vendors'!A:Z,2,0) -> Doinmedia S.A.S | C48: MSA | D48: 45399 | E48: 45793 | F48: 30 | G48: =VLOOKUP(A48,'All vendors'!B:E,4,0) -> #N/A | H48: =VLOOKUP(A48,'All vendors'!B:E,3,0) -> #N/A | I48: COL-Bogotá | J48: =VLOOKUP(A48,'All vendors'!A:Z,13,0) -> 45757.385 | K48: MSA/2024/075 | L48: Audiovisuales | M48: =VLOOKUP(A48,'All vendors'!A:Z,11,0) -> Doris Carolina Guerrero Romero | N48: =VLOOKUP(A48,'All vendors'!A:Z,12,0) -> +6013183272138 | O48: =VLOOKUP(A48,'All vendors'!A:Z,15,0) -> doinmedia@gmail.com | P48: Claudia Patricia Flórez | Q48: Davivienda | R48: Movlife SAS | S48: Sin Observaciones | T48: 0 | U48: =T48/4000 -> 0 | V48: =VLOOKUP(A48,'All vendors'!A:Z,17,0) -> 30000 | W48: 0 | AD48: 30000 | AE48: 45793
A49: 10050376 | B49: =VLOOKUP(A49,'All vendors'!A:Z,2,0) -> Fundación Pacifista | C49: MSA | D49: 45399 | E49: 45793 | F49: 30 | G49: =VLOOKUP(A49,'All vendors'!B:E,4,0) -> #N/A | H49: =VLOOKUP(A49,'All vendors'!B:E,3,0) -> #N/A | I49: COL-Bogotá | J49: =VLOOKUP(A49,'All vendors'!A:Z,13,0) -> 45761.306 | K49: MSA/2024/077 | L49: Audiovisuales | M49: =VLOOKUP(A49,'All vendors'!A:Z,11,0) -> Simon Arenas | N49: =VLOOKUP(A49,'All vendors'!A:Z,12,0) -> 0 | O49: =VLOOKUP(A49,'All vendors'!A:Z,15,0) -> 0 | P49: Claudia Patricia Flórez | Q49: Davivienda | R49: Movlife SAS | S49: Sin Observaciones | T49: 0 | U49: =T49/4000 -> 0 | V49: =VLOOKUP(A49,'All vendors'!A:Z,17,0) -> 30000 | W49: 0 | AD49: 30000 | AE49: 45793
A50: 10000364 | B50: =VLOOKUP(A50,'All vendors'!A:Z,2,0) -> Cooperativa de Transportadores Tax Coopebombas LTDA | C50: Serv Agreem | D50: 45432 | E50: 45806 | F50: 30 | G50: =VLOOKUP(A50,'All vendors'!B:E,4,0) -> #N/A | H50: =VLOOKUP(A50,'All vendors'!B:E,3,0) -> #N/A | I50: COL-Medellín | J50: =VLOOKUP(A50,'All vendors'!A:Z,13,0) -> 45643.688 | K50: SC+2500/2024/128 | L50: Transportation | M50: =VLOOKUP(A50,'All vendors'!A:Z,11,0) -> Sebastian Zapata Restrepo | N50: =VLOOKUP(A50,'All vendors'!A:Z,12,0) -> +57604514243 | O50: =VLOOKUP(A50,'All vendors'!A:Z,15,0) -> 0 | S50: Sin Observaciones | T50: 0 | U50: =T50/4000 -> 0 | V50: =VLOOKUP(A50,'All vendors'!A:Z,17,0) -> 999999999 | W50: 0 | AB50: =IF((E50-D50)>720,V50>0, "No actions") -> No actions | AD50: 999999999 | AE50: 45806
A51: 10000348 | B51: =VLOOKUP(A51,'All vendors'!A:Z,2,0) -> Inversiones Pikachu 77 CA | C51: Serv Agreem | D51: 45097 | E51: 45827 | F51: 30 | G51: =VLOOKUP(A51,'All vendors'!B:E,4,0) -> #N/A | H51: =VLOOKUP(A51,'All vendors'!B:E,3,0) -> #N/A | I51: VEN-Caracas | J51: =VLOOKUP(A51,'All vendors'!A:Z,13,0) -> 45615.636 | K51: SC+2500/2023/087 | L51: Transportation | M51: =VLOOKUP(A51,'All vendors'!A:Z,11,0) -> Carlos Jose Peña Brice | N51: =VLOOKUP(A51,'All vendors'!A:Z,12,0) -> +584142523171 | O51: =VLOOKUP(A51,'All vendors'!A:Z,15,0) -> bricecarlo@gmail.com | P51: Carlos Peña | Q51: PNC Bank, N.A | R51: Camila Valentina Peña | S51: Clausula 9na literal 2 Tope: 20.000 USD | T51: NA | U51: 0 | V51: =VLOOKUP(A51,'All vendors'!A:Z,17,0) -> 999999999 | W51: 0 | Z51: =IF(H51>E51,"No actions","Update ATC") -> #N/A | AA51: =IF(E51<(TODAY()+90),"Send email to SC","No actions") -> No actions | AB51: =IF(E51<=(TODAY()+F51),"Send notification to supplier","No actions") -> No actions | AC51: =IF((E51-D51)>720,W51>0, "No actions") -> FALSE | AD51: 999999999 | AE51: 45827
A52: 10051631 | B52: =VLOOKUP(A52,'All vendors'!A:Z,2,0) -> Carolina García Gonzalez dba Grafik Publimpresos | C52: Purch Agreem | D52: 45474 | E52: 45838 | F52: 30 | G52: =VLOOKUP(A52,'All vendors'!B:E,4,0) -> #N/A | H52: =VLOOKUP(A52,'All vendors'!B:E,3,0) -> #N/A | I52: COL-Bogotá | J52: =VLOOKUP(A52,'All vendors'!A:Z,13,0) -> 45841.594 | K52: SsC+2500//COL-VEN/2024/130 | L52: POP goods | M52: =VLOOKUP(A52,'All vendors'!A:Z,11,0) -> Carolina García Gonzalez | N52: =VLOOKUP(A52,'All vendors'!A:Z,12,0) -> +573005643549 | O52: =VLOOKUP(A52,'All vendors'!A:Z,15,0) -> 0 | P52: Franklin Cardenas | Q52: Bank of America | S52: Tope: 20.000 USD. | T52: 0 | U52: 0 | V52: =VLOOKUP(A52,'All vendors'!A:Z,17,0) -> 19000 | W52: 0 | AD52: 19000 | AE52: 45838
A53: 10000413 | B53: =VLOOKUP(A53,'All vendors'!A:Z,2,0) -> Eco Emprendedores Creativos SAS | C53: Purch Agreem | D53: 45474 | E53: 45838 | F53: 30 | G53: =VLOOKUP(A53,'All vendors'!B:E,4,0) -> #N/A | H53: =VLOOKUP(A53,'All vendors'!B:E,3,0) -> #N/A | I53: COL-Bogotá | J53: =VLOOKUP(A53,'All vendors'!A:Z,13,0) -> 45854.323 | K53: SsC+2500//COL-VEN/2024/131 | L53: POP goods | M53: =VLOOKUP(A53,'All vendors'!A:Z,11,0) -> Juan Camilo Aragon Meneses | N53: =VLOOKUP(A53,'All vendors'!A:Z,12,0) -> +573108830067 | O53: =VLOOKUP(A53,'All vendors'!A:Z,15,0) -> gerencia@ecoemprendedorescreativos.co | P53: Franklin Cardenas | Q53: Bank of America | S53: Tope: 20.000 USD. | T53: 0 | U53: 0 | V53: =VLOOKUP(A53,'All vendors'!A:Z,17,0) -> 999999999 | W53: 0 | AD53: 999999999 | AE53: 45838
A54: 10020247 | B54: =VLOOKUP(A54,'All vendors'!A:Z,2,0) -> Rutas E Inversiones F.C | C54: Serv Agreem | D54: 45475 | E54: 45839 | F54: 30 | G54: =VLOOKUP(A54,'All vendors'!B:E,4,0) -> #N/A | H54: =VLOOKUP(A54,'All vendors'!B:E,3,0) -> #N/A | I54: VEN-San Cristobal | J54: =VLOOKUP(A54,'All vendors'!A:Z,13,0) -> 45616.59 | K54: SsC+2500//COL-VEN/2024/133 | L54: Transportation | M54: =VLOOKUP(A54,'All vendors'!A:Z,11,0) -> Franklyn Fernando Cárdenas Díaz | N54: =VLOOKUP(A54,'All vendors'!A:Z,12,0) -> +584149777910 | O54: =VLOOKUP(A54,'All vendors'!A:Z,15,0) -> dag42a2009@gmail.com | P54: Franklin Cardenas | Q54: Bank of America | S54: Tope: 20.000 USD. | T54: 0 | U54: 0 | V54: =VLOOKUP(A54,'All vendors'!A:Z,17,0) -> 999999999 | W54: 0 | Z54: =IF(H54>E54,"No actions","Update ATC") -> #N/A | AA54: =IF(E54<(TODAY()+90),"Send email to SC","No actions") -> No actions | AB54: =IF(E54<=(TODAY()+F54),"Send notification to supplier","No actions") -> No actions | AC54: =IF((E54-D54)>720,W54>0, "No actions") -> No actions | AD54: 999999999 | AE54: 45839
A55: 10050483 | B55: =VLOOKUP(A55,'All vendors'!A:Z,2,0) -> Distribuidora Avila Care, C.A | C55: Purch Agreem | D55: 45498 | E55: 45868 | F55: 30 | G55: =VLOOKUP(A55,'All vendors'!B:E,4,0) -> #N/A | H55: =VLOOKUP(A55,'All vendors'!B:E,3,0) -> #N/A | I55: VEN-Caracas | J55: =VLOOKUP(A55,'All vendors'!A:Z,13,0) -> 45880.292 | K55: MPA/COL-VEN/2024/037 | L55: Pharma | M55: =VLOOKUP(A55,'All vendors'!A:Z,11,0) -> JULIO CESAR SALAZAR | N55: =VLOOKUP(A55,'All vendors'!A:Z,12,0) -> +584127381235 | O55: =VLOOKUP(A55,'All vendors'!A:Z,15,0) -> info.avilacare@gmail.com | P55: Franklin Cardenas | Q55: Bank of America | S55: Tope: 20.000 USD. | T55: 0 | U55: 0 | V55: =VLOOKUP(A55,'All vendors'!A:Z,17,0) -> 999999 | W55: 0 | AD55: 999999 | AE55: 45868
A56: 10047642 | B56: =VLOOKUP(A56,'All vendors'!A:Z,2,0) -> Global Business Soluciones Empresariales C.A | C56: Purch Agreem | D56: 45498 | E56: 45868 | F56: 30 | G56: =VLOOKUP(A56,'All vendors'!B:E,4,0) -> #N/A | H56: =VLOOKUP(A56,'All vendors'!B:E,3,0) -> #N/A | I56: VEN-Caracas | J56: =VLOOKUP(A56,'All vendors'!A:Z,13,0) -> 45776.358 | K56: MPA/COL-VEN/2024/039 | L56: Pharma | M56: =VLOOKUP(A56,'All vendors'!A:Z,11,0) -> Tiffany Roslin Rodriguez Nunez | N56: =VLOOKUP(A56,'All vendors'!A:Z,12,0) -> +584145441037 | O56: =VLOOKUP(A56,'All vendors'!A:Z,15,0) -> global99soluciones@gmail.com | P56: Franklin Cardenas | Q56: Bank of America | S56: Tope: 20.000 USD. | T56: 0 | U56: 0 | V56: =VLOOKUP(A56,'All vendors'!A:Z,17,0) -> 200000 | W56: 0 | AD56: 200000 | AE56: 45868
A57: 10050484 | B57: =VLOOKUP(A57,'All vendors'!A:Z,2,0) -> Drogueria Y Suministros Drofarzuca C.A. | C57: Purch Agreem | D57: 45498 | E57: 45868 | F57: 30 | G57: =VLOOKUP(A57,'All vendors'!B:E,4,0) -> #N/A | H57: =VLOOKUP(A57,'All vendors'!B:E,3,0) -> #N/A | I57: VEN-Caracas | J57: =VLOOKUP(A57,'All vendors'!A:Z,13,0) -> 45768.715 | K57: MPA/COL-VEN/2024/038 | L57: Pharma | M57: =VLOOKUP(A57,'All vendors'!A:Z,11,0) -> Eleazar Alfonso Gonzalez Gonzalez | N57: =VLOOKUP(A57,'All vendors'!A:Z,12,0) -> +584121261393 | O57: =VLOOKUP(A57,'All vendors'!A:Z,15,0) -> Drofarzuca@Gmail.Com | P57: Franklin Cardenas | Q57: Bank of America | S57: Tope: 20.000 USD. | T57: 0 | U57: 0 | V57: =VLOOKUP(A57,'All vendors'!A:Z,17,0) -> 999999 | W57: 0 | Z57: =IF(H57>E57,"No actions","Update ATC") -> #N/A | AA57: =IF(E57<(TODAY()+90),"Send email to SC","No actions") -> No actions | AB57: =IF(E57<=(TODAY()+F57),"Send notification to supplier","No actions") -> No actions | AC57: =IF((E57-D57)>720,W57>0, "No actions") -> No actions | AD57: 999999 | AE57: 45868
A58: 10047942 | B58: =VLOOKUP(A58,'All vendors'!A:Z,2,0) -> Grupo Allmed C.A | C58: Purch Agreem | D58: 45498 | E58: 45868 | F58: 30 | G58: =VLOOKUP(A58,'All vendors'!B:E,4,0) -> #N/A | H58: =VLOOKUP(A58,'All vendors'!B:E,3,0) -> #N/A | I58: VEN-Caracas | J58: =VLOOKUP(A58,'All vendors'!A:Z,13,0) -> 45853.379 | K58: MPA/COL-VEN/2024/040 | L58: Pharma | M58: =VLOOKUP(A58,'All vendors'!A:Z,11,0) -> Yossue Alejandro García Berroterán | N58: =VLOOKUP(A58,'All vendors'!A:Z,12,0) -> +5804142346402 | O58: =VLOOKUP(A58,'All vendors'!A:Z,15,0) -> y.garcia@grupoallmed.com | P58: Franklin Cardenas | Q58: Bank of America | S58: Tope: 20.000 USD. | T58: 0 | U58: 0 | V58: =VLOOKUP(A58,'All vendors'!A:Z,17,0) -> 200000 | W58: 0 | Z58: =IF(H58>E58,"No actions","Update ATC") -> #N/A | AA58: =IF(E58<(TODAY()+90),"Send email to SC","No actions") -> No actions | AB58: =IF(E58<=(TODAY()+F58),"Send notification to supplier","No actions") -> No actions | AC58: =IF((E58-D58)>720,W58>0, "No actions") -> No actions | AD58: 200000 | AE58: 45868
A59: 10021800 | B59: =VLOOKUP(A59,'All vendors'!A:Z,2,0) -> Soluciones y Servicios 2019 C.A. | C59: Serv Agreem | D59: 45139 | E59: 45869 | F59: 30 | G59: =VLOOKUP(A59,'All vendors'!B:E,4,0) -> #N/A | H59: =VLOOKUP(A59,'All vendors'!B:E,3,0) -> #N/A | I59: VEN-Caracas | J59: =VLOOKUP(A59,'All vendors'!A:Z,13,0) -> 45646.667 | K59: SC+2500/2023/067 | L59: Cleaning services | M59: =VLOOKUP(A59,'All vendors'!A:Z,11,0) -> Jairo José Salinas González | N59: =VLOOKUP(A59,'All vendors'!A:Z,12,0) -> +584141386857 | O59: =VLOOKUP(A59,'All vendors'!A:Z,15,0) -> solucionesserviciosca2019@gmail.com | S59: Tope: 20.000 USD | T59: NA | U59: 0 | V59: =VLOOKUP(A59,'All vendors'!A:Z,17,0) -> 999999999 | W59: 0 | AD59: 999999999 | AE59: 45869
A60: 10005332 | B60: =VLOOKUP(A60,'All vendors'!A:Z,2,0) -> Maso Tourism International LLC | C60: Serv Agreem | D60: 45139 | E60: 45869 | F60: 30 | G60: =VLOOKUP(A60,'All vendors'!B:E,4,0) -> #N/A | H60: =VLOOKUP(A60,'All vendors'!B:E,3,0) -> #N/A | I60: VEN-Caracas | J60: =VLOOKUP(A60,'All vendors'!A:Z,13,0) -> 45784.695 | K60: SC+2500/2023/072 | L60: Travel Agency | M60: =VLOOKUP(A60,'All vendors'!A:Z,11,0) -> Albania Arraez | N60: =VLOOKUP(A60,'All vendors'!A:Z,12,0) -> +582122776284 | O60: =VLOOKUP(A60,'All vendors'!A:Z,15,0) -> aarraez@turismomaso.com | P60: Daniela castro, Albania arráez | Q60: Face Bank International | R60: Maso Tourisim International | S60: Tope: 20.000 USD | T60: NA | U60: 0 | V60: =VLOOKUP(A60,'All vendors'!A:Z,17,0) -> 999999999 | W60: 0 | Z60: =IF(H60>E60,"No actions","Update ATC") -> #N/A | AA60: =IF(E60<(TODAY()+90),"Send email to SC","No actions") -> No actions | AB60: =IF(E60<=(TODAY()+F60),"Send notification to supplier","No actions") -> No actions | AC60: =IF((E60-D60)>720,W60>0, "No actions") -> FALSE | AD60: 999999999 | AE60: 45869
A61: 10000527 | B61: =VLOOKUP(A61,'All vendors'!A:Z,2,0) -> Rio Technology SAS- En Reorganizacion | C61: MPA | D61: 45536 | E61: 45900 | F61: 30 | G61: =VLOOKUP(A61,'All vendors'!B:E,4,0) -> #N/A | H61: =VLOOKUP(A61,'All vendors'!B:E,3,0) -> #N/A | I61: COL-Bogotá | J61: =VLOOKUP(A61,'All vendors'!A:Z,13,0) -> 45908.16 | K61: MPA/COL-VEN/2024/036 | L61: Technology | M61: =VLOOKUP(A61,'All vendors'!A:Z,11,0) -> Jorge Enrique Gómez Parra | N61: =VLOOKUP(A61,'All vendors'!A:Z,12,0) -> +576018966650 | O61: =VLOOKUP(A61,'All vendors'!A:Z,15,0) -> jorge.gomez@riotechnology.com.co | P61: Daniela castro, Albania arráez | Q61: Face Bank International | R61: Maso Tourisim International | S61: Tope: 20.000 USD | T61: NA | U61: 0 | V61: =VLOOKUP(A61,'All vendors'!A:Z,17,0) -> 999999999 | W61: 0 | AD61: 999999999 | AE61: 45900
A62: 10000404 | B62: =VLOOKUP(A62,'All vendors'!A:Z,2,0) -> Coordinandora Mercantil SA | C62: MSA | D62: 44378 | E62: 45900 | F62: 30 | G62: =VLOOKUP(A62,'All vendors'!B:E,4,0) -> #N/A | H62: =VLOOKUP(A62,'All vendors'!B:E,3,0) -> #N/A | I62: COL-Bogotá | J62: =VLOOKUP(A62,'All vendors'!A:Z,13,0) -> 45653.125 | K62: MSA/2021/031 | L62: Shipping Services | M62: =VLOOKUP(A62,'All vendors'!A:Z,11,0) -> Carolina Fuquen | N62: =VLOOKUP(A62,'All vendors'!A:Z,12,0) -> +573017591015 | O62: =VLOOKUP(A62,'All vendors'!A:Z,15,0) -> carolina@coordinadora.com | P62: Jesús Cárdenas | Q62: Bancolombia | R62: COORDINADORA MERCANTIL SA | S62: Se renueva automáticamente. Se firmo una Negociacion Rescue 2024-2025 | T62: 0 | U62: =T62/4000 -> 0 | V62: =VLOOKUP(A62,'All vendors'!A:Z,17,0) -> 999999999 | W62: 0 | Z62: =IF(H62>E62,"No actions","Update ATC") -> #N/A | AA62: =IF(E62<(TODAY()+90),"Send email to SC","No actions") -> No actions | AB62: =IF(E62<=(TODAY()+F62),"Send notification to supplier","No actions") -> No actions | AC62: =IF((E62-D62)>720,W62>0, "No actions") -> FALSE | AD62: 999999999 | AE62: 45900
A63: 10040286 | B63: =VLOOKUP(A63,'All vendors'!A:Z,2,0) -> Yummy Rides, C.A. | C63: Serv Agreem | D63: 45187 | E63: 45917 | F63: 30 | G63: =VLOOKUP(A63,'All vendors'!B:E,4,0) -> #N/A | H63: =VLOOKUP(A63,'All vendors'!B:E,3,0) -> #N/A | I63: VEN-Caracas | J63: =VLOOKUP(A63,'All vendors'!A:Z,13,0) -> 45881.296 | K63: SC+2500/2023/103 | L63: Transportation | M63: =VLOOKUP(A63,'All vendors'!A:Z,11,0) -> Ronald Mario Gonzalez Soto | N63: =VLOOKUP(A63,'All vendors'!A:Z,12,0) -> +584123922108 | O63: =VLOOKUP(A63,'All vendors'!A:Z,15,0) -> ronald.soto@yummysuperapp.com | P63: Mercedez Espinoza | S63: Tope: 20.000 USD En proceso de renovación | T63: NA | U63: 0 | V63: =VLOOKUP(A63,'All vendors'!A:Z,17,0) -> 50000 | W63: 0 | Z63: =IF(H63>E63,"No actions","Update ATC") -> #N/A | AA63: =IF(E63<(TODAY()+90),"Send email to SC","No actions") -> No actions | AB63: =IF(E63<=(TODAY()+F63),"Send notification to supplier","No actions") -> No actions | AC63: =IF((E63-D63)>720,W63>0, "No actions") -> FALSE | AD63: 50000 | AE63: 45917
A64: 10035655 | B64: =VLOOKUP(A64,'All vendors'!A:Z,2,0) -> Bancolombia S.A | C64: MSA | D64: 45176 | E64: 46272 | F64: 90 | G64: =VLOOKUP(A64,'All vendors'!B:E,4,0) -> #N/A | H64: =VLOOKUP(A64,'All vendors'!B:E,3,0) -> #N/A | I64: COL-Bogotá | J64: =VLOOKUP(A64,'All vendors'!A:Z,13,0) -> 45806.413 | K64: MSA/2023/064 | L64: Office Rental | M64: =VLOOKUP(A64,'All vendors'!A:Z,11,0) -> Christian Julian Luna Rodriguez | N64: =VLOOKUP(A64,'All vendors'!A:Z,12,0) -> +573203914797 | O64: =VLOOKUP(A64,'All vendors'!A:Z,15,0) -> chluna@bancolombia.com.co | P64: Jose Zubillaga | Q64: Bank of America | R64: 15 de agosto SC, LLC | S64: Sin Observaciones | T64: 0 | U64: =T64/4000 -> 0 | V64: =VLOOKUP(A64,'All vendors'!A:Z,17,0) -> 999999999 | W64: 0 | Z64: =IF(H64>E64,"No actions","Update ATC") -> #N/A | AA64: =IF(E64<(TODAY()+90),"Send email to SC","No actions") -> No actions | AB64: =IF(E64<=(TODAY()+F64),"Send notification to supplier","No actions") -> No actions | AC64: =IF((E64-D64)>720,W64>0, "No actions") -> FALSE | AD64: 999999999 | AE64: 46272
A65: 10000520 | B65: =VLOOKUP(A65,'All vendors'!A:Z,2,0) -> Efectivo Limitada | C65: MSA | D65: 45184 | E65: 46279 | F65: 30 | G65: =VLOOKUP(A65,'All vendors'!B:E,4,0) -> #N/A | H65: =VLOOKUP(A65,'All vendors'!B:E,3,0) -> #N/A | I65: COL-Bogotá | J65: =VLOOKUP(A65,'All vendors'!A:Z,13,0) -> 45779.688 | K65: MSA/2023/065 | L65: Cash Services | M65: =VLOOKUP(A65,'All vendors'!A:Z,11,0) -> Paula Carolina Parra Bernal | N65: =VLOOKUP(A65,'All vendors'!A:Z,12,0) -> +573183900021 | O65: =VLOOKUP(A65,'All vendors'!A:Z,15,0) -> notificaciones@efecty.com.co | P65: Ludivia Posada Valencia | Q65: Bancolombia | R65: EFECTIVO LTDA | S65: Sin Observaciones | T65: 0 | U65: =T65/4000 -> 0 | V65: =VLOOKUP(A65,'All vendors'!A:Z,17,0) -> 999999999 | W65: 0 | Z65: =IF(H65>E65,"No actions","Update ATC") -> #N/A | AA65: =IF(E65<(TODAY()+90),"Send email to SC","No actions") -> No actions | AB65: =IF(E65<=(TODAY()+F65),"Send notification to supplier","No actions") -> No actions | AC65: =IF((E65-D65)>720,W65>0, "No actions") -> FALSE | AD65: 999999999 | AE65: 46279
A66: 10000446 | B66: =VLOOKUP(A66,'All vendors'!A:Z,2,0) -> Sebastian Cardona Fernandez | C66: Serv Agreem | D66: 45553 | E66: 45917 | F66: 30 | G66: =VLOOKUP(A66,'All vendors'!B:E,4,0) -> #N/A | H66: =VLOOKUP(A66,'All vendors'!B:E,3,0) -> #N/A | I66: COL-Cúcuta | J66: =VLOOKUP(A66,'All vendors'!A:Z,13,0) -> 45658.709 | K66: MPA/COL-VEN/2024/136 | L66: POP goods | M66: =VLOOKUP(A66,'All vendors'!A:Z,11,0) -> Sebastian Cardona Fernandez | N66: =VLOOKUP(A66,'All vendors'!A:Z,12,0) -> +573045241325 | O66: =VLOOKUP(A66,'All vendors'!A:Z,15,0) -> serviciosaulacf@gmail.com | P66: Ludivia Posada Valencia | Q66: Bancolombia | R66: EFECTIVO LTDA | S66: Tope: 76.00.000,00 COP | T66: 0 | U66: =T66/4000 -> 0 | V66: =VLOOKUP(A66,'All vendors'!A:Z,17,0) -> 999999999 | W66: 0 | Z66: =IF(H66>E66,"No actions","Update ATC") -> #N/A | AA66: =IF(E66<(TODAY()+90),"Send email to SC","No actions") -> No actions | AB66: =IF(E66<=(TODAY()+F66),"Send notification to supplier","No actions") -> No actions | AC66: =IF((E66-D66)>720,W66>0, "No actions") -> No actions | AD66: 999999999 | AE66: 45917
A67: 10000399 | B67: =VLOOKUP(A67,'All vendors'!A:Z,2,0) -> Corporacion Vinculos | C67: Serv Agreem | D67: 45189 | E67: 45919 | F67: 30 | G67: =VLOOKUP(A67,'All vendors'!B:E,4,0) -> #N/A | H67: =VLOOKUP(A67,'All vendors'!B:E,3,0) -> #N/A | I67: COL-Bogotá | J67: =VLOOKUP(A67,'All vendors'!A:Z,13,0) -> 45853.65 | K67: SC+2500/2023/102 | L67: Coaching Services | M67: =VLOOKUP(A67,'All vendors'!A:Z,11,0) -> Mariana Saenz Uribe | N67: =VLOOKUP(A67,'All vendors'!A:Z,12,0) -> +573108071828 | O67: =VLOOKUP(A67,'All vendors'!A:Z,15,0) -> corporacionvinculos@corporacionvinculos.com | P67: Mariana Saenz | Q67: Banco de Bogotá | R67: Corporación Vínculos | S67: Tope: 20.000 USD. Tiene 1 enmienda | T67: 0 | U67: =T67/4000 -> 0 | V67: =VLOOKUP(A67,'All vendors'!A:Z,17,0) -> 999999999 | W67: 0 | Z67: =IF(H67>E67,"No actions","Update ATC") -> #N/A | AA67: =IF(E67<(TODAY()+90),"Send email to SC","No actions") -> No actions | AB67: =IF(E67<=(TODAY()+F67),"Send notification to supplier","No actions") -> No actions | AC67: =IF((E67-D67)>720,W67>0, "No actions") -> FALSE | AD67: 999999999 | AE67: 45919
A68: 10016130 | B68: =VLOOKUP(A68,'All vendors'!A:Z,2,0) -> Vanes del Valle S.A.S | C68: Serv Agreem | D68: 45573 | E68: 45938 | F68: 30 | G68: =VLOOKUP(A68,'All vendors'!B:E,4,0) -> #N/A | H68: =VLOOKUP(A68,'All vendors'!B:E,3,0) -> #N/A | I68: COL-Cali | J68: =VLOOKUP(A68,'All vendors'!A:Z,13,0) -> 45869.399 | K68: SsC+2500//COL-VEN/2024/136 | L68: Transportation | M68: =VLOOKUP(A68,'All vendors'!A:Z,11,0) -> Leonardo Esteban Ordoñez Galvis | N68: =VLOOKUP(A68,'All vendors'!A:Z,12,0) -> +573165383777 | O68: =VLOOKUP(A68,'All vendors'!A:Z,15,0) -> comercial@vanesdelvalle.com | P68: Robison Vega | Q68: Bancolombia | R68: Vanes del Valle SAS | S68: Sin Observaciones | T68: 0 | U68: =T68/4000 -> 0 | V68: =VLOOKUP(A68,'All vendors'!A:Z,17,0) -> 999999999 | W68: 0 | Z68: =IF(H68>E68,"No actions","Update ATC") -> #N/A | AA68: =IF(E68<(TODAY()+90),"Send email to SC","No actions") -> No actions | AB68: =IF(E68<=(TODAY()+F68),"Send notification to supplier","No actions") -> No actions | AC68: =IF((E68-D68)>720,W68>0, "No actions") -> No actions | AD68: 999999999 | AE68: 45938
A69: 10021009 | B69: =VLOOKUP(A69,'All vendors'!A:Z,2,0) -> Quality Transportes S.A.S | C69: Serv Agreem | D69: 45586 | E69: 45955 | F69: 30 | G69: =VLOOKUP(A69,'All vendors'!B:E,4,0) -> #N/A | H69: =VLOOKUP(A69,'All vendors'!B:E,3,0) -> #N/A | I69: COL-Cúcuta | J69: =VLOOKUP(A69,'All vendors'!A:Z,13,0) -> 0 | K69: SsC+2500//COL-VEN/2024/132 | L69: Transportation | M69: =VLOOKUP(A69,'All vendors'!A:Z,11,0) -> Victor Hugo Marin Diaz | N69: =VLOOKUP(A69,'All vendors'!A:Z,12,0) -> +573178675686 | O69: =VLOOKUP(A69,'All vendors'!A:Z,15,0) -> Gerenciaqualitytransportes@gmail.com | P69: Robison Vega | Q69: Bancolombia | R69: Vanes del Valle SAS | S69: Sin Observaciones | T69: 0 | U69: =T69/4000 -> 0 | V69: =VLOOKUP(A69,'All vendors'!A:Z,17,0) -> 2400 | W69: 0 | AD69: 2400 | AE69: 45955
A70: 10000521 | B70: =VLOOKUP(A70,'All vendors'!A:Z,2,0) -> Egor Rent A Car S.A.S | C70: Serv Agreem | D70: 44974 | E70: 45338 | F70: 30 | G70: =VLOOKUP(A70,'All vendors'!B:E,4,0) -> #N/A | H70: =VLOOKUP(A70,'All vendors'!B:E,3,0) -> #N/A | I70: COL-Bogotá | J70: =VLOOKUP(A70,'All vendors'!A:Z,13,0) -> 45792.619 | K70: SsC-2500-2023-026 | L70: Transportation | M70: =VLOOKUP(A70,'All vendors'!A:Z,11,0) -> Ediberto Gordillo Alvarez | N70: =VLOOKUP(A70,'All vendors'!A:Z,12,0) -> +573106662972 | O70: =VLOOKUP(A70,'All vendors'!A:Z,15,0) -> egordillo@hotmail.com | P70: Edilberto Gordillo | S70: Tope: 11.904.750,00 COP | T70: 0 | U70: =T70/4000 -> 0 | V70: =VLOOKUP(A70,'All vendors'!A:Z,17,0) -> 999999999 | W70: 0 | Z70: =IF(H70>E70,"No actions","Update ATC") -> #N/A | AA70: =IF(E70<(TODAY()+90),"Send email to SC","No actions") -> Send email to SC | AB70: =IF(E70<=(TODAY()+F70),"Send notification to supplier","No actions") -> Send notification to supplier | AC70: =IF((E70-D70)>720,W70>0, "No actions") -> No actions | AD70: 999999999 | AE70: 45338

Sheet Contracted Suppliers_Closed
B1: Contracted Supplier Tracking Sheet
B3: COLOMBIA - VENEZUELA
A4: Vendor account | B4: Supplier name | C4: Type of contract | D4: Contract Start Date | E4: Contract End Date | F4: Notice date (days) | G4: ATC status | H4: ATC clearance expiration date | I4: Site | J4: ATC | K4: Contract Reference | L4: Category of Goods or Services | M4: Contact Person | N4: Contact Phone/Fax Numbers | O4: Contact Email Address | P4: Ownership or Leadership Information | Q4: Name of Financial Institution (for bank-to-bank transactations only) | R4: Name of Account Holder (for bank-to-bank transactations only) | S4: Notes | T4: TOPE EN DOLARES | U4: Valor Gastado | V4: Number of Amendments | W4: Valor gastado USD | Y4: ATC | Z4: Notification to SC | AA4: Notification to Supplier | AB4: Amendments
A5: 10016768 | B5: =VLOOKUP(A5,'All vendors'!A:Z,2,0) -> Comercializadora Surtiempresa SAS | C5: Purch Agreem | D5: 44846 | E5: 45574 | F5: 5 | G5: =VLOOKUP(A5,'All vendors'!B:E,4,0) -> #N/A | H5: =VLOOKUP(A5,'All vendors'!B:E,3,0) -> #N/A | I5: COL-Bogotá | J5: =VLOOKUP(A5,'All vendors'!A:Z,13,0) -> 45859.428 | K5: SC+2500/2022/041 | L5: Purchase of goods | M5: =VLOOKUP(A5,'All vendors'!A:Z,11,0) -> Yeymy Sánchez Suárez | N5: =VLOOKUP(A5,'All vendors'!A:Z,12,0) -> +573133175241 | O5: =VLOOKUP(A5,'All vendors'!A:Z,15,0) -> comercial@surtimpresa.com | P5: Yeymy Lucena Sánchez Suárez | Q5: Banco Caja Social | R5: Comercializadora Surtiempresa SAS | S5: Tope: 20.000 USD. Se realizara un proceso nuevo | T5: 20000 | U5: 56532751 | V5: 0 | W5: =VLOOKUP(A5,'All vendors'!A:Z,17,0) -> 999999999 | X5: 1 | AA5: =IF(H5>E5,"No actions","Update ATC") -> #N/A | AB5: =IF(E5<(TODAY()+90),"Send email to SC","No actions") -> Send email to SC | AC5: =IF(E5<=(TODAY()+F5),"Send notification to supplier","No actions") -> Send notification to supplier | AD5: =IF((E5-D5)>720,X5>0, "No actions") -> TRUE
A6: 10050145 | B6: =VLOOKUP(A6,'All vendors'!A:Z,2,0) -> Julio Bermudez | C6: Serv Agreem | D6: 45385 | E6: 45576 | F6: 30 | G6: =VLOOKUP(A6,'All vendors'!B:E,4,0) -> #N/A | H6: =VLOOKUP(A6,'All vendors'!B:E,3,0) -> #N/A | I6: VEN-Caracas | J6: =VLOOKUP(A6,'All vendors'!A:Z,13,0) -> 45740.678 | K6: Sin Numero | L6: Dotación | M6: =VLOOKUP(A6,'All vendors'!A:Z,11,0) -> Julio Bermudez | N6: =VLOOKUP(A6,'All vendors'!A:Z,12,0) -> +584120120225 | O6: =VLOOKUP(A6,'All vendors'!A:Z,15,0) -> intertono@hotmail.com | P6: Claudia Patricia Flórez | Q6: Davivienda | R6: Movlife SAS | S6: Tope: 6.912,05 USD. No se renovara | T6: 6912.05 | U6: 0 | V6: 0 | W6: =VLOOKUP(A6,'All vendors'!A:Z,17,0) -> 14000 | X6: 0
A7: 10036870 | B7: =VLOOKUP(A7,'All vendors'!A:Z,2,0) -> Comercializadora Femavi S.A.S. | C7: Purch Agreem | D7: 45189 | E7: 45554 | F7: 30 | G7: =VLOOKUP(A7,'All vendors'!B:E,4,0) -> #N/A | H7: =VLOOKUP(A7,'All vendors'!B:E,3,0) -> #N/A | I7: COL-Bogotá | J7: =VLOOKUP(A7,'All vendors'!A:Z,13,0) -> 45700.473 | K7: SC+2500/2023/101 | L7: POP goods | M7: =VLOOKUP(A7,'All vendors'!A:Z,11,0) -> Victor Bohada | N7: =VLOOKUP(A7,'All vendors'!A:Z,12,0) -> +573102924522 | O7: =VLOOKUP(A7,'All vendors'!A:Z,15,0) -> victorbohada@femavi.com.co | S7: Tope: 20.000 USD. El contrato terminará, hay dos contratos en firma para reemplazarlo | T7: 20000 | U7: =495000+17068735 -> 17563735 | V7: 0 | W7: =VLOOKUP(A7,'All vendors'!A:Z,17,0) -> 20000 | X7: 0 | AA7: =IF(H7>E7,"No actions","Update ATC") -> #N/A | AB7: =IF(E7<(TODAY()+90),"Send email to SC","No actions") -> Send email to SC | AC7: =IF(E7<=(TODAY()+F7),"Send notification to supplier","No actions") -> Send notification to supplier | AD7: =IF((E7-D7)>720,X7>0, "No actions") -> No actions
A8: 10002985 | B8: =VLOOKUP(A8,'All vendors'!A:Z,2,0) -> Interamericana De Auditores Y Consultores Ltda | C8: Serv Agreem | D8: 45447 | E8: 45510 | F8: 30 | G8: =VLOOKUP(A8,'All vendors'!B:E,4,0) -> #N/A | H8: =VLOOKUP(A8,'All vendors'!B:E,3,0) -> #N/A | I8: COL-Bogotá | J8: =VLOOKUP(A8,'All vendors'!A:Z,13,0) -> 45769.466 | K8: SC+2500/2024/123 | L8: Auditoria | M8: =VLOOKUP(A8,'All vendors'!A:Z,11,0) -> Jose Luis Cruz Blanco | N8: =VLOOKUP(A8,'All vendors'!A:Z,12,0) -> +573102986541 | O8: =VLOOKUP(A8,'All vendors'!A:Z,15,0) -> director@interamericana.co | P8: Edilberto Gordillo | S8: Tope: 11.904.750,00 COP. En proceso de renovación | T8: =11904750/4000 -> 2976.1875 | U8: 1980000 | V8: 0 | W8: =VLOOKUP(A8,'All vendors'!A:Z,17,0) -> 20000 | X8: 0 | AA8: =IF(H8>E8,"No actions","Update ATC") -> #N/A | AB8: =IF(E8<(TODAY()+90),"Send email to SC","No actions") -> Send email to SC | AC8: =IF(E8<=(TODAY()+F8),"Send notification to supplier","No actions") -> Send notification to supplier | AD8: =IF((E8-D8)>720,X8>0, "No actions") -> No actions
A9: 10026142 | B9: =VLOOKUP(A9,'All vendors'!A:Z,2,0) -> Institucion Prestadora de Servicios de Salud Domiciliarios Sanarte Clinica de Heridas y Ostomias S.A | C9: Serv Agreem | D9: 44977 | E9: 45341 | F9: 30 | G9: =VLOOKUP(A9,'All vendors'!B:E,4,0) -> #N/A | H9: =VLOOKUP(A9,'All vendors'!B:E,3,0) -> #N/A | I9: COL-Cúcuta | J9: =VLOOKUP(A9,'All vendors'!A:Z,13,0) -> 45329.129 | K9: SsC-2500//2023/023 | L9: Health ( Ambulance service) | M9: =VLOOKUP(A9,'All vendors'!A:Z,11,0) -> Beatriz Adriana Villamizar Sarmiento | N9: =VLOOKUP(A9,'All vendors'!A:Z,12,0) -> +575922778 | O9: =VLOOKUP(A9,'All vendors'!A:Z,15,0) -> ipssanarte@gmail.com | P9: Beatriz Villamizar | Q9: Bancolombia | R9: SANARTE SAS | S9: Dayana: se tramitará carta de culminación anticipada ya que este servicio de ambulancia no fue utilizado. Fecha finalización 19-02-2024 Y/O HASTA EL AGOTAMIENTO DE LOS RECURSOS Costo de los servicios: HASTA LA SUMA DE $4.000.000. A la fecha 26/01/2024 no se ha gastado nada. | T9: 0 | U9: 0 | V9: 0 | Y9: =IF(H9>E9,"No actions","Update ATC") -> #N/A | Z9: =IF(E9<(TODAY()+90),"Send email to SC","No actions") -> Send email to SC | AA9: =IF(E9<=(TODAY()+F9),"Send notification to supplier","No actions") -> Send notification to supplier | AB9: =IF((E9-D9)>720,V9>0, "No actions") -> No actions
A10: 10000522 | B10: =VLOOKUP(A10,'All vendors'!A:Z,2,0) -> Freedomcenter S.A.S | C10: Serv Agreem | D10: 45061 | E10: 45351 | F10: 5 | G10: =VLOOKUP(A10,'All vendors'!B:E,4,0) -> #N/A | H10: =VLOOKUP(A10,'All vendors'!B:E,3,0) -> #N/A | I10: COL-Bogotá | J10: =VLOOKUP(A10,'All vendors'!A:Z,13,0) -> 45810.038 | K10: SC+2500/2023/081 | L10: Education Data collection | M10: =VLOOKUP(A10,'All vendors'!A:Z,11,0) -> Olga Paola Vargas Lopez | N10: =VLOOKUP(A10,'All vendors'!A:Z,12,0) -> +573113751223 | O10: =VLOOKUP(A10,'All vendors'!A:Z,15,0) -> contacto@freedomcenter.com.co | S10: Waiver firmado | T10: 0 | U10: =28498506.75+107288496+135787002.75 -> 2.7157401e+08 | V10: 0 | Y10: =IF(H10>E10,"No actions","Update ATC") -> #N/A | Z10: =IF(E10<(TODAY()+90),"Send email to SC","No actions") -> Send email to SC | AA10: =IF(E10<=(TODAY()+F10),"Send notification to supplier","No actions") -> Send notification to supplier | AB10: =IF((E10-D10)>720,V10>0, "No actions") -> No actions
A11: 10020995 | B11: =VLOOKUP(A11,'All vendors'!A:Z,2,0) -> Global Safe Salud S.A.S | C11: Serv Agreem | D11: 44986 | E11: 45351 | F11: 5 | G11: =VLOOKUP(A11,'All vendors'!B:E,4,0) -> #N/A | H11: =VLOOKUP(A11,'All vendors'!B:E,3,0) -> #N/A | I11: COL-Cúcuta | J11: =VLOOKUP(A11,'All vendors'!A:Z,13,0) -> 45329.448 | K11: SsC-2500//2023/024 | L11: Ambulance service | M11: =VLOOKUP(A11,'All vendors'!A:Z,11,0) -> Rafael Stiven Parada Dominguez | N11: =VLOOKUP(A11,'All vendors'!A:Z,12,0) -> 0 | O11: =VLOOKUP(A11,'All vendors'!A:Z,15,0) -> contratacion.globalsalud@gmail.com | P11: Lucy del Socorro Peinado | Q11: Banco de Bogotá | R11: GLOBAL SAFE SALUD SAS | S11: Dayana: se tramitará carta de culminación anticipada ya que este servicio de ambulancia no fue utilizado. Fecha finalización 29-02-2024 Y/O HASTA EL AGOTAMIENTO DE LOS RECURSOS Costo de los servicios: HASTA LA SUMA DE $4.000.000. | T11: 0 | U11: 200000 | V11: 0 | Y11: =IF(H11>E11,"No actions","Update ATC") -> #N/A | Z11: =IF(E11<(TODAY()+90),"Send email to SC","No actions") -> Send email to SC | AA11: =IF(E11<=(TODAY()+F11),"Send notification to supplier","No actions") -> Send notification to supplier | AB11: =IF((E11-D11)>720,V11>0, "No actions") -> No actions
A12: 10000402 | B12: =VLOOKUP(A12,'All vendors'!A:Z,2,0) -> Tigers Job Ltda | C12: MSA | D12: 44348 | E12: 45360 | F12: 30 | G12: =VLOOKUP(A12,'All vendors'!B:E,4,0) -> #N/A | H12: =VLOOKUP(A12,'All vendors'!B:E,3,0) -> #N/A | I12: COL-Cúcuta | J12: =VLOOKUP(A12,'All vendors'!A:Z,13,0) -> 45654.532 | K12: MSA/2021/026 | L12: Private Security | M12: =VLOOKUP(A12,'All vendors'!A:Z,11,0) -> Angelica Guerrero Gonzalez | N12: =VLOOKUP(A12,'All vendors'!A:Z,12,0) -> +573152350459 | O12: =VLOOKUP(A12,'All vendors'!A:Z,15,0) -> comercial@tigerjob.com.co | P12: Maria del Carmen Delgado | Q12: Banco de Bogotá | R12: TIGERS JOB Ltda | S12: No se va a renovar. Se realizará un proceso nuevo RFQ para un contrato mayor a 2500 USD, ya que el MSA se agotaron las enmiendas y tiene un Waiver. | T12: 0 | U12: =17774998+17774998+17774998+17774998+17774998+17774998+17774998+17774998+17774998+17774998+10063916+10063916+10063916+10063916+4035567+4035567+4035567+17267416.5+4035567+4035567+3704277+3704277+3704277+3704277 -> 2.70268e+08 | V12: 0 | Y12: =IF(H12>E12,"No actions","Update ATC") -> #N/A | Z12: =IF(E12<(TODAY()+90),"Send email to SC","No actions") -> Send email to SC | AA12: =IF(E12<=(TODAY()+F12),"Send notification to supplier","No actions") -> Send notification to supplier | AB12: =IF((E12-D12)>720,V12>0, "No actions") -> FALSE
A13: 10000430 | B13: =VLOOKUP(A13,'All vendors'!A:Z,2,0) -> Sociedad Taxis Satelital Taxsatel SAS | C13: Serv Agreem | D13: 44278 | E13: 45373 | F13: 30 | G13: =VLOOKUP(A13,'All vendors'!B:E,4,0) -> #N/A | H13: =VLOOKUP(A13,'All vendors'!B:E,3,0) -> #N/A | I13: COL-Cúcuta | J13: =VLOOKUP(A13,'All vendors'!A:Z,13,0) -> 45654.504 | K13: SC+2500/2023/071 | L13: Transp Services | M13: =VLOOKUP(A13,'All vendors'!A:Z,11,0) -> Jose Nicolas Pineda | N13: =VLOOKUP(A13,'All vendors'!A:Z,12,0) -> +573013165339 | O13: =VLOOKUP(A13,'All vendors'!A:Z,15,0) -> nicolaspineda@hotmail.com | P13: Jesus A. Daza | S13: No se renovara. Se firmo y envio carta de finalización anticipada. | T13: 0 | V13: 0 | Y13: =IF(H13>E13,"No actions","Update ATC") -> #N/A | Z13: =IF(E13<(TODAY()+90),"Send email to SC","No actions") -> Send email to SC | AA13: =IF(E13<=(TODAY()+F13),"Send notification to supplier","No actions") -> Send notification to supplier | AB13: =IF((E13-D13)>720,V13>0, "No actions") -> FALSE
A14: 10003150 | B14: =VLOOKUP(A14,'All vendors'!A:Z,2,0) -> Servicios de salud ocupacional Unimsalud S.A.S. | C14: Serv Agreem | D14: 45017 | E14: 45382 | F14: 5 | G14: =VLOOKUP(A14,'All vendors'!B:E,4,0) -> #N/A | H14: =VLOOKUP(A14,'All vendors'!B:E,3,0) -> #N/A | I14: COL-Bogotá | J14: =VLOOKUP(A14,'All vendors'!A:Z,13,0) -> 45419.643 | K14: SC+2500/2023/078 | L14: Health Services | M14: =VLOOKUP(A14,'All vendors'!A:Z,11,0) -> Mariela Rodriguez de Rodriguez | N14: =VLOOKUP(A14,'All vendors'!A:Z,12,0) -> +576012100478 | O14: =VLOOKUP(A14,'All vendors'!A:Z,15,0) -> unimsalud@unimsalud.com.co | P14: Mariela Rodriguez de Rodriguez | Q14: BBVA | R14: Servicios de salud Ocupacional Unimsalud | S14: No se va a renovar. | T14: 0 | V14: 0 | Y14: =IF(H14>E14,"No actions","Update ATC") -> #N/A | Z14: =IF(E14<(TODAY()+90),"Send email to SC","No actions") -> Send email to SC | AA14: =IF(E14<=(TODAY()+F14),"Send notification to supplier","No actions") -> Send notification to supplier | AB14: =IF((E14-D14)>720,V14>0, "No actions") -> No actions
A15: 10000356 | B15: =VLOOKUP(A15,'All vendors'!A:Z,2,0) -> #N/A | C15: MPA | D15: 45323 | E15: 45688 | F15: 30 | G15: =VLOOKUP(A15,'All vendors'!B:E,4,0) -> #N/A | H15: =VLOOKUP(A15,'All vendors'!B:E,3,0) -> #N/A | I15: COL-Bogotá | J15: =VLOOKUP(A15,'All vendors'!A:Z,13,0) -> #N/A | K15: MPA/2023/029 | L15: Equipos Tech | M15: =VLOOKUP(A15,'All vendors'!A:Z,11,0) -> #N/A | N15: =VLOOKUP(A15,'All vendors'!A:Z,12,0) -> #N/A | O15: =VLOOKUP(A15,'All vendors'!A:Z,15,0) -> #N/A | P15: Mercedez Espinoza | S15: Se envio una carta de cancelacion anticipada de contrato ya que no pueden cumplir con los valores pactads en el anexo A | U15: 0 | V15: 0 | W15: =VLOOKUP(A15,'All vendors'!A:Z,17,0) -> #N/A | X15: 0
A16: 10013763 | B16: =VLOOKUP(A16,'All vendors'!A:Z,2,0) -> Empresa Social del Estado Bellosalud | C16: MSA | D16: 44706 | E16: 45436 | F16: 5 | G16: =VLOOKUP(A16,'All vendors'!B:E,4,0) -> #N/A | H16: =VLOOKUP(A16,'All vendors'!B:E,3,0) -> #N/A | I16: COL-Medellín | J16: =VLOOKUP(A16,'All vendors'!A:Z,13,0) -> 45497.237 | K16: MSA/2021/035 | L16: Health Services | M16: =VLOOKUP(A16,'All vendors'!A:Z,11,0) -> Giovanni Alberto Muñoz García | N16: =VLOOKUP(A16,'All vendors'!A:Z,12,0) -> +573232885428 | O16: =VLOOKUP(A16,'All vendors'!A:Z,15,0) -> cuentasmedicasbellosalud@gmail.com | P16: Alfonso Montoya | Q16: Banco de Bogotá | R16: E.S.E. Bello Salud | S16: Sin Observaciones | U16: 29864254 | V16: 0 | W16: =VLOOKUP(A16,'All vendors'!A:Z,17,0) -> 999999999 | X16: 0 | AA16: =IF(H16>E16,"No actions","Update ATC") -> #N/A | AB16: =IF(E16<(TODAY()+90),"Send email to SC","No actions") -> Send email to SC | AC16: =IF(E16<=(TODAY()+F16),"Send notification to supplier","No actions") -> Send notification to supplier | AD16: =IF((E16-D16)>720,X16>0, "No actions") -> FALSE
A17: 10050019 | B17: =VLOOKUP(A17,'All vendors'!A:Z,2,0) -> Oro Company SAS | C17: Serv Agreem | D17: 45359 | E17: 45442 | F17: 30 | G17: =VLOOKUP(A17,'All vendors'!B:E,4,0) -> #N/A | H17: =VLOOKUP(A17,'All vendors'!B:E,3,0) -> #N/A | I17: COL-Bogotá | J17: No tiene ATC | K17: SsC-2500-2024-049 | L17: Ilustration | M17: =VLOOKUP(A17,'All vendors'!A:Z,11,0) -> PEREA PALACIOS MARTHA | N17: =VLOOKUP(A17,'All vendors'!A:Z,12,0) -> +573132184740 | O17: =VLOOKUP(A17,'All vendors'!A:Z,15,0) -> administracion@orotaller.com | P17: Claudia Patricia Flórez | Q17: Davivienda | R17: Movlife SAS | S17: Sin Observaciones | U17: 7735000 | V17: 0 | W17: =VLOOKUP(A17,'All vendors'!A:Z,17,0) -> 2400 | X17: 0
A18: 10000403 | B18: =VLOOKUP(A18,'All vendors'!A:Z,2,0) -> Asociacion Profamilia | C18: MSA | D18: 44355 | E18: 45443 | F18: 30 | G18: =VLOOKUP(A18,'All vendors'!B:E,4,0) -> #N/A | H18: =VLOOKUP(A18,'All vendors'!B:E,3,0) -> #N/A | I18: COL-Bogotá | J18: =VLOOKUP(A18,'All vendors'!A:Z,13,0) -> 45804.216 | K18: MSA/2020/020 | L18: Health Services | M18: =VLOOKUP(A18,'All vendors'!A:Z,11,0) -> Juliana Marín Restrepo | N18: =VLOOKUP(A18,'All vendors'!A:Z,12,0) -> +573124116546 | O18: =VLOOKUP(A18,'All vendors'!A:Z,15,0) -> juliana.marin@profamilia.com | P18: Jorge Ivàn Rojo | Q18: Banco de Bogotá | R18: ASOCIACION PROFAMILIA | S18: Sin Observaciones | U18: 2200929443 | V18: 0 | W18: =VLOOKUP(A18,'All vendors'!A:Z,17,0) -> 999999999 | X18: 1 | AA18: =IF(H18>E18,"No actions","Update ATC") -> #N/A | AB18: =IF(E18<(TODAY()+90),"Send email to SC","No actions") -> Send email to SC | AC18: =IF(E18<=(TODAY()+F18),"Send notification to supplier","No actions") -> Send notification to supplier | AD18: =IF((E18-D18)>720,X18>0, "No actions") -> TRUE
A19: 10050020 | B19: =VLOOKUP(A19,'All vendors'!A:Z,2,0) -> Laura Natalia Noriega Gomez | C19: Serv Agreem | D19: 18-Marz-24 | E19: 45443 | F19: 30 | G19: =VLOOKUP(A19,'All vendors'!B:E,4,0) -> #N/A | H19: =VLOOKUP(A19,'All vendors'!B:E,3,0) -> #N/A | I19: COL-Bogotá | J19: No tiene ATC | K19: SC-2500/2024/048 | L19: Graphic Design | M19: =VLOOKUP(A19,'All vendors'!A:Z,11,0) -> Laura Natalia Noriega Gomez | N19: =VLOOKUP(A19,'All vendors'!A:Z,12,0) -> +573168203747 | O19: =VLOOKUP(A19,'All vendors'!A:Z,15,0) -> noriegagomezln@gmail.com | P19: Franklin Cardenas | Q19: Bank of America | S19: Tope: 9.500.000 COP | T19: =9500000/4000 -> 2375 | U19: 9500000 | V19: 0 | W19: =VLOOKUP(A19,'All vendors'!A:Z,17,0) -> 19000 | X19: 0
A20: 10000528 | B20: =VLOOKUP(A20,'All vendors'!A:Z,2,0) -> T&T Col S.A.S | C20: MSA | D20: 44409 | E20: 45504 | F20: 30 | G20: =VLOOKUP(A20,'All vendors'!B:E,4,0) -> #N/A | H20: =VLOOKUP(A20,'All vendors'!B:E,3,0) -> #N/A | I20: COL-Cúcuta | J20: =VLOOKUP(A20,'All vendors'!A:Z,13,0) -> 45654.504 | K20: MSA/2021/027 | L20: Transportation | M20: =VLOOKUP(A20,'All vendors'!A:Z,11,0) -> María Fernanda Tarazona Rojas | N20: =VLOOKUP(A20,'All vendors'!A:Z,12,0) -> +573126852001 | O20: =VLOOKUP(A20,'All vendors'!A:Z,15,0) -> tytcol.operaciones@gmail.com | P20: Eglen Kevin Castillo | Q20: BBVA | R20: T&T COL SAS | S20: El contrato terminará, se comienza nuevo proceso de RFQ | T20: 0 | U20: 511895000 | V20: 0 | W20: =VLOOKUP(A20,'All vendors'!A:Z,17,0) -> 999999999 | X20: 1 | AA20: =IF(H20>E20,"No actions","Update ATC") -> #N/A | AB20: =IF(E20<(TODAY()+90),"Send email to SC","No actions") -> Send email to SC | AC20: =IF(E20<=(TODAY()+F20),"Send notification to supplier","No actions") -> Send notification to supplier | AD20: =IF((E20-D20)>720,X20>0, "No actions") -> TRUE

Sheet Spend by Vendor
A1: Vendor Party # | B1: Entity | C1: Vendor Account # | D1: Vendor Name | E1: Vendor Group | F1: ATC Check ID | G1: Integra ATC Sub Date | H1: ATC Clearance Exp Date | I1: IRC ATC Status | J1: Vendor Hold Status | K1: Anticipated Spend | L1: Total Spending | M1: Overspent | N1: Vendor Created Date | O1: Vendor Modified Date
A2: 000000017 | B2: 4COL | C2: 10020295 | D2: Laura Yu | E2: EMP | F2: 82544 | I2: Cleared | J2: All | K2: 0 | L2: 0 | M2: N | N2: 44880 | O2: 44880
A3: 000000178 | B3: 4COL | C3: 10000451 | D3: Asociación Civil amigos del Hospital de Niños de Valencia | E3: SUB | I3: Cleared | J3: No | K3: 0 | L3: 0 | M3: N | N3: 44603 | O3: 44701
A4: 000000345 | B4: 4COL | C4: 10000454 | D4: Madres y Padres Por Los Niños En Venezuela (MAPANI VZLA) | E4: SUB | F4: 146434 | G4: 2/26/2021 | H4: 2/10/2023 | I4: Expired | J4: All Except Payment | K4: 0 | L4: 0 | M4: N | N4: 44603 | O4: 44968
A5: 000000499 | B5: 4COL | C5: 10004362 | D5: Asociación Larense de Planificación Familiar | E5: SUB | F5: 254426 | G5: 4/28/2023 | H5: 4/29/2024 | I5: Cleared | J5: No | K5: 0 | L5: 0 | M5: N | N5: 44697 | O5: 45048
A6: 000001065 | B6: 4COL | C6: 10012617 | D6: Olivia Hadley | E6: EMP | J6: All | K6: 0 | L6: 0 | M6: N | N6: 44784 | O6: 44784
A7: 000001331 | B7: 4COL | C7: 10000003 | D7: Rosalind Montanez | E7: EMP | J7: No | K7: 0 | L7: 0 | M7: N | N7: 44497 | O7: 44497
A8: 000001690 | B8: 4COL | C8: 10009561 | D8: Elena Wallraff | E8: EMP | J8: No | K8: 0 | L8: 0 | M8: N | N8: 44750 | O8: 44750
A9: 000001770 | B9: 4COL | C9: 10013463 | D9: To be determined (TBD) | E9: SUB | J9: All | K9: 0 | L9: 0 | M9: N | N9: 44796 | O9: 44796
A10: 000001977 | B10: 4COL | C10: 10009484 | D10: Yolanda Barbera Barbera | E10: CONT | J10: No | K10: 0 | L10: 37874.86 | M10: Y | N10: 44749 | O10: 44944
A11: 000002165 | B11: 4COL | C11: 10032300 | D11: Martine Dherte | E11: EMP | J11: No | K11: 0 | L11: 0 | M11: N | N11: 45062 | O11: 45062
A12: 000002304 | B12: 4COL | C12: 10002402 | D12: Mohammed Mahdi | E12: EMP | J12: No | K12: 0 | L12: 0 | M12: N | N12: 44683 | O12: 44944
A13: 000002676 | B13: 4COL | C13: 10025082 | D13: Juliet Stein | E13: CONT | J13: All | K13: 0 | L13: 0 | M13: N | N13: 44946 | O13: 44946
A14: 000003448 | B14: 4COL | C14: 10030596 | D14: Helen Rolston-Clemmer | E14: EMP | J14: All | K14: 0 | L14: 0 | M14: N | N14: 45037 | O14: 45037
A15: 000003638 | B15: 4COL | C15: 10002838 | D15: Heather Molloy | E15: EMP | J15: No | K15: 0 | L15: 0 | M15: N | N15: 44686 | O15: 44686
A16: 000004658 | B16: 4COL | C16: 10007031 | D16: Maria Nattaly Dulcey Chaparro | E16: CONT | J16: No | K16: 0 | L16: 0 | M16: N | N16: 44725 | O16: 44725
A17: 000004709 | B17: 4COL | C17: 10006317 | D17: Paola Andrea Buendia Torres | E17: TRADE | F17: 207018 | G17: 6/6/2022 | H17: 6/7/2023 | I17: Cleared | J17: No | K17: 2400 | L17: 0 | M17: N | N17: 44718 | O17: 44721
A18: 000005421 | B18: 4COL | C18: 10000456 | D18: Planson International Corporation | E18: TRADE | F18: 246792 | G18: 2/27/2023 | H18: 2/26/2024 | I18: Cleared | J18: No | K18: 1000000 | L18: 518466.71 | M18: N | N18: 44603 | O18: 44984
A19: 000005461 | B19: 4COL | C19: 10000457 | D19: Taylor Made Graphics Co. Inc. | E19: TRADE | F19: 246311 | G19: 2/23/2023 | H19: 2/22/2024 | I19: Cleared | J19: No | K19: 500000 | L19: 24914.45 | M19: N | N19: 44603 | O19: 44988
A20: 000006750 | B20: 4COL | C20: 10016591 | D20: Laura Rossello | E20: CONT | J20: No | K20: 0 | L20: 7000 | M20: Y | N20: 44827 | O20: 44937
A21: 000006872 | B21: 4COL | C21: 10004041 | D21: Kate Say | E21: EMP | J21: All | K21: 0 | L21: 0 | M21: N | N21: 44693 | O21: 44693
A22: 000006959 | B22: 4COL | C22: 10008219 | D22: Esperance Nshimiyimana | E22: EMP | J22: All | K22: 0 | L22: 0 | M22: N | N22: 44736 | O22: 44736
A23: 000006960 | B23: 4COL | C23: 10000744 | D23: Norman Slawsky | E23: INTVOL | J23: No | K23: 0 | L23: 0 | M23: N | N23: 44664 | O23: 44664
A24: 000007068 | B24: 4COL | C24: 10013103 | D24: Alphonse Kitoga | E24: CONT | J24: No | K24: 0 | L24: 0 | M24: N | N24: 44791 | O24: 45022
A25: 000007488 | B25: 4COL | C25: 10021562 | D25: Gordana Ivkovic-Grujic | E25: EMP | J25: No | K25: 0 | L25: 0 | M25: N | N25: 44896 | O25: 44896
A26: 000008203 | B26: 4COL | C26: 10030338 | D26: Alphonse Soungalo Diakite | E26: EMP | J26: All | K26: 0 | L26: 0 | M26: N | N26: 45034 | O26: 45034
A27: 000008350 | B27: 4COL | C27: 10013375 | D27: Shama Imtiaz | E27: EMP | J27: No | K27: 0 | L27: 0 | M27: N | N27: 44795 | O27: 44795
A28: 000008473 | B28: 4COL | C28: 10028778 | D28: Abdikadir Hassan | E28: EMP | J28: All | K28: 0 | L28: 0 | M28: N | N28: 45001 | O28: 45001
A29: 000008614 | B29: 4COL | C29: 10020847 | D29: Damien Bigirimana | E29: EMP | J29: All | K29: 0 | L29: 0 | M29: N | N29: 44886 | O29: 44886
A30: 000008673 | B30: 4COL | C30: 10018969 | D30: Mireine Bulonza | E30: EMP | J30: No | K30: 0 | L30: 0 | M30: N | N30: 44860 | O30: 44860
A31: 000009227 | B31: 4COL | C31: 10006333 | D31: Vannina Kaneza | E31: EMP | J31: No | K31: 0 | L31: 0 | M31: N | N31: 44718 | O31: 44944
... A94: 000018955 | B94: 4COL | C94: 10029326 | D94: Acacia Keith | E94: EMP | J94: All | K94: 0 | L94: 0 | M94: N | N94: 45012 | O94: 45012
A95: 000019464 | B95: 4COL | C95: 10003669 | D95: Asociación Civil Acción Zuliana por la Vida | E95: SUB | F95: 254430 | G95: 4/28/2023 | H95: 4/29/2024 | I95: Cleared | J95: No | K95: 2501 | L95: 0 | M95: N | N95: 44692 | O95: 45049
A96: 000019602 | B96: 4COL | C96: 10026473 | D96: QUAMED | E96: TRADE | F96: 244518 | G96: 2/10/2023 | H96: 2/9/2024 | I96: Cleared | J96: No | K96: 50000 | L96: 38713.91 | M96: N | N96: 44967 | O96: 44967
A97: 000020446 | B97: 4COL | C97: 10006868 | D97: Graciela Pasquier | E97: EMP | J97: No | K97: 0 | L97: 2000 | M97: Y | N97: 44722 | O97: 44722
A98: 000020466 | B98: 4COL | C98: 10000017 | D98: Maria Menjivar | E98: EMP | J98: No | K98: 0 | L98: 1406.53 | M98: Y | N98: 44497 | O98: 44497
A99: 000020531 | B99: 4COL | C99: 10000004 | D99: Cassandra Chaire | E99: EMP | J99: No | K99: 0 | L99: 1526.71 | M99: Y | N99: 44497 | O99: 44497
A100: 000020813 | B100: 4COL | C100: 10014704 | D100: Facebook | E100: TRADE | F100: 222906 | G100: 9/5/2022 | H100: 9/6/2023 | I100: Cleared | J100: No | K100: 44444444 | L100: 11679242 | M100: N | N100: 44809 | O100: 45063
A101: 000021506 | B101: 4COL | C101: 10027720 | D101: Berivan Mohammad Ali | E101: EMP | J101: All | K101: 0 | L101: 0 | M101: N | N101: 44985 | O101: 44985
A102: 000021753 | B102: 4COL | C102: 10000033 | D102: Jairo Tovar | E102: EMP | J102: No | K102: 0 | L102: 0 | M102: N | N102: 44497 | O102: 44643
A103: 000021904 | B103: 4COL | C103: 10010808 | D103: Martin Lubari Sebit | E103: EMP | J103: All | K103: 0 | L103: 2174.36 | M103: Y | N103: 44764 | O103: 44764
A104: 000022972 | B104: 4COL | C104: 10015485 | D104: Safaa Abdullah | E104: EMP | J104: No | K104: 0 | L104: 0 | M104: N | N104: 44816 | O104: 44816
A105: 000023251 | B105: 4COL | C105: 10000035 | D105: Nelly Zapata | E105: EMP | J105: No | K105: 0 | L105: 0 | M105: N | N105: 44497 | O105: 44643
A106: 000023253 | B106: 4COL | C106: 10000036 | D106: Johann Diaz | E106: EMP | J106: No | K106: 0 | L106: 0 | M106: N | N106: 44497 | O106: 44643
A107: 000023284 | B107: 4COL | C107: 10000034 | D107: Camilo Valenzuela | E107: EMP | J107: No | K107: 0 | L107: 0 | M107: N | N107: 44497 | O107: 44643
A108: 000023298 | B108: 4COL | C108: 10001688 | D108: Marwa Fadel | E108: EMP | J108: No | K108: 0 | L108: 0 | M108: N | N108: 44676 | O108: 44944
A109: 000023350 | B109: 4COL | C109: 10029226 | D109: Lilian Mulungye | E109: EMP | J109: All | K109: 0 | L109: 471.58 | M109: Y | N109: 45012 | O109: 45012
A110: 000023954 | B110: 4COL | C110: 10022900 | D110: Altaf Hussain | E110: EMP | J110: No | K110: 0 | L110: 0 | M110: N | N110: 44916 | O110: 44916
A111: 000024308 | B111: 4COL | C111: 10026030 | D111: Saddam Hussain | E111: EMP | J111: No | K111: 0 | L111: 0 | M111: N | N111: 44960 | O111: 44960
A112: 000024389 | B112: 4COL | C112: 10013982 | D112: Amine Ahmat Djazouli | E112: EMP | J112: All | K112: 0 | L112: 823.31 | M112: Y | N112: 44802 | O112: 44802
... A117: 000024525 | B117: 4COL | C117: 10008167 | D117: Mulamba Salumu Philippe | E117: CONT | J117: No | K117: 0 | L117: 0 | M117: N | N117: 44736 | O117: 44944
A118: 000024557 | B118: 4COL | C118: 10004047 | D118: Asociacion Civil Red de Casas Don Bosco | E118: SUB | I118: Cleared | J118: No | K118: 1 | L118: 0 | M118: N | N118: 44693 | O118: 44701
A119: 000024575 | B119: 4COL | C119: 10000450 | D119: Asociación Civil Equipo de Proyectos y Asesoría Social (EDEPA) | E119: SUB | F119: 149851 | G119: 3/24/2021 | H119: 2/10/2023 | I119: Expired | J119: All Except Payment | K119: 0 | L119: 0 | M119: N | N119: 44603 | O119: 44968
A120: 000025187 | B120: 4COL | C120: 10000044 | D120: Paola Segura | E120: EMP | J120: No | K120: 0 | L120: 224.9 | M120: Y | N120: 44497 | O120: 44643
A121: 000025188 | B121: 4COL | C121: 10000042 | D121: DANA GUERRERO | E121: EMP | J121: No | K121: 0 | L121: 0 | M121: N | N121: 44497 | O121: 44643
A122: 000025189 | B122: 4COL | C122: 10000043 | D122: KARELY VANEGAS | E122: EMP | J122: No | K122: 0 | L122: 0 | M122: N | N122: 44497 | O122: 44643
A123: 000025196 | B123: 4COL | C123: 10000041 | D123: Anggi Gonzalez | E123: EMP | J123: No | K123: 0 | L123: 0 | M123: N | N123: 44497 | O123: 44643
A124: 000025252 | B124: 4COL | C124: 10000040 | D124: Yenny Torbello | E124: EMP | J124: No | K124: 0 | L124: 0 | M124: N | N124: 44497 | O124: 44643
A125: 000025436 | B125: 4COL | C125: 10000049 | D125: deyse mogollon | E125: EMP | J125: No | K125: 0 | L125: 0 | M125: N | N125: 44497 | O125: 44643
A126: 000025437 | B126: 4COL | C126: 10000050 | D126: adriana mendoza | E126: EMP | J126: No | K126: 0 | L126: 0 | M126: N | N126: 44497 | O126: 44643
A127: 000025641 | B127: 4COL | C127: 10000045 | D127: Saraisabel Martinez | E127: EMP | J127: No | K127: 0 | L127: 212.58 | M127: Y | N127: 44497 | O127: 44643
A128: 000025642 | B128: 4COL | C128: 10005326 | D128: Sandybel Arévalo | E128: CONT | J128: No | K128: 0 | L128: 0 | M128: N | N128: 44706 | O128: 44706
A129: 000025662 | B129: 4COL | C129: 10000046 | D129: Geraldyne Lopez | E129: EMP | J129: No | K129: 0 | L129: 0 | M129: N | N129: 44497 | O129: 44643
A130: 000025663 | B130: 4COL | C130: 10000047 | D130: Erika Ortega | E130: EMP | J130: No | K130: 0 | L130: 0 | M130: N | N130: 44497 | O130: 44643
A131: 000025691 | B131: 4COL | C131: 10032903 | D131: Benazir Vighio | E131: EMP | J131: No | K131: 0 | L131: 0 | M131: N | N131: 45069 | O131: 45069
... A156: 000027831 | B156: 4COL | C156: 10000074 | D156: Astrid Ruiz | E156: EMP | J156: No | K156: 0 | L156: 0 | M156: N | N156: 44497 | O156: 44643
A157: 000028466 | B157: 4COL | C157: 10000452 | D157: Asociación Venezolana de Servicios de Salud de Orientación Cristiana (AVESSOC) | E157: SUB | F157: 174085 | G157: 5/12/2021 | H157: 2/10/2023 | I157: Expired | J157: All Except Payment | K157: 0 | L157: 0 | M157: N | N157: 44603 | O157: 44968
A158: 000028549 | B158: 4COL | C158: 10000075 | D158: Ana Churio | E158: EMP | J158: No | K158: 0 | L158: 0 | M158: N | N158: 44497 | O158: 44643
A159: 000028550 | B159: 4COL | C159: 10000076 | D159: Angie Guayambuco | E159: EMP | J159: No | K159: 0 | L159: 0 | M159: N | N159: 44497 | O159: 44643
A160: 000028552 | B160: 4COL | C160: 10000077 | D160: Erika Mora | E160: EMP | J160: No | K160: 0 | L160: 122.08 | M160: Y | N160: 44497 | O160: 44643
A161: 000028553 | B161: 4COL | C161: 10000078 | D161: Rodriguez Padilla Nerina | E161: EMP | J161: No | K161: 0 | L161: 0 | M161: N | N161: 44497 | O161: 45033
A162: 000028554 | B162: 4COL | C162: 10000079 | D162: Azalia Salazar | E162: EMP | J162: No | K162: 0 | L162: 0 | M162: N | N162: 44497 | O162: 44643
A163: 000028555 | B163: 4COL | C163: 10000080 | D163: andreina ureña | E163: EMP | J163: No | K163: 0 | L163: 0 | M163: N | N163: 44497 | O163: 44643
A164: 000028564 | B164: 4COL | C164: 10000081 | D164: Luisa Garcia | E164: EMP | J164: No | K164: 0 | L164: 0 | M164: N | N164: 44497 | O164: 44643
A165: 000028670 | B165: 4COL | C165: 10000082 | D165: Valentina Sepulveda | E165: EMP | J165: No | K165: 0 | L165: 0 | M165: N | N165: 44497 | O165: 44643
A166: 000029799 | B166: 4COL | C166: 10000083 | D166: Paola Pinilla | E166: EMP | J166: No | K166: 0 | L166: 0 | M166: N | N166: 44497 | O166: 44643
A167: 000030113 | B167: 4COL | C167: 10001674 | D167: Blay Franck Charles DIOUF | E167: EMP | J167: No | K167: 0 | L167: 0 | M167: N | N167: 44676 | O167: 44944
A168: 000030121 | B168: 4COL | C168: 10000084 | D168: saray peña | E168: EMP | J168: No | K168: 0 | L168: 0 | M168: N | N168: 44497 | O168: 44643
A169: 000030351 | B169: 4COL | C169: 10000085 | D169: Eliana Prada | E169: EMP | J169: No | K169: 0 | L169: 0 | M169: N | N169: 44497 | O169: 44643
... A260: 000045173 | B260: 4COL | C260: 10000173 | D260: Jose Clavijo | E260: EMP | J260: No | K260: 0 | L260: 0 | M260: N | N260: 44497 | O260: 45040
A261: 000045228 | B261: 4COL | C261: 10016769 | D261: Secretariado Diocesano De Pastoral Social | E261: SUB | I261: Cleared | J261: All | K261: 0 | L261: 0 | M261: N | N261: 44831 | O261: 44831
A262: 000045575 | B262: 4COL | C262: 10016733 | D262: Asociación para el Desarrollo de la Educación Integral y Comunitaria (ASEINC) | E262: SUB | F262: 225954 | G262: 9/26/2022 | H262: 9/27/2023 | I262: Cleared | J262: No | K262: 0 | L262: 0 | M262: N | N262: 44830 | O262: 44832
A263: 000045621 | B263: 4COL | C263: 10013461 | D263: Corporación El Minuto de Dios | E263: SUB | I263: Cleared | J263: All | K263: 0 | L263: 0 | M263: N | N263: 44796 | O263: 44796
A264: 000045678 | B264: 4COL | C264: 10000174 | D264: Mariel Rojas | E264: EMP | J264: No | K264: 0 | L264: 2.22 | M264: Y | N264: 44497 | O264: 44643
A265: 000045679 | B265: 4COL | C265: 10000175 | D265: Zaida Mayorga | E265: EMP | J265: No | K265: 0 | L265: 68.82 | M265: Y | N265: 44497 | O265: 44643
A266: 000045680 | B266: 4COL | C266: 10000176 | D266: Angela Schell | E266: EMP | J266: No | K266: 0 | L266: 0 | M266: N | N266: 44497 | O266: 44497
A267: 000045781 | B267: 4COL | C267: 10004001 | D267: Corporación Infancia y Desarrollo | E267: SUB | I267: Cleared | J267: No | K267: 0 | L267: 0 | M267: N | N267: 44693 | O267: 44701
A268: 000046536 | B268: 4COL | C268: 10000177 | D268: Yurany Avila | E268: EMP | J268: No | K268: 0 | L268: 0 | M268: N | N268: 44497 | O268: 44643
A269: 000046540 | B269: 4COL | C269: 10000178 | D269: Maria Fernanda Higuera | E269: EMP | J269: No | K269: 0 | L269: 637 | M269: Y | N269: 44497 | O269: 44643
A270: 000046645 | B270: 4COL | C270: 10000179 | D270: Zory Escobar | E270: EMP | J270: No | K270: 0 | L270: 0 | M270: N | N270: 44497 | O270: 44643
A271: 000048420 | B271: 4COL | C271: 10000180 | D271: Sofia Grijalba | E271: EMP | J271: No | K271: 0 | L271: 0 | M271: N | N271: 44497 | O271: 44643
A272: 000049686 | B272: 4COL | C272: 10020459 | D272: Abdul Ahmadi | E272: EMP | J272: No | K272: 0 | L272: 598.99 | M272: Y | N272: 44881 | O272: 44958
A273: 000053078 | B273: 4COL | C273: 10005019 | D273: Angela Marquez de Arboleda | E273: CONT | J273: No | K273: 0 | L273: 18200 | M273: Y | N273: 44704 | O273: 44706
A274: 000053170 | B274: 4COL | C274: 10000181 | D274: Raquel Itriago | E274: EMP | J274: No | K274: 0 | L274: 0 | M274: N | N274: 44497 | O274: 44643
A275: 000053172 | B275: 4COL | C275: 10000182 | D275: Miyer Sierra | E275: EMP | J275: No | K275: 0 | L275: 0 | M275: N | N275: 44497 | O275: 44497
A276: 000053470 | B276: 4COL | C276: 10000183 | D276: Carolina Escobar | E276: EMP | J276: No | K276: 0 | L276: 0 | M276: N | N276: 44497 | O276: 44643
A277: 000053471 | B277: 4COL | C277: 10000184 | D277: Helybet Rios | E277: EMP | J277: No | K277: 0 | L277: 0 | M277: N | N277: 44497 | O277: 44643
A278: 000053543 | B278: 4COL | C278: 10000185 | D278: Ronny Candelo | E278: EMP | J278: No | K278: 0 | L278: 0 | M278: N | N278: 44497 | O278: 44643
A279: 000053775 | B279: 4COL | C279: 10000186 | D279: Anabel Quimuna | E279: EMP | J279: No | K279: 0 | L279: 0 | M279: N | N279: 44497 | O279: 44623
A280: 000053863 | B280: 4COL | C280: 10000187 | D280: Estefania Sirlopu | E280: EMP | J280: No | K280: 0 | L280: 648.97 | M280: Y | N280: 44497 | O280: 44643
...

Sheet Sheet1
A1: Vendor account | B1: Name | C1: Vendor hold | D1: Group | E1: Currency/ Donor Currency | F1: Group2 | G1: Line of business | H1: Segment | I1: Terms of payment | J1: Vendor total spend | K1: Reference | L1: Phone | M1: ATC clearance expiration date | N1: ATC status | O1: Email address | P1: URL | Q1: Vendor anticipated spend USD | R1: Last name | S1: Last name prefix | T1: Middle name | U1: Created by | V1: Modified by | W1: Birth date | X1: Channel Reference Identifier | Y1: Contact number/address | Z1: Country of birth | AA1: Country of birth entered | AB1: Date of birth entered | AC1: Description | AD1: Electronic address Id | AE1: Extension | AF1: First name | AG1: Gender | AH1: Gender entered | AI1: Instant message | AJ1: International calling code | AK1: Last name2 | AL1: Location | AM1: Maiden name | AN1: Maiden name entered | AO1: Marketing opt-in | AP1: Middle name2 | AQ1: Middle name entered | AR1: Mobile | AS1: Nationality | AT1: Nationality entered | AU1: Party reference for private location | AV1: Primary | AW1: Private | AX1: Type | AY1: Modified by2 | AZ1: Modified date and time | BA1: Affix | BB1: Affix type | BC1: Description2 | BD1: Affix2 | BE1: Affix type2 | BF1: Description3 | BG1: Display as | BH1: Name elements | BI1: Name elements2 | BJ1: Name elements3 | BK1: Name elements4 | BL1: Number of blank spaces | BM1: Number of blank spaces2 | BN1: Number of blank spaces3 | BO1: Separator | BP1: Separator2 | BQ1: Separator3 | BR1: Name2 | BS1: Personnel number | BT1: Created by2 | BU1: Created date and time | BV1: Modified by3 | BW1: Modified date and time2 | BX1: Vendor total spend2 | BY1: Anniversary day | BZ1: Anniversary month | CA1: Anniversary year | CB1: ATC check Id | CC1: ATC check Id2 | CD1: ATC clearance expiration date 2 | CE1: ATC status2 | CF1: ATC status3 | CG1: Birth day | CH1: Birth month | CI1: Birth year | CJ1: Children | CK1: DUNS number | CL1: Email address2 | CM1: Facebook | CN1: Fax | CO1: First name2 | CP1: First name3 | CQ1: Gender2 | CR1: Hobbies | CS1: Initials | CT1: Instant messenger sign-in | CU1: Integra ATC submission date | CV1: Known as | CW1: Known As 2 | CX1: Language | CY1: Last name3 | CZ1: Last name4 | DA1: LinkedIn | DB1: Location2
A2: 10000001 | B2: Gabriela Gonzalez | C2: No | D2: CONT | E2: COP | F2: CONT | I2: Net30 | J2: 0 | O2: Gabriela.Gonzalez@rescue.org | Q2: 20000 | R2: Gonzalez | U2: Admin | V2: Admin | AA2: No | AB2: No | AH2: No | AI2: No | AN2: No | AO2: No | AQ2: No | AR2: No | AT2: No | AV2: No | AW2: No | BG2: FirstMiddleLast | BH2: First name | BI2: Middle name | BJ2: Last name | BK2: None | BL2: 1 | BM2: 1 | BN2: 0 | BX2: 0 | BY2: 0 | CA2: 0 | CG2: 0 | CI2: 0
A3: 10000210 | B3: Louisiana Mendoza | C3: No | D3: EMP | E3: COP | F3: EMP | I3: Net30 | J3: 5273.31 | O3: Louisiana.Mendoza@rescue.org | Q3: 0 | R3: Mendoza | U3: UPagola | V3: UPagola | AA3: No | AB3: No | AH3: No | AI3: No | AN3: No | AO3: No | AQ3: No | AR3: No | AT3: No | AV3: No | AW3: No | BG3: FirstMiddleLast | BH3: First name | BI3: Middle name | BJ3: Last name | BK3: None | BL3: 1 | BM3: 1 | BN3: 0 | BX3: 0 | BY3: 0 | CA3: 0 | CG3: 0 | CI3: 0
A4: 10000218 | B4: Veronica Suarez | C4: No | D4: CONT | E4: COP | F4: CONT | I4: Net30 | J4: 0 | O4: Veronica.Suarez@rescue.org | Q4: 0 | R4: Suarez | U4: UPagola | V4: UPagola | AA4: No | AB4: No | AH4: No | AI4: No | AN4: No | AO4: No | AQ4: No | AR4: No | AT4: No | AV4: No | AW4: No | BG4: FirstMiddleLast | BH4: First name | BI4: Middle name | BJ4: Last name | BK4: None | BL4: 1 | BM4: 1 | BN4: 0 | BX4: 0 | BY4: 0 | CA4: 0 | CG4: 0 | CI4: 0
A5: 10000245 | B5: Reinaldo Chacon | C5: No | D5: CONT | E5: COP | F5: CONT | I5: Net30 | J5: 0 | O5: Reinaldo.Chacon@rescue.org | Q5: 0 | R5: Chacon | U5: Admin | V5: Admin | AA5: No | AB5: No | AH5: No | AI5: No | AN5: No | AO5: No | AQ5: No | AR5: No | AT5: No | AV5: No | AW5: No | BG5: FirstMiddleLast | BH5: First name | BI5: Middle name | BJ5: Last name | BK5: None | BL5: 1 | BM5: 1 | BN5: 0 | BX5: 0 | BY5: 0 | CA5: 0 | CG5: 0 | CI5: 0
A6: 10000261 | B6: Jose Baptista | C6: No | D6: CONT | E6: USD | F6: CONT | I6: Net30 | J6: 0 | O6: Jose.Baptista@rescue.org | Q6: 0 | R6: Baptista | U6: Admin | V6: Admin | AA6: No | AB6: No | AH6: No | AI6: No | AN6: No | AO6: No | AQ6: No | AR6: No | AT6: No | AV6: No | AW6: No | BG6: FirstMiddleLast | BH6: First name | BI6: Middle name | BJ6: Last name | BK6: None | BL6: 1 | BM6: 1 | BN6: 0 | BX6: 0 | BY6: 0 | CA6: 0 | CG6: 0 | CI6: 0
A7: 10000262 | B7: Angelica Sanchez | C7: No | D7: CONT | E7: USD | F7: CONT | I7: Net30 | J7: 0 | O7: Angelica.Sanchez@rescue.org | Q7: 0 | R7: Sanchez | U7: Admin | V7: Admin | AA7: No | AB7: No | AH7: No | AI7: No | AN7: No | AO7: No | AQ7: No | AR7: No | AT7: No | AV7: No | AW7: No | BG7: FirstMiddleLast | BH7: First name | BI7: Middle name | BJ7: Last name | BK7: None | BL7: 1 | BM7: 1 | BN7: 0 | BX7: 0 | BY7: 0 | CA7: 0 | CG7: 0 | CI7: 0
A8: 10000264 | B8: Ivan Delahais | C8: No | D8: CONT | E8: COP | F8: CONT | I8: Net30 | J8: 0 | O8: Ivan.Delahais@rescue.org | Q8: 0 | R8: Delahais | U8: Admin | V8: Admin | AA8: No | AB8: No | AH8: No | AI8: No | AN8: No | AO8: No | AQ8: No | AR8: No | AT8: No | AV8: No | AW8: No | BG8: FirstMiddleLast | BH8: First name | BI8: Middle name | BJ8: Last name | BK8: None | BL8: 1 | BM8: 1 | BN8: 0 | BX8: 0 | BY8: 0 | CA8: 0 | CG8: 0 | CI8: 0
A9: 10000266 | B9: Esttefany Alvarez | C9: No | D9: CONT | E9: COP | F9: CONT | I9: Net30 | J9: 0 | O9: Esttefany.Alvarez@rescue.org | Q9: 0 | R9: Alvarez | U9: Admin | V9: Admin | AA9: No | AB9: No | AH9: No | AI9: No | AN9: No | AO9: No | AQ9: No | AR9: No | AT9: No | AV9: No | AW9: No | BG9: FirstMiddleLast | BH9: First name | BI9: Middle name | BJ9: Last name | BK9: None | BL9: 1 | BM9: 1 | BN9: 0 | BX9: 0 | BY9: 0 | CA9: 0 | CG9: 0 | CI9: 0
A10: 10000272 | B10: Reinaldo Gutierrez | C10: No | D10: CONT | E10: USD | F10: CONT | I10: Net30 | J10: 0 | O10: Reinaldo.Gutierrez@rescue.org | Q10: 0 | R10: Gutierrez | U10: Admin | V10: Admin | AA10: No | AB10: No | AH10: No | AI10: No | AN10: No | AO10: No | AQ10: No | AR10: No | AT10: No | AV10: No | AW10: No | BG10: FirstMiddleLast | BH10: First name | BI10: Middle name | BJ10: Last name | BK10: None | BL10: 1 | BM10: 1 | BN10: 0 | BX10: 0 | BY10: 0 | CA10: 0 | CG10: 0 | CI10: 0
A11: 10000275 | B11: Lucia Añasco | C11: No | D11: CONT | E11: USD | F11: CONT | I11: Net30 | J11: 0 | O11: Lucia.Anasco@rescue.org | Q11: 0 | R11: Añasco | U11: Admin | V11: Admin | AA11: No | AB11: No | AH11: No | AI11: No | AN11: No | AO11: No | AQ11: No | AR11: No | AT11: No | AV11: No | AW11: No | BG11: FirstMiddleLast | BH11: First name | BI11: Middle name | BJ11: Last name | BK11: None | BL11: 1 | BM11: 1 | BN11: 0 | BX11: 0 | BY11: 0 | CA11: 0 | CG11: 0 | CI11: 0
A12: 10000277 | B12: Miriam Moya | C12: No | D12: CONT | E12: COP | F12: CONT | I12: Net30 | J12: 0 | O12: Miriam.Moya@rescue.org | Q12: 0 | R12: Moya | U12: Admin | V12: Admin | AA12: No | AB12: No | AH12: No | AI12: No | AN12: No | AO12: No | AQ12: No | AR12: No | AT12: No | AV12: No | AW12: No | BG12: FirstMiddleLast | BH12: First name | BI12: Middle name | BJ12: Last name | BK12: None | BL12: 1 | BM12: 1 | BN12: 0 | BX12: 0 | BY12: 0 | CA12: 0 | CG12: 0 | CI12: 0
A13: 10000279 | B13: Diana Montero | C13: No | D13: CONT | E13: USD | F13: CONT | I13: Net30 | J13: 0 | O13: Diana.Montero@rescue.org | Q13: 0 | R13: Montero | U13: Admin | V13: Admin | AA13: No | AB13: No | AH13: No | AI13: No | AN13: No | AO13: No | AQ13: No | AR13: No | AT13: No | AV13: No | AW13: No | BG13: FirstMiddleLast | BH13: First name | BI13: Middle name | BJ13: Last name | BK13: None | BL13: 1 | BM13: 1 | BN13: 0 | BX13: 0 | BY13: 0 | CA13: 0 | CG13: 0 | CI13: 0
A14: 10000285 | B14: Marcela Valdez | C14: No | D14: CONT | E14: COP | F14: CONT | I14: Net30 | J14: 0 | O14: Marcela.Valdez@rescue.org | Q14: 0 | R14: Valdez | U14: Admin | V14: Admin | AA14: No | AB14: No | AH14: No | AI14: No | AN14: No | AO14: No | AQ14: No | AR14: No | AT14: No | AV14: No | AW14: No | BG14: FirstMiddleLast | BH14: First name | BI14: Middle name | BJ14: Last name | BK14: None | BL14: 1 | BM14: 1 | BN14: 0 | BX14: 0 | BY14: 0 | CA14: 0 | CG14: 0 | CI14: 0
A15: 10000287 | B15: Diana Perez | C15: All | D15: CONT | E15: USD | F15: CONT | I15: Net30 | J15: 0 | Q15: 0 | R15: Perez | U15: Admin | V15: Admin | AA15: No | AB15: No | AH15: No | AI15: No | AN15: No | AO15: No | AQ15: No | AR15: No | AT15: No | AV15: No | AW15: No | BG15: FirstMiddleLast | BH15: First name | BI15: Middle name | BJ15: Last name | BK15: None | BL15: 1 | BM15: 1 | BN15: 0 | BX15: 0 | BY15: 0 | CA15: 0 | CG15: 0 | CI15: 0
A16: 10000288 | B16: Paola Milian | C16: No | D16: CONT | E16: USD | F16: CONT | I16: Net30 | J16: 0 | Q16: 0 | R16: Milian | U16: Admin | V16: Admin | AA16: No | AB16: No | AH16: No | AI16: No | AN16: No | AO16: No | AQ16: No | AR16: No | AT16: No | AV16: No | AW16: No | BG16: FirstMiddleLast | BH16: First name | BI16: Middle name | BJ16: Last name | BK16: None | BL16: 1 | BM16: 1 | BN16: 0 | BX16: 0 | BY16: 0 | CA16: 0 | CG16: 0 | CI16: 0
A17: 10000300 | B17: Stephanie Hernandez | C17: No | D17: CONT | E17: COP | F17: CONT | I17: Net30 | J17: 0 | O17: Stephanie.Hernandez@rescue.org | Q17: 0 | R17: Hernandez | U17: Admin | V17: Admin | AA17: No | AB17: No | AH17: No | AI17: No | AN17: No | AO17: No | AQ17: No | AR17: No | AT17: No | AV17: No | AW17: No | BG17: FirstMiddleLast | BH17: First name | BI17: Middle name | BJ17: Last name | BK17: None | BL17: 1 | BM17: 1 | BN17: 0 | BX17: 0 | BY17: 0 | CA17: 0 | CG17: 0 | CI17: 0
A18: 10000317 | B18: Manuel Bello | C18: No | D18: CONT | E18: COP | F18: CONT | I18: Net30 | J18: 0 | O18: Manuel.Bello@rescue.org | Q18: 0 | R18: Bello | U18: Admin | V18: Admin | AA18: No | AB18: No | AH18: No | AI18: No | AN18: No | AO18: No | AQ18: No | AR18: No | AT18: No | AV18: No | AW18: No | BG18: FirstMiddleLast | BH18: First name | BI18: Middle name | BJ18: Last name | BK18: None | BL18: 1 | BM18: 1 | BN18: 0 | BX18: 0 | BY18: 0 | CA18: 0 | CG18: 0 | CI18: 0
A19: 10000327 | B19: Abogados IRC Colombia | C19: All | D19: CONT | E19: USD | F19: CONT | I19: Net30 | J19: 0 | O19: AbogadosIRC.Colombia@rescue.org | Q19: 0 | R19: Colombia | U19: Admin | V19: Admin | AA19: No | AB19: No | AH19: No | AI19: No | AN19: No | AO19: No | AQ19: No | AR19: No | AT19: No | AV19: No | AW19: No | BG19: FirstMiddleLast | BH19: First name | BI19: Middle name | BJ19: Last name | BK19: None | BL19: 1 | BM19: 1 | BN19: 0 | BX19: 0 | BY19: 0 | CA19: 0 | CG19: 0 | CI19: 0
A20: 10000331 | B20: ATG Action Translation Group SAS | C20: All except payment | D20: TRADE | E20: COP | F20: TRADE | G20: ProSvcs | H20: TranslateInterpret | I20: Net30 | J20: 30797.13 | K20: Carlos Javier Rivera Rojas | L20: +573005630873 | M20: 45775.112 | N20: Cleared | O20: atgtraducciones@gmail.com | P20: http://atgtraducciones.com/ | Q20: 999999999 | Y20: +573005630873 | AA20: No | AB20: No | AC20: Business 4COL | AD20: 000289693 | AH20: No | AI20: No | AN20: No | AO20: No | AQ20: No | AR20: No | AT20: No | AV20: Yes | AW20: No | AX20: Phone | AY20: shadrackom | AZ20: 45408.631 | BR20: LilianaPatricia BernalHerrera | BS20: 150727 | BT20: Admin | BU20: 44094.387 | BV20: Admin | BW20: 44094.387 | BX20: 5008.27 | BY20: 0 | CA20: 0 | CG20: 0 | CI20: 0 | CL20: Liliana.Bernal@rescue.org | CX20: en-US | DB20: Liliana Bernal
A21: 10000332 | B21: Alianza Fiduciaria SA Fideicomisos | C21: No | D21: TRADE | E21: COP | F21: TRADE | G21: Food Items | H21: Food Services | I21: Net30 | J21: 215634.63 | K21: Jesús Andrés Quintero Sánchez | L21: +5716447700 | M21: 45566.65 | N21: Cleared | O21: jequintero@alianza.com.co | P21: https://www.alianza.com.co/ | Q21: 999999999 | Y21: +5716447700 | AA21: No | AB21: No | AC21: Business 4COL | AD21: 000158837 | AH21: No | AI21: No | AN21: No | AO21: No | AQ21: No | AR21: No | AT21: No | AV21: Yes | AW21: No | AX21: Phone | AY21: KevinHu | AZ21: 44930.752 | BX21: 0 | BY21: 0 | CA21: 0 | CG21: 0 | CI21: 0
A22: 10000333 | B22: Blanco Santana Montiel & Rincón | C22: No | D22: TRADE | E22: USD | F22: TRADE | G22: ProSvcs | H22: Legal Services | I22: Net30 | J22: 113800.28 | K22: Maria Alejandra Blanco Blanco | L22: +5824242506417 | M22: 45497.392 | N22: Cleared | O22: mablanco@bsmr.com.ve | P22: https://www.bsmr.com.ve/ | Q22: 999999999 | Y22: +5824242506417 | AA22: No | AB22: No | AC22: Primary Contact | AD22: 000124731 | AH22: No | AI22: No | AN22: No | AO22: No | AQ22: No | AR22: No | AT22: No | AV22: Yes | AW22: No | AX22: Phone | AY22: KevinHu | AZ22: 44791.724 | BX22: 0 | BY22: 0 | CA22: 0 | CG22: 0 | CI22: 0
A23: 10000334 | B23: Camara de Comercio De Bogota | C23: No | D23: TRADE | E23: COP | F23: TRADE | I23: Net30 | J23: 0 | K23: Gustavo Aroca Cespedes | L23: +5713830300 | O23: gustavo.aroca@ccb.org.co | P23: https://www.ccb.org.co/ | Q23: 2400 | Y23: +5713830300 | AA23: No | AB23: No | AC23: Business 4COL | AD23: 000077782 | AH23: No | AI23: No | AN23: No | AO23: No | AQ23: No | AR23: No | AT23: No | AV23: Yes | AW23: No | AX23: Phone | AY23: iyanb | AZ23: 44743.981 | BX23: 0 | BY23: 0 | CA23: 0 | CG23: 0 | CI23: 0
A24: 10000335 | B24: Campamento La Milagrosa, CA | C24: All except payment | D24: TRADE | E24: USD | F24: TRADE | I24: Net30 | J24: 0 | K24: Luis Enrique Porras | L24: +582123396036 | M24: 44769.375 | N24: Expired | O24: lamilagrosa.kp@gmail.com | Q24: 19000 | Y24: +582123396036 | AA24: No | AB24: No | AC24: Business 4COL | AD24: 000077785 | AH24: No | AI24: No | AN24: No | AO24: No | AQ24: No | AR24: No | AT24: No | AV24: Yes | AW24: No | AX24: Phone | AY24: iyanb | AZ24: 44743.981 | BX24: 0 | BY24: 0 | CA24: 0 | CG24: 0 | CI24: 0
A25: 10000336 | B25: Club de Cazadores SA | C25: No | D25: TRADE | E25: COP | F25: TRADE | G25: ProSvcs | H25: Lodging | I25: Net30 | J25: 0 | K25: Manuel Guillermo Gil Quintero | L25: +5775751164 | M25: 45419.577 | N25: Cleared | O25: clubcazadorescucuta1@hotmail.com | P25: https://www.clubcazadores.com.co/ | Q25: 999999999 | Y25: +5775751164 | AA25: No | AB25: No | AC25: Business 4COL | AD25: 000191291 | AH25: No | AI25: No | AN25: No | AO25: No | AQ25: No | AR25: No | AT25: No | AV25: Yes | AW25: No | AX25: Phone | AY25: kimberlymag | AZ25: 45054.098 | BX25: 0 | BY25: 0 | CA25: 0 | CG25: 0 | CI25: 0
A26: 10000337 | B26: Comercializadora Distriaseo de Nariño SAS | C26: No | D26: TRADE | E26: COP | F26: TRADE | G26: Medical | H26: Medical Consumables | I26: Net30 | J26: 0 | K26: Leydi Yanira Eraso | L26: +573174960376 | M26: 45497.056 | N26: Cleared | O26: distriaseodenarino.sas@gmail.com | P26: https://distriaseodenar.negocio.site/ | Q26: 999999999 | Y26: +573174960376 | AA26: No | AB26: No | AC26: Business 4COL | AD26: 000122224 | AH26: No | AI26: No | AN26: No | AO26: No | AQ26: No | AR26: No | AT26: No | AV26: Yes | AW26: No | AX26: Phone | AY26: KevinHu | AZ26: 44783.679 | BX26: 0 | BY26: 0 | CA26: 0 | CG26: 0 | CI26: 0
A27: 10000338 | B27: Comercializadora Montes De Colombia SAS | C27: No | D27: TRADE | E27: COP | F27: TRADE | G27: OfficeSupl | H27: Office Supplies | I27: Net30 | J27: 0 | K27: Gregorio Higinio Garzon Jaimes | L27: +0113215061585 | M27: 45566.247 | N27: Cleared | O27: aerogarzo@hotmail.com | P27: https://www.superlosmontes.com/site/ | Q27: 999999999 | X27: 1283f04a-85e4-4b7e-b040-9ebdb852f2b1 | Y27: +0113215061585 | AA27: No | AB27: No | AC27: Business 4COL | AD27: 000227891 | AH27: No | AI27: No | AN27: No | AO27: No | AQ27: No | AR27: No | AT27: No | AV27: Yes | AW27: No | AX27: Phone | AY27: vincentng | AZ27: 45201.244 | BX27: 0 | BY27: 0 | CA27: 0 | CG27: 0 | CI27: 0
A28: 10000339 | B28: Comunidad de las Hermanas de la Caridad Dominicas de la Presentacion de la Santisima Virgen | C28: No | D28: TRADE | E28: COP | F28: TRADE | G28: Facilities | H28: RealEstateLeaseRent | I28: Net30 | J28: 0 | K28: Hna. BlancaMargarita Duque Lopez | L28: +573168255459 | M28: 45465.997 | N28: Cleared | O28: bmduque@hotmail.com | Q28: 999999999 | Y28: +573168255459 | AA28: No | AB28: No | AC28: Business 4COL | AD28: 000202491 | AH28: No | AI28: No | AN28: No | AO28: No | AQ28: No | AR28: No | AT28: No | AV28: Yes | AW28: No | AX28: Phone | AY28: KevinHu | AZ28: 45103.35 | BR28: Oscar Valderrama | BS28: 146055 | BT28: UPagola | BU28: 43774.568 | BV28: UPagola | BW28: 43774.568 | BX28: 5706.73 | BY28: 0 | CA28: 0 | CG28: 0 | CI28: 0 | CL28: Oscar.Valderrama@rescue.org | CX28: en-US | DB28: Oscar Valderrama
A29: 10000340 | B29: Corporacion Parque Explora | C29: No | D29: TRADE | E29: COP | F29: TRADE | I29: Net30 | J29: 0 | K29: Monica Escobar | L29: +5715168300 | O29: monica.escobar@parqueexplora.org | P29: https://www.parqueexplora.org/ | Q29: 2400 | Y29: +5715168300 | AA29: No | AB29: No | AC29: Business 4COL | AD29: 000077798 | AH29: No | AI29: No | AN29: No | AO29: No | AQ29: No | AR29: No | AT29: No | AV29: Yes | AW29: No | AX29: Phone | AY29: iyanb | AZ29: 44743.981 | BX29: 0 | BY29: 0 | CA29: 0 | CG29: 0 | CI29: 0
A30: 10000341 | B30: Del Mar Abogados SAS | C30: No | D30: TRADE | E30: COP | F30: TRADE | G30: ProSvcs | H30: Legal Services | I30: Net30 | J30: 34835.78 | K30: Caroline Del Mar Gallardo Rojas | L30: +5713221386 | M30: 45477.556 | N30: Cleared | O30: caroline@grupodelmar.com | P30: https://www.grupodelmar.com/ | Q30: 999999999 | Y30: +5713221386 | AA30: No | AB30: No | AC30: Business 4COL | AD30: 000205105 | AH30: No | AI30: No | AN30: No | AO30: No | AQ30: No | AR30: No | AT30: No | AV30: Yes | AW30: No | AX30: Phone | AY30: sophyo | AZ30: 45112.24 | BX30: 0 | BY30: 0 | CA30: 0 | CG30: 0 | CI30: 0
A31: 10000342 | B31: Delicias Aguitas, CA | C31: No | D31: TRADE | E31: COP | F31: TRADE | G31: ProSvcs | H31: Consultancy | I31: Net30 | J31: 0 | K31: Alexandra Reina Taurel Beracasa | L31: +582122329039 | M31: 45465.997 | N31: Cleared | O31: deliciasaguitas@gmail.com | Q31: 999999999 | Y31: +582122329039 | AA31: No | AB31: No | AC31: Business 4COL | AD31: 000202043 | AH31: No | AI31: No | AN31: No | AO31: No | AQ31: No | AR31: No | AT31: No | AV31: Yes | AW31: No | AX31: Phone | AY31: kimberlymag | AZ31: 45100.343 | BR31: Oscar Valderrama | BS31: 146055 | BT31: UPagola | BU31: 43774.568 | BV31: UPagola | BW31: 43774.568 | BX31: 5706.73 | BY31: 0 | CA31: 0 | CG31: 0 | CI31: 0 | CL31: Oscar.Valderrama@rescue.org | CX31: en-US | DB31: Oscar Valderrama
A32: 10000343 | B32: Docuxer Sociedad por Acciones Simplificada | C32: No | D32: TRADE | E32: COP | F32: TRADE | G32: Technology | H32: Equipment or Devices | I32: Net30 | J32: 2188.47 | K32: Monica Patricia Lobo acuna | L32: +573167430292 | M32: 45498.594 | N32: Cleared | O32: monica.lobo@docuxer.com | P32: https://www.docuxer.com/ | Q32: 999999999 | Y32: +573167430292 | AA32: No | AB32: No | AC32: Primary Number 4COL | AD32: 000128068 | AH32: No | AI32: No | AN32: No | AO32: No | AQ32: No | AR32: No | AT32: No | AV32: Yes | AW32: No | AX32: Phone | AY32: KevinHu | AZ32: 44805.61 | BX32: 0 | BY32: 0 | CA32: 0 | CG32: 0 | CI32: 0
A33: 10000344 | B33: Empresa Social Del Estado - Metrosalud | C33: No | D33: TRADE | E33: COP | F33: TRADE | G33: Medical | H33: Medical Consumables | I33: Net30 | J33: 2978.24 | K33: Valentina Sosa Carvajal | L33: +5760455117505 | M33: 45497.059 | N33: Cleared | O33: gerencia@metrosalud.gov.co | P33: http://www.metrosalud.gov.co/ | Q33: 999999999 | Y33: +5760455117505 | AA33: No | AB33: No | AC33: Primary Contact | AD33: 000207777 | AH33: No | AI33: No | AN33: No | AO33: No | AQ33: No | AR33: No | AT33: No | AV33: Yes | AW33: No | AX33: Phone | AY33: vincentng | AZ33: 45121.142 | BX33: 0 | BY33: 0 | CA33: 0 | CG33: 0 | CI33: 0
A34: 10000345 | B34: Fundacion Artesanos De Sueños | C34: No | D34: TRADE | E34: COP | F34: TRADE | G34: Food Items | H34: Misc Food Items | I34: Net30 | J34: 0 | K34: Marisol Alvarez Munevar | L34: +573142830180 | M34: 45465.997 | N34: Cleared | O34: fundacionartesanosdesuenos@gmail.com | P34: https://www.fundacionartesanosdesuenos.org/ | Q34: 999999999 | Y34: +573142830180 | AA34: No | AB34: No | AC34: Business 4COL | AD34: 000219731 | AH34: No | AI34: No | AN34: No | AO34: No | AQ34: No | AR34: No | AT34: No | AV34: Yes | AW34: No | AX34: Phone | AY34: KevinHu | AZ34: 45166.41 | BR34: Oscar Valderrama | BS34: 146055 | BT34: UPagola | BU34: 43774.568 | BV34: UPagola | BW34: 43774.568 | BX34: 5706.73 | BY34: 0 | CA34: 0 | CG34: 0 | CI34: 0 | CL34: Oscar.Valderrama@rescue.org | CX34: en-US | DB34: Oscar Valderrama
A35: 10000346 | B35: Global Operadora Hotelera SAS | C35: No | D35: TRADE | E35: COP | F35: TRADE | G35: Travel Svc | H35: Food Services | I35: Net30 | J35: 599.5 | K35: Milena Mosquera | L35: +3102394883 | M35: 45489.747 | N35: Cleared | O35: ventas2@embassy-bogota.com.co | P35: www.bogota.embassysuites.com | Q35: 19000 | X35: ca6695fe-ba75-4d2c-81cd-68da272bdefe | Y35: +3102394883 | AA35: No | AB35: No | AC35: Business 4COL | AD35: 000230101 | AH35: No | AI35: No | AN35: No | AO35: No | AQ35: No | AR35: No | AT35: No | AV35: Yes | AW35: No | AX35: Phone | AY35: KevinHu | AZ35: 45210.356 | BX35: 0 | BY35: 0 | CA35: 0 | CG35: 0 | CI35: 0
A36: 10000347 | B36: Integral Group MHL, CA | C36: All except payment | D36: TRADE | E36: USD | F36: TRADE | I36: Net30 | J36: 0 | K36: Michelle Maria Lemoine | L36: +584143211830 | M36: 44768.375 | N36: Expired | O36: michele.lemoine1@gmail.com | Q36: 19000 | Y36: +584143211830 | AA36: No | AB36: No | AC36: Business 4COL | AD36: 000077818 | AH36: No | AI36: No | AN36: No | AO36: No | AQ36: No | AR36: No | AT36: No | AV36: Yes | AW36: No | AX36: Phone | AY36: iyanb | AZ36: 44743.981 | BX36: 0 | BY36: 0 | CA36: 0 | CG36: 0 | CI36: 0
A37: 10000348 | B37: Inversiones Pikachu 77 CA | C37: No | D37: TRADE | E37: USD | F37: TRADE | G37: Construct | H37: Construction Svcs | I37: Net30 | J37: 15237.59 | K37: Carlos Jose Peña Brice | L37: +584142523171 | M37: 45615.636 | N37: Cleared | O37: bricecarlo@gmail.com | Q37: 999999999 | Y37: +584142523171 | AA37: No | AB37: No | AC37: Business 4COL | AD37: 000247243 | AH37: No | AI37: No | AN37: No | AO37: No | AQ37: No | AR37: No | AT37: No | AV37: Yes | AW37: No | AX37: Phone | AY37: shadrackom | AZ37: 45250.392 | BR37: Melix Carolina Acevedo Moreno | BS37: 155600 | BT37: Admin | BU37: 44300.443 | BV37: Admin | BW37: 44300.443 | BX37: 193.17 | BY37: 0 | CA37: 0 | CG37: 0 | CI37: 0 | CL37: Melix.Acevedo@rescue.org | CX37: en-US | DB37: Melix Acevedo
A38: 10000349 | B38: Muebles y Plasticos SAS | C38: All except payment | D38: TRADE | E38: COP | F38: TRADE | I38: Net30 | J38: 0 | K38: Hugo Fernando Garcia | L38: +5714030303 | M38: 44788.375 | N38: Expired | O38: compumuebles@compumuebles.com | P38: https://compumuebles.com/ | Q38: 19000 | Y38: +5714030303 | AA38: No | AB38: No | AC38: Business 4COL | AD38: 000077822 | AH38: No | AI38: No | AN38: No | AO38: No | AQ38: No | AR38: No | AT38: No | AV38: Yes | AW38: No | AX38: Phone | AY38: iyanb | AZ38: 44743.981 | BX38: 0 | BY38: 0 | CA38: 0 | CG38: 0 | CI38: 0
A39: 10000350 | B39: Multisuministros Nissi SAS | C39: No | D39: TRADE | E39: COP | F39: TRADE | G39: OfficeSupl | H39: Misc Consumables | I39: Net30 | J39: 247.29 | K39: Hernan Camilo Escobar | L39: +573152869071 | M39: 45497.396 | N39: Cleared | O39: multisuministrosnissi@gmail.com | Q39: 999999999 | Y39: +573152869071 | AA39: No | AB39: No | AC39: Primary Number 4COL | AD39: 000124734 | AH39: No | AI39: No | AN39: No | AO39: No | AQ39: No | AR39: No | AT39: No | AV39: Yes | AW39: No | AX39: Phone | AY39: KevinHu | AZ39: 44791.753 | BX39: 0 | BY39: 0 | CA39: 0 | CG39: 0 | CI39: 0
A40: 10000351 | B40: Organización Terpel SA | C40: No | D40: TRADE | E40: COP | F40: TRADE | I40: Net30 | J40: 1337.11 | K40: Carlos Arturo Prada Perez | L40: +573185215187 | M40: 45566.39 | N40: Cleared | O40: carlos.prada@terpel.com | P40: https://www.terpel.com/ | Q40: 999999999 | Y40: +573185215187 | AA40: No | AB40: No | AC40: Business 4COL | AD40: 000227754 | AH40: No | AI40: No | AN40: No | AO40: No | AQ40: No | AR40: No | AT40: No | AV40: Yes | AW40: No | AX40: Phone | AY40: sophyo | AZ40: 45201.101 | BX40: 0 | BY40: 0 | CA40: 0 | CG40: 0 | CI40: 0
A41: 10000352 | B41: Papeleria El Cid SAS | C41: No | D41: TRADE | E41: COP | F41: TRADE | G41: Equipment | H41: Equipment or Devices | I41: Net30 | J41: 786.6 | K41: Fabian Tamayo Carvajal | L41: +574489411 | M41: 45465.146 | N41: Cleared | O41: ventas3@papelcid.com | P41: https://www.elcidpapeleria.com/inicio | Q41: 19000 | Y41: +574489411 | AA41: No | AB41: No | AC41: Primary Contact | AD41: 000201950 | AH41: No | AI41: No | AN41: No | AO41: No | AQ41: No | AR41: No | AT41: No | AV41: Yes | AW41: No | AX41: Phone | AY41: kimberlymag | AZ41: 45100.232 | BR41: Jeimy Guerrero | BS41: 166795 | BT41: Admin | BU41: 44690.599 | BV41: Admin | BW41: 44690.599 | BX41: 943.54 | BY41: 0 | CA41: 0 | CG41: 0 | CI41: 0 | CL41: Jeimy.Guerrero@rescue.org | CP41: jeimy | CX41: en-US | CZ41: guerrero | DB41: jeimy guerrero
A42: 10000353 | B42: People Pass SA | C42: No | D42: TRADE | E42: COP | F42: TRADE | G42: Travel Svc | H42: Customs Clearance | I42: Net30 | J42: 1933.73 | K42: Edwin Alberto Parra Moncada Parra Moncada | L42: +573173836054 | M42: 45497.396 | N42: Cleared | O42: edwin.parra@peoplepass.com.co | P42: https://www.peoplepass.com.co/ | Q42: 999999999 | Y42: +573173836054 | AA42: No | AB42: No | AC42: Business 4COL | AD42: 000124733 | AH42: No | AI42: No | AN42: No | AO42: No | AQ42: No | AR42: No | AT42: No | AV42: Yes | AW42: No | AX42: Phone | AY42: KevinHu | AZ42: 44791.752 | BX42: 0 | BY42: 0 | CA42: 0 | CG42: 0 | CI42: 0
A43: 10000354 | B43: Prinntech SAS | C43: No | D43: TRADE | E43: COP | F43: TRADE | G43: Technology | H43: Technology Services | I43: Net30 | J43: 225.35 | K43: Carolina Garcia | L43: +5717432931 | M43: 45449.563 | N43: Cleared | O43: carolina.garcia@prinntech.com | P43: http://www.prinntech.com/ | Q43: 2400 | Y43: +5717432931 | AA43: No | AB43: No | AC43: Business 4COL | AD43: 000197987 | AH43: No | AI43: No | AN43: No | AO43: No | AQ43: No | AR43: No | AT43: No | AV43: Yes | AW43: No | AX43: Phone | AY43: kimberlymag | AZ43: 45084.113 | BR43: Ronny Candelo | BS43: 155389 | BT43: Admin | BU43: 44285.452 | BV43: Admin | BW43: 44285.452 | BX43: 1334 | BY43: 0 | CA43: 0 | CG43: 0 | CI43: 0 | CL43: Ronny.Candelo@rescue.org | CX43: en-US | DB43: Ronny Candelo
A44: 10000355 | B44: Prosegur Vigilancia y Seguridad Privada LTDA | C44: No | D44: TRADE | E44: COP | F44: TRADE | I44: Net30 | J44: 397.9 | K44: Jonathan Cortes | L44: +573232202544 | O44: jonathan.cortes@prosegur.com | P44: https://www.prosegur.com/ | Q44: 2400 | Y44: +573232202544 | AA44: No | AB44: No | AC44: Business 4COL | AD44: 000077839 | AH44: No | AI44: No | AN44: No | AO44: No | AQ44: No | AR44: No | AT44: No | AV44: Yes | AW44: No | AX44: Phone | AY44: iyanb | AZ44: 44743.981 | BX44: 0 | BY44: 0 | CA44: 0 | CG44: 0 | CI44: 0
A45: 10000356 | B45: Prosuministros de Colombia SAS | C45: No | D45: TRADE | E45: COP | F45: TRADE | G45: Technology | H45: Value Added Reseller | I45: Net30 | J45: 42755.48 | K45: Daniel Felipe Valbuena Cubides | L45: +573204170057 | M45: 45497.059 | N45: Cleared | O45: gerencia@prosuministros.com | P45: https://prosuministros.com/ | Q45: 999999999 | Y45: +573204170057 | AA45: No | AB45: No | AC45: Business 4COL | AD45: 000205037 | AH45: No | AI45: No | AN45: No | AO45: No | AQ45: No | AR45: No | AT45: No | AV45: Yes | AW45: No | AX45: Phone | AY45: sophyo | AZ45: 45112.136 | BX45: 0 | BY45: 0 | CA45: 0 | CG45: 0 | CI45: 0
A46: 10000357 | B46: Rosero, Moscoso & Asociados | C46: No | D46: TRADE | E46: COP | F46: TRADE | G46: ProSvcs | H46: Legal Services | I46: Net30 | J46: 0 | K46: Eduardo Rosero Alban | L46: +593995270410 | M46: 45534.202 | N46: Cleared | O46: erosero@rma.pro.ec | P46: https://rma.pro.ec/ | Q46: 999999999 | Y46: +593995270410 | AA46: No | AB46: No | AC46: Business 4COL | AD46: 000220163 | AH46: No | AI46: No | AN46: No | AO46: No | AQ46: No | AR46: No | AT46: No | AV46: Yes | AW46: No | AX46: Phone | AY46: kimberlymag | AZ46: 45168.139 | BX46: 0 | BY46: 0 | CA46: 0 | CG46: 0 | CI46: 0
A47: 10000358 | B47: SC Service Servicios De Confianza SAS | C47: No | D47: TRADE | E47: COP | F47: TRADE | G47: Vehicles | H47: Cars and Trucks | I47: Net30 | J47: 0 | K47: Rafael Eduardo Yanet Sanchez | L47: +573164031622 | M47: 45533.702 | N47: Cleared | O47: scserviciosdeconfianzasas@gmail.com | Q47: 999999999 | Y47: +573164031622 | AA47: No | AB47: No | AC47: Business 4COL | AD47: 000220165 | AH47: No | AI47: No | AN47: No | AO47: No | AQ47: No | AR47: No | AT47: No | AV47: Yes | AW47: No | AX47: Phone | AY47: kimberlymag | AZ47: 45168.141 | BX47: 0 | BY47: 0 | CA47: 0 | CG47: 0 | CI47: 0
A48: 10000359 | B48: Servicios Integrales y Suministros Candelas | C48: All except payment | D48: TRADE | E48: USD | F48: TRADE | G48: Travel Svc | H48: Transportation | I48: Net30 | J48: 0 | K48: Jose Luis Chacon Candelas | L48: +542763442705 | M48: 45243.65 | N48: Expired | O48: siscan.ve@gmail.com | Q48: 999999999 | Y48: +542763442705 | AA48: No | AB48: No | AC48: Primary Contact | AD48: 000222271 | AH48: No | AI48: No | AN48: No | AO48: No | AQ48: No | AR48: No | AT48: No | AV48: Yes | AW48: No | AX48: Phone | AY48: KevinHu | AZ48: 45175.799 | BX48: 0 | BY48: 0 | CA48: 0 | CG48: 0 | CI48: 0
A49: 10000360 | B49: Sodexho Pass Venezuela, CA | C49: All except payment | D49: CASH | E49: USD | F49: CASH | I49: Net30 | J49: 0 | K49: Lisbeth Mayra Alvarez | L49: +584141504277 | M49: 44788.375 | N49: Expired | O49: Lisbeth.ALVAREZ@sodexo.com | P49: https://www.sodexo.com.ve/ | Q49: 19000 | Y49: +584141504277 | AA49: No | AB49: No | AC49: Business 4COL | AD49: 000077852 | AH49: No | AI49: No | AN49: No | AO49: No | AQ49: No | AR49: No | AT49: No | AV49: Yes | AW49: No | AX49: Phone | AY49: iyanb | AZ49: 44743.981 | BX49: 0 | BY49: 0 | CA49: 0 | CG49: 0 | CI49: 0
A50: 10000361 | B50: Suministros Anvi, CA | C50: All except payment | D50: TRADE | E50: USD | F50: TRADE | I50: Net30 | J50: 0 | K50: Lisbeth Del Valle Amundarain | L50: +584123279060 | M50: 44768.375 | N50: Expired | O50: suministrosanvi@gmail.com | Q50: 19000 | Y50: +584123279060 | AA50: No | AB50: No | AC50: Business 4COL | AD50: 000077855 | AH50: No | AI50: No | AN50: No | AO50: No | AQ50: No | AR50: No | AT50: No | AV50: Yes | AW50: No | AX50: Phone | AY50: iyanb | AZ50: 44743.981 | BX50: 0 | BY50: 0 | CA50: 0 | CG50: 0 | CI50: 0
A51: 10000362 | B51: Surtidora Institucional SAS | C51: No | D51: TRADE | E51: COP | F51: TRADE | G51: Equipment | H51: Equipment or Devices | I51: Net30 | J51: 2948.93 | K51: Liliana Rocio Madariaga | L51: +573173696146 | M51: 45625.608 | N51: Cleared | O51: ventas7@surtidorainstitucional.com.co | P51: https://www.surtidorainstitucional.com.co/ | Q51: 999999999 | Y51: +573173696146 | AA51: No | AB51: No | AC51: Primary Contact | AD51: 000251857 | AH51: No | AI51: No | AN51: No | AO51: No | AQ51: No | AR51: No | AT51: No | AV51: Yes | AW51: No | AX51: Phone | AY51: vincentng | AZ51: 45259.242 | BR51: Dayana Carolina Moronta Correa | BS51: 150360 | BT51: Admin | BU51: 44076.287 | BV51: Admin | BW51: 44076.287 | BX51: 844.81 | BY51: 0 | CA51: 0 | CG51: 0 | CI51: 0 | CL51: Dayana.Moronta@rescue.org | CX51: en-US | DB51: Dayana Moronta
A52: 10000363 | B52: Tannus & Asociados SAS | C52: No | D52: TRADE | E52: COP | F52: TRADE | I52: Net30 | J52: 309.77 | K52: Rodrigo Eduardo Tannus Serrano | L52: +573115069125 | O52: rtannus@tannus.co | P52: http://tannus.co/es/ | Q52: 2400 | Y52: +573115069125 | AA52: No | AB52: No | AC52: Business 4COL | AD52: 000077860 | AH52: No | AI52: No | AN52: No | AO52: No | AQ52: No | AR52: No | AT52: No | AV52: Yes | AW52: No | AX52: Phone | AY52: iyanb | AZ52: 44743.981 | BX52: 0 | BY52: 0 | CA52: 0 | CG52: 0 | CI52: 0
A53: 10000364 | B53: Cooperativa de Transportadores Tax Coopebombas LTDA | C53: No | D53: TRADE | E53: COP | F53: TRADE | G53: Travel Svc | H53: Transportation | I53: Net30 | J53: 11997.45 | K53: Sebastian Zapata Restrepo | L53: +57604514243 | M53: 45643.688 | N53: Cleared | P53: https://www.coopebombas.com/ | Q53: 999999999 | Y53: +57604514243 | AA53: No | AB53: No | AC53: Business 4COL | AD53: 000257513 | AH53: No | AI53: No | AN53: No | AO53: No | AQ53: No | AR53: No | AT53: No | AV53: Yes | AW53: No | AX53: Phone | AY53: sophyo | AZ53: 45278.055 | BX53: 0 | BY53: 0 | CA53: 0 | CG53: 0 | CI53: 0
A54: 10000365 | B54: Tornicentro Group SAS | C54: No | D54: TRADE | E54: COP | F54: TRADE | G54: Construct | H54: Construction Svcs | I54: Net30 | J54: 46.4 | K54: Julian David Madero Amado | L54: +573132935061 | M54: 45497.059 | N54: Cleared | O54: julianmadero@tornicentro.com.co | P54: https://www.tornicentro.com.co/ | Q54: 999999999 | Y54: +573132935061 | AA54: No | AB54: No | AC54: Business 4COL | AD54: 000122891 | AH54: No | AI54: No | AN54: No | AO54: No | AQ54: No | AR54: No | AT54: No | AV54: Yes | AW54: No | AX54: Phone | AY54: KevinHu | AZ54: 44784.835 | BX54: 0 | BY54: 0 | CA54: 0 | CG54: 0 | CI54: 0
A55: 10000366 | B55: Amparo Rangel De Castañeda | C55: All except payment | D55: TRADE | E55: COP | F55: TRADE | I55: Net30 | J55: 0 | K55: Amparo Rangel De Catañeda | L55: +573102661899 | M55: 44748.375 | N55: Expired | O55: amparito.ra@hotmail.com | Q55: 19000 | R55: De Castañeda | T55: Rangel | U55: iyanb | V55: iyanb | Y55: +573102661899 | AA55: No | AB55: No | AC55: Business 4COL | AD55: 000077869 | AH55: No | AI55: No | AN55: No | AO55: No | AQ55: No | AR55: No | AT55: No | AV55: Yes | AW55: No | AX55: Phone | AY55: iyanb | AZ55: 44743.981 | BG55: FirstMiddleLast | BH55: First name | BI55: Middle name | BJ55: Last name | BK55: None | BL55: 1 | BM55: 1 | BN55: 0 | BX55: 0 | BY55: 0 | CA55: 0 | CG55: 0 | CI55: 0
A56: 10000367 | B56: Armando Agustin Revelo Martinez | C56: No | D56: TRADE | E56: COP | F56: TRADE | G56: ProSvcs | H56: Consultancy | I56: Net30 | J56: 0 | K56: Armando Agustin Revelo | L56: +573155029690 | M56: 45497.396 | N56: Cleared | O56: armandoreplay@gmail.com | Q56: 999999999 | R56: Revelo Martinez | T56: Agustin | U56: iyanb | V56: iyanb | Y56: +573155029690 | AA56: No | AB56: No | AC56: Business 4COL | AD56: 000210888 | AH56: No | AI56: No | AN56: No | AO56: No | AQ56: No | AR56: No | AT56: No | AV56: Yes | AW56: No | AX56: Phone | AY56: vincentng | AZ56: 45132.06 | BG56: FirstMiddleLast | BH56: First name | BI56: Middle name | BJ56: Last name | BK56: None | BL56: 1 | BM56: 1 | BN56: 0 | BX56: 0 | BY56: 0 | CA56: 0 | CG56: 0 | CI56: 0
A57: 10000368 | B57: Camilo Andres Salamanca Alvarez | C57: All except payment | D57: TRADE | E57: COP | F57: TRADE | I57: Net30 | J57: 2.26 | K57: Camilo Andres Salamanca Alvarez | L57: +573153610772 | M57: 45243.653 | N57: Expired | O57: salamanca.camilo@gmail.com | Q57: 999999999 | R57: Salamanca Alvarez | T57: Andres | U57: iyanb | V57: iyanb | Y57: +573153610772 | AA57: No | AB57: No | AC57: Business 4COL | AD57: 000143628 | AH57: No | AI57: No | AN57: No | AO57: No | AQ57: No | AR57: No | AT57: No | AV57: Yes | AW57: No | AX57: Phone | AY57: amadouf | AZ57: 44876.452 | BG57: FirstMiddleLast | BH57: First name | BI57: Middle name | BJ57: Last name | BK57: None | BL57: 1 | BM57: 1 | BN57: 0 | BX57: 0 | BY57: 0 | CA57: 0 | CG57: 0 | CI57: 0
A58: 10000369 | B58: Carlos Alberto Molinares Rovira | C58: No | D58: TRADE | E58: COP | F58: TRADE | G58: Safety | I58: Net30 | J58: 0 | K58: Carlos Alberto Molinares Rovira | L58: +573102772300 | M58: 45497.4 | N58: Cleared | O58: carlosmolinares15@gmail.com | Q58: 999999999 | R58: Molinares Rovira | T58: Alberto | U58: iyanb | V58: iyanb | Y58: +573102772300 | AA58: No | AB58: No | AC58: Business 4COL | AD58: 000124743 | AH58: No | AI58: No | AN58: No | AO58: No | AQ58: No | AR58: No | AT58: No | AV58: Yes | AW58: No | AX58: Phone | AY58: KevinHu | AZ58: 44791.78 | BG58: FirstMiddleLast | BH58: First name | BI58: Middle name | BJ58: Last name | BK58: None | BL58: 1 | BM58: 1 | BN58: 0 | BX58: 0 | BY58: 0 | CA58: 0 | CG58: 0 | CI58: 0
A59: 10000370 | B59: Celmira Quintero Carrillo | C59: No | D59: TRADE | E59: COP | F59: TRADE | G59: Food Items | H59: Food Services | I59: Net30 | J59: 0 | K59: Celmira Quintero Carrillo | L59: +573178868531 | M59: 45465.997 | N59: Cleared | O59: celmiraquinterocarrillo@gmail.com | Q59: 999999999 | R59: Carrillo | T59: Quintero | U59: iyanb | V59: iyanb | Y59: +573178868531 | AA59: No | AB59: No | AC59: Business 4COL | AD59: 000202054 | AH59: No | AI59: No | AN59: No | AO59: No | AQ59: No | AR59: No | AT59: No | AV59: Yes | AW59: No | AX59: Phone | AY59: kimberlymag | AZ59: 45100.35 | BG59: FirstMiddleLast | BH59: First name | BI59: Middle name | BJ59: Last name | BK59: None | BL59: 1 | BM59: 1 | BN59: 0 | BR59: Oscar Valderrama | BS59: 146055 | BT59: UPagola | BU59: 43774.568 | BV59: UPagola | BW59: 43774.568 | BX59: 5706.73 | BY59: 0 | CA59: 0 | CG59: 0 | CI59: 0 | CL59: Oscar.Valderrama@rescue.org | CX59: en-US | DB59: Oscar Valderrama
A60: 10000371 | B60: Cristian Camilo Poveda Leon | C60: No | D60: TRADE | E60: COP | F60: TRADE | I60: Net30 | J60: 1127.02 | K60: Cristian Camilo Poveda Leon | L60: +573112839718 | O60: camilolion55@gmail.com | Q60: 2400 | R60: Poveda Leon | T60: Camilo | U60: iyanb | V60: iyanb | Y60: +573112839718 | AA60: No | AB60: No | AC60: Business 4COL | AD60: 000077879 | AH60: No | AI60: No | AN60: No | AO60: No | AQ60: No | AR60: No | AT60: No | AV60: Yes | AW60: No | AX60: Phone | AY60: iyanb | AZ60: 44743.981 | BG60: FirstMiddleLast | BH60: First name | BI60: Middle name | BJ60: Last name | BK60: None | BL60: 1 | BM60: 1 | BN60: 0 | BX60: 0 | BY60: 0 | CA60: 0 | CG60: 0 | CI60: 0
A61: 10000372 | B61: Gerson Alexis Omaña Maldonado | C61: No | D61: TRADE | E61: COP | F61: TRADE | G61: OfficeSupl | H61: Misc Consumables | I61: Net30 | J61: 492.89 | K61: Gerson Alexis Omaña | L61: +573122591121 | M61: 45497.4 | N61: Cleared | O61: gersonoma@gmail.com | Q61: 999999999 | R61: Omaña Maldonado | T61: Alexis | U61: iyanb | V61: iyanb | Y61: +573122591121 | AA61: No | AB61: No | AC61: Business 4COL | AD61: 000124744 | AH61: No | AI61: No | AN61: No | AO61: No | AQ61: No | AR61: No | AT61: No | AV61: Yes | AW61: No | AX61: Phone | AY61: KevinHu | AZ61: 44791.782 | BG61: FirstMiddleLast | BH61: First name | BI61: Middle name | BJ61: Last name | BK61: None | BL61: 1 | BM61: 1 | BN61: 0 | BX61: 0 | BY61: 0 | CA61: 0 | CG61: 0 | CI61: 0
A62: 10000373 | B62: Gilda Maria Otero De Niño | C62: No | D62: TRADE | E62: COP | F62: TRADE | G62: Facilities | H62: RealEstateLeaseRent | I62: Net30 | J62: 10482 | K62: Gilda Maria Otero De Niño | L62: +573002204939 | M62: 45497.198 | N62: Cleared | O62: gildaoteroj@yahoo.es | Q62: 999999999 | R62: Otero De Niño | T62: Maria | U62: iyanb | V62: iyanb | Y62: +573002204939 | AA62: No | AB62: No | AC62: Business 4COL | AD62: 000210703 | AH62: No | AI62: No | AN62: No | AO62: No | AQ62: No | AR62: No | AT62: No | AV62: Yes | AW62: No | AX62: Phone | AY62: sophyo | AZ62: 45131.311 | BG62: FirstMiddleLast | BH62: First name | BI62: Middle name | BJ62: Last name | BK62: None | BL62: 1 | BM62: 1 | BN62: 0 | BR62: Oscar Valderrama | BS62: 146055 | BT62: UPagola | BU62: 43774.568 | BV62: UPagola | BW62: 43774.568 | BX62: 5706.73 | BY62: 0 | CA62: 0 | CG62: 0 | CI62: 0 | CL62: Oscar.Valderrama@rescue.org | CX62: en-US | DB62: Oscar Valderrama
A63: 10000374 | B63: Jaime Eduardo Castellanos Villalba | C63: No | D63: TRADE | E63: COP | F63: TRADE | G63: ProSvcs | H63: MiscManualLaborSvcs | I63: Net30 | J63: 0 | K63: Jaime Eduardo Castellanos | L63: +573108522267 | M63: 45534.205 | N63: Cleared | O63: jecv@fumicast.com | P63: www.fumicast.com | Q63: 999999999 | R63: Castellanos Villalba | T63: Eduardo | U63: iyanb | V63: iyanb | Y63: +573108522267 | AA63: No | AB63: No | AC63: Primary Contact | AD63: 000220170 | AH63: No | AI63: No | AN63: No | AO63: No | AQ63: No | AR63: No | AT63: No | AV63: Yes | AW63: No | AX63: Phone | AY63: kimberlymag | AZ63: 45168.146 | BG63: FirstMiddleLast | BH63: First name | BI63: Middle name | BJ63: Last name | BK63: None | BL63: 1 | BM63: 1 | BN63: 0 | BX63: 0 | BY63: 0 | CA63: 0 | CG63: 0 | CI63: 0
A64: 10000375 | B64: Javier Orlando Gomez Aguilar | C64: No | D64: TRADE | E64: COP | F64: TRADE | I64: Net30 | J64: 0 | K64: Javier Orlando Gomez Aguilar | L64: +573108791298 | O64: gyrservice@outlook.com | Q64: 2400 | R64: Gomez Aguilar | T64: Orlando | U64: iyanb | V64: iyanb | Y64: +573108791298 | AA64: No | AB64: No | AC64: Business 4COL | AD64: 000077887 | AH64: No | AI64: No | AN64: No | AO64: No | AQ64: No | AR64: No | AT64: No | AV64: Yes | AW64: No | AX64: Phone | AY64: iyanb | AZ64: 44743.981 | BG64: FirstMiddleLast | BH64: First name | BI64: Middle name | BJ64: Last name | BK64: None | BL64: 1 | BM64: 1 | BN64: 0 | BX64: 0 | BY64: 0 | CA64: 0 | CG64: 0 | CI64: 0
A65: 10000376 | B65: Luz Jaidive Murillo Munar | C65: No | D65: TRADE | E65: COP | F65: TRADE | I65: Net30 | J65: 0 | K65: Luz Jaidive Murillo Munar | L65: +573168661994 | O65: casa.diamante@hotmail.com | Q65: 2400 | R65: Murillo Munar | T65: Jaidive | U65: iyanb | V65: iyanb | Y65: +573168661994 | AA65: No | AB65: No | AC65: Business 4COL | AD65: 000077889 | AH65: No | AI65: No | AN65: No | AO65: No | AQ65: No | AR65: No | AT65: No | AV65: Yes | AW65: No | AX65: Phone | AY65: iyanb | AZ65: 44743.981 | BG65: FirstMiddleLast | BH65: First name | BI65: Middle name | BJ65: Last name | BK65: None | BL65: 1 | BM65: 1 | BN65: 0 | BX65: 0 | BY65: 0 | CA65: 0 | CG65: 0 | CI65: 0
A66: 10000377 | B66: Marcel Ferley Leyton | C66: No | D66: TRADE | E66: COP | F66: TRADE | G66: ProSvcs | H66: Equipment or Devices | I66: Net30 | J66: 0 | K66: Margarita Ortiz Millan | L66: +573212003535 | M66: 45534.247 | N66: Cleared | O66: mundofrio88@hotmail.com | Q66: 999999999 | R66: Leyton | T66: Ferley | U66: iyanb | V66: iyanb | Y66: +573212003535 | AA66: No | AB66: No | AC66: Primary Contact | AD66: 000220177 | AH66: No | AI66: No | AN66: No | AO66: No | AQ66: No | AR66: No | AT66: No | AV66: Yes | AW66: No | AX66: Phone | AY66: kimberlymag | AZ66: 45168.153 | BG66: FirstMiddleLast | BH66: First name | BI66: Middle name | BJ66: Last name | BK66: None | BL66: 1 | BM66: 1 | BN66: 0 | BX66: 0 | BY66: 0 | CA66: 0 | CG66: 0 | CI66: 0
A67: 10000378 | B67: Marco Tulio Gonzalez | C67: No | D67: TRADE | E67: COP | F67: TRADE | G67: Facilities | H67: RealEstateLeaseRent | I67: Net30 | J67: 0 | K67: Marco Tulio Gonzalez Campos | L67: +573223490514 | M67: 45531.598 | N67: Cleared | O67: mtgc1931@gmail.com | Q67: 999999999 | R67: Gonzalez | T67: Tulio | U67: iyanb | V67: iyanb | Y67: +573223490514 | AA67: No | AB67: No | AC67: Primary Contact | AD67: 000219960 | AH67: No | AI67: No | AN67: No | AO67: No | AQ67: No | AR67: No | AT67: No | AV67: Yes | AW67: No | AX67: Phone | AY67: KevinHu | AZ67: 45167.345 | BG67: FirstMiddleLast | BH67: First name | BI67: Middle name | BJ67: Last name | BK67: None | BL67: 1 | BM67: 1 | BN67: 0 | BX67: 0 | BY67: 0 | CA67: 0 | CG67: 0 | CI67: 0
A68: 10000379 | B68: Maruan Abouantoun Naddour | C68: No | D68: TRADE | E68: COP | F68: TRADE | I68: Net30 | J68: 0 | K68: Maruan Abouantoun | L68: +573012121958 | O68: maruan.abouantoun@gmail.com | Q68: 2400 | R68: Naddour | T68: Abouantoun | U68: iyanb | V68: iyanb | Y68: +573012121958 | AA68: No | AB68: No | AC68: Business 4COL | AD68: 000077895 | AH68: No | AI68: No | AN68: No | AO68: No | AQ68: No | AR68: No | AT68: No | AV68: Yes | AW68: No | AX68: Phone | AY68: iyanb | AZ68: 44743.981 | BG68: FirstMiddleLast | BH68: First name | BI68: Middle name | BJ68: Last name | BK68: None | BL68: 1 | BM68: 1 | BN68: 0 | BX68: 0 | BY68: 0 | CA68: 0 | CG68: 0 | CI68: 0
A69: 10000380 | B69: Paul Dario Davila Gonzalez | C69: No | D69: TRADE | E69: COP | F69: TRADE | G69: Equipment | H69: Equipment or Devices | I69: Net30 | J69: 0 | K69: Paul Dario Davila | L69: +593998323998 | M69: 45531.601 | N69: Cleared | O69: ventas@vagadamia.com | P69: http://www.vagadamia.com/ | Q69: 999999999 | R69: Davila Gonzalez | T69: Dario | U69: iyanb | V69: iyanb | Y69: +593998323998 | AA69: No | AB69: No | AC69: Business 4COL | AD69: 000219661 | AH69: No | AI69: No | AN69: No | AO69: No | AQ69: No | AR69: No | AT69: No | AV69: Yes | AW69: No | AX69: Phone | AY69: vincentng | AZ69: 45166.204 | BG69: FirstMiddleLast | BH69: First name | BI69: Middle name | BJ69: Last name | BK69: None | BL69: 1 | BM69: 1 | BN69: 0 | BX69: 0 | BY69: 0 | CA69: 0 | CG69: 0 | CI69: 0
A70: 10000381 | B70: Pompeyo Ortiz Ortiz | C70: No | D70: TRADE | E70: COP | F70: TRADE | G70: Travel Svc | H70: Food Services | I70: Net30 | J70: 0 | K70: Karime Oitzl | L70: +573143925568 | M70: 45466 | N70: Cleared | O70: papeleria_dashika@hotmail.com | Q70: 999999999 | R70: Ortiz | T70: Ortiz | U70: iyanb | V70: iyanb | Y70: +573143925568 | AA70: No | AB70: No | AC70: Primary Contact | AD70: 000202477 | AH70: No | AI70: No | AN70: No | AO70: No | AQ70: No | AR70: No | AT70: No | AV70: Yes | AW70: No | AX70: Phone | AY70: KevinHu | AZ70: 45103.341 | BG70: FirstMiddleLast | BH70: First name | BI70: Middle name | BJ70: Last name | BK70: None | BL70: 1 | BM70: 1 | BN70: 0 | BR70: Oscar Valderrama | BS70: 146055 | BT70: UPagola | BU70: 43774.568 | BV70: UPagola | BW70: 43774.568 | BX70: 5706.73 | BY70: 0 | CA70: 0 | CG70: 0 | CI70: 0 | CL70: Oscar.Valderrama@rescue.org | CX70: en-US | DB70: Oscar Valderrama
A71: 10000382 | B71: Viviana Soto Lopez | C71: No | D71: TRADE | E71: COP | F71: TRADE | G71: ProSvcs | H71: MiscManualLaborSvcs | I71: Net30 | J71: 0 | K71: Viviana Soto Lopez | L71: +573202353080 | M71: 45497.205 | N71: Cleared | O71: hotelvillarealcucuta@gmail.com | P71: https://hotelvillarealcucuta.wordpress.com/ | Q71: 999999999 | R71: Lopez | T71: Soto | U71: iyanb | V71: iyanb | Y71: +573202353080 | AA71: No | AB71: No | AC71: Business 4COL | AD71: 000210726 | AH71: No | AI71: No | AN71: No | AO71: No | AQ71: No | AR71: No | AT71: No | AV71: Yes | AW71: No | AX71: Phone | AY71: sophyo | AZ71: 45131.328 | BG71: FirstMiddleLast | BH71: First name | BI71: Middle name | BJ71: Last name | BK71: None | BL71: 1 | BM71: 1 | BN71: 0 | BX71: 0 | BY71: 0 | CA71: 0 | CG71: 0 | CI71: 0
A72: 10000384 | B72: Lina Abu Awad | C72: All except payment | D72: CONT | E72: COP | F72: CONT | I72: Net30 | J72: 975 | K72: Lina Abu Awad | L72: +962796978454 | M72: 44798.375 | N72: Expired | O72: Lina.AbuAwad@rescue.org | Q72: 2400 | R72: Awad | T72: Abu | U72: iyanb | V72: iyanb | Y72: +962796978454 | AA72: No | AB72: No | AC72: Primary Contact | AD72: 000090070 | AH72: No | AI72: No | AN72: No | AO72: No | AQ72: No | AR72: No | AT72: No | AV72: Yes | AW72: No | AX72: Phone | AY72: kennedyro | AZ72: 44743.981 | BG72: FirstMiddleLast | BH72: First name | BI72: Middle name | BJ72: Last name | BK72: None | BL72: 1 | BM72: 1 | BN72: 0 | BX72: 0 | BY72: 0 | CA72: 0 | CG72: 0 | CI72: 0
A73: 10000385 | B73: Diana Maria Perez Rodriguez | C73: No | D73: CONT | E73: COP | F73: CONT | I73: Net30 | J73: 4466.72 | K73: Diana Perez | L73: +573124827984 | O73: dianaperez.coach@gmail.com | Q73: 2400 | R73: Perez Rodriguez | T73: Maria | U73: iyanb | V73: iyanb | Y73: +573124827984 | AA73: No | AB73: No | AC73: Business 4COL | AD73: 000077909 | AH73: No | AI73: No | AN73: No | AO73: No | AQ73: No | AR73: No | AT73: No | AV73: Yes | AW73: No | AX73: Phone | AY73: iyanb | AZ73: 44743.981 | BG73: FirstMiddleLast | BH73: First name | BI73: Middle name | BJ73: Last name | BK73: None | BL73: 1 | BM73: 1 | BN73: 0 | BX73: 0 | BY73: 0 | CA73: 0 | CG73: 0 | CI73: 0
A74: 10000386 | B74: Lina Paola Milian Miranda | C74: No | D74: CONT | E74: COP | F74: CONT | I74: Net30 | J74: 0 | K74: Lina Millan | L74: +573203144906 | O74: paola.milian@gmail.com | Q74: 2400 | R74: Milian Miranda | T74: Paola | U74: iyanb | V74: iyanb | Y74: +573203144906 | AA74: No | AB74: No | AC74: Business 4COL | AD74: 000077911 | AH74: No | AI74: No | AN74: No | AO74: No | AQ74: No | AR74: No | AT74: No | AV74: Yes | AW74: No | AX74: Phone | AY74: iyanb | AZ74: 44743.981 | BG74: FirstMiddleLast | BH74: First name | BI74: Middle name | BJ74: Last name | BK74: None | BL74: 1 | BM74: 1 | BN74: 0 | BX74: 0 | BY74: 0 | CA74: 0 | CG74: 0 | CI74: 0
A75: 10000390 | B75: Administracion De Transporte Del Norte De Santander SAS | C75: All except payment | D75: TRADE | E75: COP | F75: TRADE | I75: Net30 | J75: 0 | K75: Jovino Alberto Morales Gelvez | L75: +573132774456 | M75: 44914.333 | N75: Expired | O75: acamitrans@gmail.com | Q75: 19000 | Y75: +573132774456 | AA75: No | AB75: No | AC75: Business 4COL | AD75: 000079727 | AH75: No | AI75: No | AN75: No | AO75: No | AQ75: No | AR75: No | AT75: No | AV75: Yes | AW75: No | AX75: Phone | AY75: iyanb | AZ75: 44743.981 | BX75: 0 | BY75: 0 | CA75: 0 | CG75: 0 | CI75: 0
A76: 10000391 | B76: Agencia De Viajes Y Turismo Aviatur SAS | C76: No | D76: TRADE | E76: COP | F76: TRADE | G76: Travel Svc | H76: Agency | I76: Net30 | J76: 261560.79 | K76: Margarita Restrepo | L76: +573153493584 | M76: 45477.497 | N76: Cleared | O76: magarita.restrepo@aviatur.com | P76: https://www.aviatur.com/ | Q76: 999999999 | Y76: +573153493584 | AA76: No | AB76: No | AC76: Primary Contact | AD76: 000205064 | AH76: No | AI76: No | AN76: No | AO76: No | AQ76: No | AR76: No | AT76: No | AV76: Yes | AW76: No | AX76: Phone | AY76: kimberlymag | AZ76: 45112.181 | BR76: LuisGustavo CanizalesQuintero | BS76: 159071 | BT76: Admin | BU76: 44462.208 | BV76: Admin | BW76: 44462.208 | BX76: 8.37 | BY76: 0 | CA76: 0 | CG76: 0 | CI76: 0 | CL76: Luis.Canizales@rescue.org | CX76: en-US | DB76: Luis Cañizales
A77: 10000392 | B77: Alianza Serco SAS | C77: All except payment | D77: TRADE | E77: COP | F77: TRADE | I77: Net30 | J77: 0 | K77: Claudia Yasmin Valdivieso Aguillon | L77: +573114467336 | M77: 44916.333 | N77: Expired | O77: alianzaserco1@gmail.com | Q77: 19000 | Y77: +573114467336 | AA77: No | AB77: No | AC77: Business 4COL | AD77: 000079732 | AH77: No | AI77: No | AN77: No | AO77: No | AQ77: No | AR77: No | AT77: No | AV77: Yes | AW77: No | AX77: Phone | AY77: iyanb | AZ77: 44743.981 | BX77: 0 | BY77: 0 | CA77: 0 | CG77: 0 | CI77: 0
A78: 10000393 | B78: Arca Publicidad Z SAS | C78: No | D78: TRADE | E78: COP | F78: TRADE | G78: ProSvcs | H78: Marketing Technology | I78: Net30 | J78: 1719.66 | K78: Paula Andrea Zuluaga Hurtado | L78: +576043220734 | M78: 45534.202 | N78: Cleared | O78: impresionesmedellin@gmail.com | P78: https://arcapublicidadz.co/ | Q78: 999999999 | Y78: +576043220734 | AA78: No | AB78: No | AC78: Primary Contact | AD78: 000220155 | AH78: No | AI78: No | AN78: No | AO78: No | AQ78: No | AR78: No | AT78: No | AV78: Yes | AW78: No | AX78: Phone | AY78: kimberlymag | AZ78: 45168.127 | BX78: 0 | BY78: 0 | CA78: 0 | CG78: 0 | CI78: 0
A79: 10000394 | B79: Casinos Y Servicios Del Caribe SA | C79: No | D79: TRADE | E79: COP | F79: TRADE | G79: Travel Svc | H79: Event Space | I79: Net30 | J79: 6389.4 | K79: Sandra Reyes Prada | L79: +573208573355 | M79: 45534.247 | N79: Cleared | O79: ventas2@hotel-bolivar.com | P79: https://www.hotel-bolivar.com/ | Q79: 999999999 | Y79: +573208573355 | AA79: No | AB79: No | AC79: Primary Contact | AD79: 000220875 | AH79: No | AI79: No | AN79: No | AO79: No | AQ79: No | AR79: No | AT79: No | AV79: Yes | AW79: No | AX79: Phone | AY79: KevinHu | AZ79: 45169.333 | BX79: 0 | BY79: 0 | CA79: 0 | CG79: 0 | CI79: 0
A80: 10000395 | B80: Centro Especializado De Diagnostico Materno Infantil IPS SAS | C80: All except payment | D80: TRADE | E80: COP | F80: TRADE | G80: Medical | H80: Medical Services | I80: Net30 | J80: 0 | K80: Nelson Omar Sanchez Ure | L80: +573008213870 | M80: 45282.108 | N80: Expired | O80: cedmi.gerencia@outlook.com | P80: https://www.cemdi.net.co/ | Q80: 999999999 | Y80: +573008213870 | AA80: No | AB80: No | AC80: Primary Contact | AD80: 000157736 | AH80: No | AI80: No | AN80: No | AO80: No | AQ80: No | AR80: No | AT80: No | AV80: Yes | AW80: No | AX80: Phone | AY80: shadrackom | AZ80: 44918.098 | BX80: 0 | BY80: 0 | CA80: 0 | CG80: 0 | CI80: 0
A81: 10000396 | B81: Clickarte SAS | C81: All except payment | D81: TRADE | E81: COP | F81: TRADE | I81: Net30 | J81: 0 | K81: Lisa Neisa | L81: +57316917191 | M81: 44916.333 | N81: Expired | O81: info@clickarte.co | P81: https://clickarte.co/ | Q81: 19000 | Y81: +57316917191 | AA81: No | AB81: No | AC81: Business 4COL | AD81: 000079743 | AH81: No | AI81: No | AN81: No | AO81: No | AQ81: No | AR81: No | AT81: No | AV81: Yes | AW81: No | AX81: Phone | AY81: iyanb | AZ81: 44743.981 | BX81: 0 | BY81: 0 | CA81: 0 | CG81: 0 | CI81: 0
A82: 10000397 | B82: Compuventas Cia Ltda | C82: All except payment | D82: TRADE | E82: USD | F82: TRADE | I82: Net30 | J82: 0 | K82: Edgar Muniro Jácome Brito | L82: +593993348410 | M82: 44916.333 | N82: Expired | O82: ejacome@compuventas.com.ec | P82: https://compuventas.com.ec/ | Q82: 19000 | Y82: +593993348410 | AA82: No | AB82: No | AC82: Business 4COL | AD82: 000079746 | AH82: No | AI82: No | AN82: No | AO82: No | AQ82: No | AR82: No | AT82: No | AV82: Yes | AW82: No | AX82: Phone | AY82: iyanb | AZ82: 44743.981 | BX82: 0 | BY82: 0 | CA82: 0 | CG82: 0 | CI82: 0
A83: 10000398 | B83: Copias Digitales, SA | C83: No | D83: TRADE | E83: USD | F83: TRADE | G83: OfficeSupl | H83: Printing Services | I83: Net30 | J83: 1236 | K83: Guillermo Ojeda | L83: +584241839423 | M83: 45707.278 | N83: Cleared | O83: copiasdigitales.sa@gmail.com | P83: http://www.copiasdigitales.com/ | Q83: 19000 | Y83: +584241839423 | AA83: No | AB83: No | AC83: Business 4COL | AD83: 000270104 | AH83: No | AI83: No | AN83: No | AO83: No | AQ83: No | AR83: No | AT83: No | AV83: Yes | AW83: No | AX83: Phone | AY83: MaxwellKi | AZ83: 45342.143 | BR83: Melix Carolina Acevedo Moreno | BS83: 155600 | BT83: Admin | BU83: 44300.443 | BV83: Admin | BW83: 44300.443 | BX83: 193.17 | BY83: 0 | CA83: 0 | CG83: 0 | CI83: 0 | CL83: Melix.Acevedo@rescue.org | CX83: en-US | DB83: Melix Acevedo
A84: 10000399 | B84: Corporacion Vinculos | C84: No | D84: TRADE | E84: COP | F84: TRADE | G84: Medical | H84: Medical Services | I84: Net30 | J84: 8009.28 | K84: Mariana Saenz Uribe | L84: +573108071828 | M84: 45497.216 | N84: Cleared | O84: corporacionvinculos@corporacionvinculos.com | P84: http://corporacionvinculos.org/index/ | Q84: 999999999 | Y84: +573108071828 | AA84: No | AB84: No | AC84: Business 4COL | AD84: 000124760 | AH84: No | AI84: No | AN84: No | AO84: No | AQ84: No | AR84: No | AT84: No | AV84: Yes | AW84: No | AX84: Phone | AY84: KevinHu | AZ84: 44791.928 | BX84: 0 | BY84: 0 | CA84: 0 | CG84: 0 | CI84: 0
A85: 10000400 | B85: Corredor Ochoa Y Asociados SAS | C85: All except payment | D85: TRADE | E85: COP | F85: TRADE | I85: Net30 | J85: 0 | K85: Angie Julieth Vargas Layton | L85: +573043842815 | M85: 44917.333 | N85: Expired | O85: comercializadoracorredorochoa@hotmail.com | Q85: 19000 | Y85: +573043842815 | AA85: No | AB85: No | AC85: Business 4COL | AD85: 000079755 | AH85: No | AI85: No | AN85: No | AO85: No | AQ85: No | AR85: No | AT85: No | AV85: Yes | AW85: No | AX85: Phone | AY85: iyanb | AZ85: 44743.981 | BX85: 0 | BY85: 0 | CA85: 0 | CG85: 0 | CI85: 0
A86: 10000401 | B86: Crehana Education Colombia SAS | C86: All except payment | D86: TRADE | E86: COP | F86: TRADE | I86: Net30 | J86: 0 | K86: Laura Malpartida | L86: +573154633550 | M86: 44917.333 | N86: Expired | O86: laura@crehana.com | P86: https://www.crehana.com/co/ | Q86: 19000 | Y86: +573154633550 | AA86: No | AB86: No | AC86: Business 4COL | AD86: 000079757 | AH86: No | AI86: No | AN86: No | AO86: No | AQ86: No | AR86: No | AT86: No | AV86: Yes | AW86: No | AX86: Phone | AY86: iyanb | AZ86: 44743.981 | BX86: 0 | BY86: 0 | CA86: 0 | CG86: 0 | CI86: 0
A87: 10000402 | B87: Tigers Job Ltda | C87: No | D87: TRADE | E87: COP | F87: TRADE | G87: Safety | H87: Guards | I87: Net30 | J87: 19012.74 | K87: Angelica Guerrero Gonzalez | L87: +573152350459 | M87: 45654.532 | N87: Cleared | O87: comercial@tigerjob.com.co | P87: https://tigersjob.com.co/web_tigers/index.html | Q87: 999999999 | Y87: +573152350459 | AA87: No | AB87: No | AC87: Primary Contact | AD87: 000157759 | AH87: No | AI87: No | AN87: No | AO87: No | AQ87: No | AR87: No | AT87: No | AV87: Yes | AW87: No | AX87: Phone | AY87: shadrackom | AZ87: 44918.124 | BX87: 0 | BY87: 0 | CA87: 0 | CG87: 0 | CI87: 0
A88: 10000403 | B88: Asociacion Profamilia | C88: No | D88: TRADE | E88: COP | F88: TRADE | G88: Medical | H88: Medical Services | I88: Net30 | J88: 150091.87 | K88: Juliana Marín Restrepo | L88: +573124116546 | M88: 45449.41 | N88: Cleared | O88: juliana.marin@profamilia.com | P88: https://profamilia.org.co/ | Q88: 999999999 | Y88: +573124116546 | AA88: No | AB88: No | AC88: Business 4COL | AD88: 000196580 | AH88: No | AI88: No | AN88: No | AO88: No | AQ88: No | AR88: No | AT88: No | AV88: Yes | AW88: No | AX88: Phone | AY88: danielwa | AZ88: 45077.447 | BR88: LuisGustavo CanizalesQuintero | BS88: 159071 | BT88: Admin | BU88: 44462.208 | BV88: Admin | BW88: 44462.208 | BX88: 8.37 | BY88: 0 | CA88: 0 | CG88: 0 | CI88: 0 | CL88: Luis.Canizales@rescue.org | CX88: en-US | DB88: Luis Cañizales
A89: 10000404 | B89: Coordinandora Mercantil SA | C89: No | D89: TRADE | E89: COP | F89: TRADE | G89: Logistics | H89: Shipping | I89: Net30 | J89: 4271.46 | K89: Carolina Fuquen | L89: +573017591015 | M89: 45653.125 | N89: Cleared | O89: carolina@coordinadora.com | P89: https://www.coordinadora.com/ | Q89: 999999999 | Y89: +573017591015 | AA89: No | AB89: No | AC89: Primary Contact | AD89: 000157883 | AH89: No | AI89: No | AN89: No | AO89: No | AQ89: No | AR89: No | AT89: No | AV89: Yes | AW89: No | AX89: Phone | AY89: KevinHu | AZ89: 44918.553 | BX89: 0 | BY89: 0 | CA89: 0 | CG89: 0 | CI89: 0
A90: 10000405 | B90: Cucuta Suites SAS | C90: No | D90: TRADE | E90: COP | F90: TRADE | G90: Food Items | H90: Misc Food Items | I90: Net30 | J90: 1146.04 | K90: Quely Gomez | L90: +575888007 | M90: 45653.125 | N90: Cleared | O90: eventos@csoperador.com | P90: https://www.ihg.com/holidayinn/hotels/us/es/cucuta/cucco/hoteldetail | Q90: 999999999 | Y90: +575888007 | AA90: No | AB90: No | AC90: Primary Contact | AD90: 000259710 | AH90: No | AI90: No | AN90: No | AO90: No | AQ90: No | AR90: No | AT90: No | AV90: Yes | AW90: No | AX90: Phone | AY90: kimberlymag | AZ90: 45288.114 | BX90: 0 | BY90: 0 | CA90: 0 | CG90: 0 | CI90: 0
A91: 10000406 | B91: Dafran Distribuidora CA | C91: All except payment | D91: TRADE | E91: USD | F91: TRADE | I91: Net30 | J91: 0 | K91: Carlos Urbina | L91: +582125505686 | M91: 44917.333 | N91: Expired | O91: info@dafranve.com | P91: http://www.dafranve.com/ | Q91: 19000 | Y91: +582125505686 | AA91: No | AB91: No | AC91: Business 4COL | AD91: 000079772 | AH91: No | AI91: No | AN91: No | AO91: No | AQ91: No | AR91: No | AT91: No | AV91: Yes | AW91: No | AX91: Phone | AY91: iyanb | AZ91: 44743.981 | BX91: 0 | BY91: 0 | CA91: 0 | CG91: 0 | CI91: 0
A92: 10000407 | B92: Departour SAS | C92: No | D92: TRADE | E92: COP | F92: TRADE | G92: Travel Svc | H92: Transportation | I92: Net30 | J92: 0 | K92: Juan Pablo Sanchez Ramirez | L92: +573104665277 | M92: 45654.532 | N92: Cleared | O92: gerencia@departour.com.co | P92: https://www.departour.com.co/ | Q92: 999999999 | Y92: +573104665277 | AA92: No | AB92: No | AC92: Business 4COL | AD92: 000259984 | AH92: No | AI92: No | AN92: No | AO92: No | AQ92: No | AR92: No | AT92: No | AV92: Yes | AW92: No | AX92: Phone | AY92: KevinHu | AZ92: 45289.627 | BX92: 0 | BY92: 0 | CA92: 0 | CG92: 0 | CI92: 0
A93: 10000408 | B93: Didacticos Pinocho SA | C93: All except payment | D93: TRADE | E93: COP | F93: TRADE | G93: OfficeSupl | H93: LearnandDevt | I93: Net30 | J93: 0 | K93: Martha Cecilia Martin Martinez | L93: +573112248362 | M93: 45775.229 | N93: Cleared | O93: distribuidores1@didacticospinocho.com | P93: https://didacticospinocho.com/ | Q93: 19000 | Y93: +573112248362 | AA93: No | AB93: No | AC93: Business 4COL | AD93: 000289746 | AH93: No | AI93: No | AN93: No | AO93: No | AQ93: No | AR93: No | AT93: No | AV93: Yes | AW93: No | AX93: Phone | AY93: sophyo | AZ93: 45411.11 | BR93: LilianaPatricia BernalHerrera | BS93: 150727 | BT93: Admin | BU93: 44094.387 | BV93: Admin | BW93: 44094.387 | BX93: 5008.27 | BY93: 0 | CA93: 0 | CG93: 0 | CI93: 0 | CL93: Liliana.Bernal@rescue.org | CX93: en-US | DB93: Liliana Bernal
A94: 10000409 | B94: Distribuidor Integral De Soluciones Para Oficinas Disofi CA | C94: No | D94: TRADE | E94: USD | F94: TRADE | G94: OfficeSupl | H94: Office Supplies | I94: Net30 | J94: 389.14 | K94: Jose Sanchez | L94: +574142326002 | M94: 45714.493 | N94: Cleared | O94: jose.sanchez@disofi.com.ve | P94: https://www.disofi.com.ve/ | Q94: 999999999 | Y94: +574142326002 | AA94: No | AB94: No | AC94: Business 4COL | AD94: 000271765 | AH94: No | AI94: No | AN94: No | AO94: No | AQ94: No | AR94: No | AT94: No | AV94: Yes | AW94: No | AX94: Phone | AY94: FelistusWa | AZ94: 45349.074 | BR94: LilianaPatricia BernalHerrera | BS94: 150727 | BT94: Admin | BU94: 44094.387 | BV94: Admin | BW94: 44094.387 | BX94: 5008.27 | BY94: 0 | CA94: 0 | CG94: 0 | CI94: 0 | CL94: Liliana.Bernal@rescue.org | CX94: en-US | DB94: Liliana Bernal
A95: 10000410 | B95: Dkt Colombia SAS | C95: All except payment | D95: TRADE | E95: COP | F95: TRADE | I95: Net30 | J95: 0 | K95: Liliana Schmitz | L95: +573114529825 | M95: 44917.333 | N95: Expired | O95: comercialdkt@fastpharma.com.co | P95: https://www.dktinternational.org/ | Q95: 19000 | Y95: +573114529825 | AA95: No | AB95: No | AC95: Business 4COL | AD95: 000079784 | AH95: No | AI95: No | AN95: No | AO95: No | AQ95: No | AR95: No | AT95: No | AV95: Yes | AW95: No | AX95: Phone | AY95: iyanb | AZ95: 44743.981 | BX95: 0 | BY95: 0 | CA95: 0 | CG95: 0 | CI95: 0
A96: 10000411 | B96: Doba SAS | C96: All except payment | D96: TRADE | E96: COP | F96: TRADE | I96: Net30 | J96: 0 | K96: Dolly Constanza Barrero Sanchez | L96: +573102986542 | M96: 44917.333 | N96: Expired | O96: olly@doba.com.co | P96: http://www.doba.com.co/ | Q96: 19000 | Y96: +573102986542 | AA96: No | AB96: No | AC96: Business 4COL | AD96: 000079787 | AH96: No | AI96: No | AN96: No | AO96: No | AQ96: No | AR96: No | AT96: No | AV96: Yes | AW96: No | AX96: Phone | AY96: iyanb | AZ96: 44743.981 | BX96: 0 | BY96: 0 | CA96: 0 | CG96: 0 | CI96: 0
A97: 10000412 | B97: E.S.E. Municipal De Soacha Julio Cesar Peñaloza | C97: All except payment | D97: TRADE | E97: COP | F97: TRADE | G97: Medical | H97: Medical Services | I97: Net30 | J97: 28123.1 | K97: Maria Victoria Herrera Roa | L97: +573133966351 | M97: 45265.417 | N97: Expired | O97: empresadesalud@esesoacha.gov.co | P97: https://www.esesoacha.gov.co/ | Q97: 999999999 | Y97: +573133966351 | AA97: No | AB97: No | AC97: Business 4COL | AD97: 000158353 | AH97: No | AI97: No | AN97: No | AO97: No | AQ97: No | AR97: No | AT97: No | AV97: Yes | AW97: No | AX97: Phone | AY97: KevinHu | AZ97: 44924.58 | BX97: 0 | BY97: 0 | CA97: 0 | CG97: 0 | CI97: 0
A98: 10000413 | B98: Eco Emprendedores Creativos SAS | C98: No | D98: TRADE | E98: COP | F98: TRADE | G98: OfficeSupl | H98: Misc Consumables | I98: Net30 | J98: 24789.32 | K98: Juan Camilo Aragon Meneses | L98: +573108830067 | M98: 45477.247 | N98: Cleared | O98: gerencia@ecoemprendedorescreativos.co | P98: http://www.ecoemprendedorescreativos.com/ | Q98: 999999999 | Y98: +573108830067 | AA98: No | AB98: No | AC98: Business 4COL | AD98: 000196466 | AH98: No | AI98: No | AN98: No | AO98: No | AQ98: No | AR98: No | AT98: No | AV98: Yes | AW98: No | AX98: Phone | AY98: brendaki | AZ98: 45077.306 | BR98: LuisGustavo CanizalesQuintero | BS98: 159071 | BT98: Admin | BU98: 44462.208 | BV98: Admin | BW98: 44462.208 | BX98: 8.37 | BY98: 0 | CA98: 0 | CG98: 0 | CI98: 0 | CL98: Luis.Canizales@rescue.org | CX98: en-US | DB98: Luis Cañizales
A99: 10000414 | B99: Fundacion Orientame | C99: All except payment | D99: TRADE | E99: COP | F99: TRADE | G99: Medical | H99: Medical Services | I99: Net30 | J99: 0 | K99: Teresa Casanova | L99: +573158573752 | M99: 45280.639 | N99: Expired | O99: convenios@orientame.org.co | P99: https://orientame.org.co/ | Q99: 999999999 | Y99: +573158573752 | AA99: No | AB99: No | AC99: Business 4COL | AD99: 000157450 | AH99: No | AI99: No | AN99: No | AO99: No | AQ99: No | AR99: No | AT99: No | AV99: Yes | AW99: No | AX99: Phone | AY99: johannd | AZ99: 44916.409 | BX99: 0 | BY99: 0 | CA99: 0 | CG99: 0 | CI99: 0
A100: 10000415 | B100: Grupo Empresarial Orbe SAS | C100: No | D100: TRADE | E100: COP | F100: TRADE | G100: Medical | H100: MedicalLabEquip | I100: Net30 | J100: 0 | K100: Andrea Paola Rodriguez Peñaloza | L100: +573127658326 | M100: 45653.129 | N100: Cleared | O100: ventas@grupoempresarialorbe.com | Q100: 999999999 | Y100: +573127658326 | AA100: No | AB100: No | AC100: Business 4COL | AD100: 000259711 | AH100: No | AI100: No | AN100: No | AO100: No | AQ100: No | AR100: No | AT100: No | AV100: Yes | AW100: No | AX100: Phone | AY100: sophyo | AZ100: 45288.118 | BX100: 0 | BY100: 0 | CA100: 0 | CG100: 0 | CI100: 0
...

Sheet All vendors
A1: Vendor account | B1: Name | C1: Vendor hold | D1: Group | E1: Currency/ Donor Currency | F1: Group2 | G1: Line of business | H1: Segment | I1: Terms of payment | J1: @AKA:VendorTotalSpending | K1: Reference | L1: Phone | M1: ATC clearance expiration date | N1: ATC status | O1: Email address | P1: URL | Q1: Vendor anticipated spend USD | R1: Last name | S1: Last name prefix | T1: Middle name | U1: Created by | V1: Modified by | W1: Birth date | X1: Channel Reference Identifier | Y1: Contact number/address | Z1: Country of birth | AA1: Country of birth entered | AB1: Date of birth entered | AC1: Description | AD1: Electronic address Id | AE1: Extension | AF1: First name | AG1: Gender | AH1: Gender entered | AI1: Instant message | AJ1: International calling code | AK1: Last name2 | AL1: Location | AM1: Maiden name | AN1: Maiden name entered | AO1: Marketing opt-in | AP1: Middle name2 | AQ1: Middle name entered | AR1: Mobile | AS1: Nationality | AT1: Nationality entered | AU1: Party reference for private location | AV1: Primary | AW1: Private | AX1: Type | AY1: Modified by2 | AZ1: Modified date and time | BA1: Affix | BB1: Affix type | BC1: Description2 | BD1: Affix2 | BE1: Affix type2 | BF1: Description3 | BG1: Display as | BH1: Name elements | BI1: Name elements2 | BJ1: Name elements3 | BK1: Name elements4 | BL1: Number of blank spaces | BM1: Number of blank spaces2 | BN1: Number of blank spaces3 | BO1: Separator | BP1: Separator2 | BQ1: Separator3 | BR1: Name2 | BS1: Personnel number | BT1: Created by2 | BU1: Created date and time | BV1: Modified by3 | BW1: Modified date and time2 | BX1: @AKA:VendorTotalSpending2 | BY1: Anniversary day | BZ1: Anniversary month | CA1: Anniversary year | CB1: ATC check Id | CC1: ATC check Id2 | CD1: ATC clearance expiration date 2 | CE1: ATC status2 | CF1: ATC status3 | CG1: Birth day | CH1: Birth month | CI1: Birth year | CJ1: Children | CK1: DUNS number | CL1: Email address2 | CM1: Facebook | CN1: Fax | CO1: First name2 | CP1: First name3 | CQ1: Gender2 | CR1: Hobbies | CS1: Initials | CT1: Instant messenger sign-in | CU1: Integra ATC submission date | CV1: Known as | CW1: Known As 2 | CX1: Language | CY1: Last name3 | CZ1: Last name4 | DA1: LinkedIn | DB1: Location2
A2: 10000001 | B2: Gabriela Gonzalez | C2: No | D2: CONT | E2: COP | F2: CONT | I2: Net30 | J2: 384.16 | O2: Gabriela.Gonzalez@rescue.org | Q2: 20000 | R2: Gonzalez | U2: Admin | V2: Admin | AA2: No | AB2: No | AH2: No | AI2: No | AN2: No | AO2: No | AQ2: No | AR2: No | AT2: No | AV2: No | AW2: No | BG2: FirstMiddleLast | BH2: First name | BI2: Middle name | BJ2: Last name | BK2: None | BL2: 1 | BM2: 1 | BN2: 0 | BX2: 0 | BY2: 0 | CA2: 0 | CG2: 0 | CI2: 0
A3: 10000210 | B3: LouisianaCarolina MendozaZabala | C3: No | D3: EMP | E3: COP | F3: EMP | I3: Net30 | J3: 10852 | O3: Louisiana.Mendoza@rescue.org | Q3: 0 | R3: MendozaZabala | U3: Admin | V3: Admin | AA3: No | AB3: No | AH3: No | AI3: No | AN3: No | AO3: No | AQ3: No | AR3: No | AT3: No | AV3: No | AW3: No | BG3: FirstMiddleLast | BH3: First name | BI3: Middle name | BJ3: Last name | BK3: None | BL3: 1 | BM3: 1 | BN3: 0 | BX3: 0 | BY3: 0 | CA3: 0 | CG3: 0 | CI3: 0
A4: 10000218 | B4: Veronica Suarez | C4: No | D4: CONT | E4: COP | F4: CONT | I4: Net30 | J4: 0 | O4: Veronica.Suarez@rescue.org | Q4: 0 | R4: Suarez | U4: UPagola | V4: UPagola | AA4: No | AB4: No | AH4: No | AI4: No | AN4: No | AO4: No | AQ4: No | AR4: No | AT4: No | AV4: No | AW4: No | BG4: FirstMiddleLast | BH4: First name | BI4: Middle name | BJ4: Last name | BK4: None | BL4: 1 | BM4: 1 | BN4: 0 | BX4: 0 | BY4: 0 | CA4: 0 | CG4: 0 | CI4: 0
A5: 10000245 | B5: Reinaldo Chacon | C5: No | D5: CONT | E5: COP | F5: CONT | I5: Net30 | J5: 0 | O5: Reinaldo.Chacon@rescue.org | Q5: 0 | R5: Chacon | U5: Admin | V5: Admin | AA5: No | AB5: No | AH5: No | AI5: No | AN5: No | AO5: No | AQ5: No | AR5: No | AT5: No | AV5: No | AW5: No | BG5: FirstMiddleLast | BH5: First name | BI5: Middle name | BJ5: Last name | BK5: None | BL5: 1 | BM5: 1 | BN5: 0 | BX5: 0 | BY5: 0 | CA5: 0 | CG5: 0 | CI5: 0
A6: 10000261 | B6: Jose Baptista | C6: No | D6: CONT | E6: USD | F6: CONT | I6: Net30 | J6: 0 | O6: Jose.Baptista@rescue.org | Q6: 0 | R6: Baptista | U6: Admin | V6: Admin | AA6: No | AB6: No | AH6: No | AI6: No | AN6: No | AO6: No | AQ6: No | AR6: No | AT6: No | AV6: No | AW6: No | BG6: FirstMiddleLast | BH6: First name | BI6: Middle name | BJ6: Last name | BK6: None | BL6: 1 | BM6: 1 | BN6: 0 | BX6: 0 | BY6: 0 | CA6: 0 | CG6: 0 | CI6: 0
A7: 10000262 | B7: Angelica Sanchez | C7: No | D7: CONT | E7: USD | F7: CONT | I7: Net30 | J7: 0 | O7: Angelica.Sanchez@rescue.org | Q7: 0 | R7: Sanchez | U7: Admin | V7: Admin | AA7: No | AB7: No | AH7: No | AI7: No | AN7: No | AO7: No | AQ7: No | AR7: No | AT7: No | AV7: No | AW7: No | BG7: FirstMiddleLast | BH7: First name | BI7: Middle name | BJ7: Last name | BK7: None | BL7: 1 | BM7: 1 | BN7: 0 | BX7: 0 | BY7: 0 | CA7: 0 | CG7: 0 | CI7: 0
A8: 10000264 | B8: Ivan Delahais | C8: No | D8: CONT | E8: COP | F8: CONT | I8: Net30 | J8: 0 | O8: Ivan.Delahais@rescue.org | Q8: 0 | R8: Delahais | U8: Admin | V8: Admin | AA8: No | AB8: No | AH8: No | AI8: No | AN8: No | AO8: No | AQ8: No | AR8: No | AT8: No | AV8: No | AW8: No | BG8: FirstMiddleLast | BH8: First name | BI8: Middle name | BJ8: Last name | BK8: None | BL8: 1 | BM8: 1 | BN8: 0 | BX8: 0 | BY8: 0 | CA8: 0 | CG8: 0 | CI8: 0
A9: 10000266 | B9: Esttefany Alvarez | C9: No | D9: CONT | E9: COP | F9: CONT | I9: Net30 | J9: 0 | O9: Esttefany.Alvarez@rescue.org | Q9: 0 | R9: Alvarez | U9: Admin | V9: Admin | AA9: No | AB9: No | AH9: No | AI9: No | AN9: No | AO9: No | AQ9: No | AR9: No | AT9: No | AV9: No | AW9: No | BG9: FirstMiddleLast | BH9: First name | BI9: Middle name | BJ9: Last name | BK9: None | BL9: 1 | BM9: 1 | BN9: 0 | BX9: 0 | BY9: 0 | CA9: 0 | CG9: 0 | CI9: 0
A10: 10000272 | B10: Reinaldo Gutierrez | C10: No | D10: CONT | E10: USD | F10: CONT | I10: Net30 | J10: 0 | O10: Reinaldo.Gutierrez@rescue.org | Q10: 0 | R10: Gutierrez | U10: Admin | V10: Admin | AA10: No | AB10: No | AH10: No | AI10: No | AN10: No | AO10: No | AQ10: No | AR10: No | AT10: No | AV10: No | AW10: No | BG10: FirstMiddleLast | BH10: First name | BI10: Middle name | BJ10: Last name | BK10: None | BL10: 1 | BM10: 1 | BN10: 0 | BX10: 0 | BY10: 0 | CA10: 0 | CG10: 0 | CI10: 0
A11: 10000275 | B11: Lucia Añasco | C11: No | D11: CONT | E11: USD | F11: CONT | I11: Net30 | J11: 0 | O11: Lucia.Anasco@rescue.org | Q11: 0 | R11: Añasco | U11: Admin | V11: Admin | AA11: No | AB11: No | AH11: No | AI11: No | AN11: No | AO11: No | AQ11: No | AR11: No | AT11: No | AV11: No | AW11: No | BG11: FirstMiddleLast | BH11: First name | BI11: Middle name | BJ11: Last name | BK11: None | BL11: 1 | BM11: 1 | BN11: 0 | BX11: 0 | BY11: 0 | CA11: 0 | CG11: 0 | CI11: 0
A12: 10000277 | B12: Miriam Moya | C12: No | D12: CONT | E12: COP | F12: CONT | I12: Net30 | J12: 0 | O12: Miriam.Moya@rescue.org | Q12: 0 | R12: Moya | U12: Admin | V12: Admin | AA12: No | AB12: No | AH12: No | AI12: No | AN12: No | AO12: No | AQ12: No | AR12: No | AT12: No | AV12: No | AW12: No | BG12: FirstMiddleLast | BH12: First name | BI12: Middle name | BJ12: Last name | BK12: None | BL12: 1 | BM12: 1 | BN12: 0 | BX12: 0 | BY12: 0 | CA12: 0 | CG12: 0 | CI12: 0
A13: 10000279 | B13: Diana Montero | C13: No | D13: CONT | E13: USD | F13: CONT | I13: Net30 | J13: 0 | O13: Diana.Montero@rescue.org | Q13: 0 | R13: Montero | U13: Admin | V13: Admin | AA13: No | AB13: No | AH13: No | AI13: No | AN13: No | AO13: No | AQ13: No | AR13: No | AT13: No | AV13: No | AW13: No | BG13: FirstMiddleLast | BH13: First name | BI13: Middle name | BJ13: Last name | BK13: None | BL13: 1 | BM13: 1 | BN13: 0 | BX13: 0 | BY13: 0 | CA13: 0 | CG13: 0 | CI13: 0
A14: 10000285 | B14: Marcela Valdez | C14: No | D14: CONT | E14: COP | F14: CONT | I14: Net30 | J14: 0 | O14: Marcela.Valdez@rescue.org | Q14: 0 | R14: Valdez | U14: Admin | V14: Admin | AA14: No | AB14: No | AH14: No | AI14: No | AN14: No | AO14: No | AQ14: No | AR14: No | AT14: No | AV14: No | AW14: No | BG14: FirstMiddleLast | BH14: First name | BI14: Middle name | BJ14: Last name | BK14: None | BL14: 1 | BM14: 1 | BN14: 0 | BX14: 0 | BY14: 0 | CA14: 0 | CG14: 0 | CI14: 0
A15: 10000287 | B15: Diana Perez | C15: No | D15: CONT | E15: COP | F15: CONT | I15: Net30 | J15: 1712.61 | K15: Diana Perez | L15: +573124827984 | Q15: 0 | R15: Perez | U15: Admin | V15: Admin | Y15: +573124827984 | AA15: No | AB15: No | AC15: Primary Contact | AD15: 000291656 | AH15: No | AI15: No | AN15: No | AO15: No | AQ15: No | AR15: No | AT15: No | AV15: Yes | AW15: No | AX15: Phone | AY15: MaxwellKi | AZ15: 45419.411 | BG15: FirstMiddleLast | BH15: First name | BI15: Middle name | BJ15: Last name | BK15: None | BL15: 1 | BM15: 1 | BN15: 0 | BX15: 0 | BY15: 0 | CA15: 0 | CG15: 0 | CI15: 0
A16: 10000288 | B16: Paola Milian | C16: No | D16: CONT | E16: USD | F16: CONT | I16: Net30 | J16: 0 | Q16: 0 | R16: Milian | U16: Admin | V16: Admin | AA16: No | AB16: No | AH16: No | AI16: No | AN16: No | AO16: No | AQ16: No | AR16: No | AT16: No | AV16: No | AW16: No | BG16: FirstMiddleLast | BH16: First name | BI16: Middle name | BJ16: Last name | BK16: None | BL16: 1 | BM16: 1 | BN16: 0 | BX16: 0 | BY16: 0 | CA16: 0 | CG16: 0 | CI16: 0
A17: 10000300 | B17: Stephanie Hernandez | C17: No | D17: CONT | E17: COP | F17: CONT | I17: Net30 | J17: 0 | O17: Stephanie.Hernandez@rescue.org | Q17: 0 | R17: Hernandez | U17: Admin | V17: Admin | AA17: No | AB17: No | AH17: No | AI17: No | AN17: No | AO17: No | AQ17: No | AR17: No | AT17: No | AV17: No | AW17: No | BG17: FirstMiddleLast | BH17: First name | BI17: Middle name | BJ17: Last name | BK17: None | BL17: 1 | BM17: 1 | BN17: 0 | BX17: 0 | BY17: 0 | CA17: 0 | CG17: 0 | CI17: 0
A18: 10000317 | B18: Manuel Bello | C18: No | D18: CONT | E18: COP | F18: CONT | I18: Net30 | J18: 0 | O18: Manuel.Bello@rescue.org | Q18: 0 | R18: Bello | U18: Admin | V18: Admin | AA18: No | AB18: No | AH18: No | AI18: No | AN18: No | AO18: No | AQ18: No | AR18: No | AT18: No | AV18: No | AW18: No | BG18: FirstMiddleLast | BH18: First name | BI18: Middle name | BJ18: Last name | BK18: None | BL18: 1 | BM18: 1 | BN18: 0 | BX18: 0 | BY18: 0 | CA18: 0 | CG18: 0 | CI18: 0
A19: 10000327 | B19: Abogados IRC Colombia | C19: All | D19: CONT | E19: USD | F19: CONT | I19: Net30 | J19: 0 | O19: AbogadosIRC.Colombia@rescue.org | Q19: 0 | R19: Colombia | U19: Admin | V19: Admin | AA19: No | AB19: No | AH19: No | AI19: No | AN19: No | AO19: No | AQ19: No | AR19: No | AT19: No | AV19: No | AW19: No | BG19: FirstMiddleLast | BH19: First name | BI19: Middle name | BJ19: Last name | BK19: None | BL19: 1 | BM19: 1 | BN19: 0 | BX19: 0 | BY19: 0 | CA19: 0 | CG19: 0 | CI19: 0
A20: 10000331 | B20: ATG Action Translation Group SAS | C20: No | D20: TRADE | E20: COP | F20: TRADE | G20: ProSvcs | H20: TranslateInterpret | I20: Net30 | J20: 36362.61 | K20: Carlos Javier Rivera Rojas | L20: +573005630873 | M20: 45775.112 | N20: Cleared | O20: atgtraducciones@gmail.com | P20: http://atgtraducciones.com/ | Q20: 999999999 | Y20: +573005630873 | AA20: No | AB20: No | AC20: Business 4COL | AD20: 000317887 | AH20: No | AI20: No | AN20: No | AO20: No | AQ20: No | AR20: No | AT20: No | AV20: Yes | AW20: No | AX20: Phone | AY20: brendaki | AZ20: 45547.399 | BR20: Liliana Bernal | BS20: 150727 | BT20: Admin | BU20: 44094.387 | BV20: Admin | BW20: 44094.387 | BX20: 12076.32 | BY20: 0 | CA20: 0 | CG20: 0 | CI20: 0 | CL20: Liliana.Bernal@rescue.org | CX20: en-US | DB20: Liliana Bernal
A21: 10000332 | B21: Alianza Fiduciaria SA Fideicomisos | C21: No | D21: TRADE | E21: COP | F21: TRADE | G21: Food Items | H21: Food Services | I21: Net30 | J21: 478173.64 | K21: Jenifer Paola Juanz Maldonado | L21: +5716447700 | M21: 45918.261 | N21: Cleared | O21: jequintero@alianza.com.co | P21: https://www.alianza.com.co/ | Q21: 999999999 | Y21: +5716447700 | AA21: No | AB21: No | AC21: Business 4COL | AD21: 000340421 | AH21: No | AI21: No | AN21: No | AO21: No | AQ21: No | AR21: No | AT21: No | AV21: Yes | AW21: No | AX21: Phone | AY21: stellamas | AZ21: 45558.381 | BX21: 0 | BY21: 0 | CA21: 0 | CG21: 0 | CI21: 0
A22: 10000333 | B22: Blanco Santana Montiel & Rincón | C22: No | D22: TRADE | E22: USD | F22: TRADE | G22: ProSvcs | H22: Legal Services | I22: Net30 | J22: 125454.36 | K22: Maria Alejandra Blanco Blanco | L22: +5824242506417 | M22: 45867.716 | N22: Cleared | O22: mablanco@bsmr.com.ve | P22: https://www.bsmr.com.ve/ | Q22: 999999999 | Y22: +5824242506417 | AA22: No | AB22: No | AC22: Primary Contact | AD22: 000317889 | AH22: No | AI22: No | AN22: No | AO22: No | AQ22: No | AR22: No | AT22: No | AV22: Yes | AW22: No | AX22: Phone | AY22: brendaki | AZ22: 45547.399 | BR22: MelixCarolina AcevedoMoreno | BS22: 155600 | BT22: Admin | BU22: 44300.443 | BV22: Admin | BW22: 44300.443 | BX22: 7806.01 | BY22: 0 | CA22: 0 | CG22: 0 | CI22: 0 | CL22: Melix.Acevedo@rescue.org | CX22: en-US | DB22: Melix Acevedo
A23: 10000334 | B23: Camara de Comercio De Bogota | C23: No | D23: TRADE | E23: COP | F23: TRADE | I23: Net30 | J23: 0 | K23: Gustavo Aroca Cespedes | L23: +5713830300 | O23: gustavo.aroca@ccb.org.co | P23: https://www.ccb.org.co/ | Q23: 2400 | Y23: +5713830300 | AA23: No | AB23: No | AC23: Business 4COL | AD23: 000317890 | AH23: No | AI23: No | AN23: No | AO23: No | AQ23: No | AR23: No | AT23: No | AV23: Yes | AW23: No | AX23: Phone | AY23: brendaki | AZ23: 45547.399 | BX23: 0 | BY23: 0 | CA23: 0 | CG23: 0 | CI23: 0
A24: 10000335 | B24: Campamento La Milagrosa, CA | C24: All except payment | D24: TRADE | E24: USD | F24: TRADE | I24: Net30 | J24: 0 | K24: Luis Enrique Porras | L24: +582123396036 | M24: 44769.375 | N24: Expired | O24: lamilagrosa.kp@gmail.com | Q24: 19000 | Y24: +582123396036 | AA24: No | AB24: No | AC24: Business 4COL | AD24: 000317891 | AH24: No | AI24: No | AN24: No | AO24: No | AQ24: No | AR24: No | AT24: No | AV24: Yes | AW24: No | AX24: Phone | AY24: brendaki | AZ24: 45547.399 | BX24: 0 | BY24: 0 | CA24: 0 | CG24: 0 | CI24: 0
A25: 10000336 | B25: Club de Cazadores SA | C25: All except payment | D25: TRADE | E25: COP | F25: TRADE | G25: ProSvcs | H25: Lodging | I25: Net30 | J25: 0 | K25: Manuel Guillermo Gil Quintero | L25: +5775751164 | M25: 45419.577 | N25: Expired | O25: clubcazadorescucuta1@hotmail.com | P25: https://www.clubcazadores.com.co/ | Q25: 999999999 | Y25: +5775751164 | AA25: No | AB25: No | AC25: Business 4COL | AD25: 000317892 | AH25: No | AI25: No | AN25: No | AO25: No | AQ25: No | AR25: No | AT25: No | AV25: Yes | AW25: No | AX25: Phone | AY25: brendaki | AZ25: 45547.399 | BX25: 0 | BY25: 0 | CA25: 0 | CG25: 0 | CI25: 0
A26: 10000337 | B26: Comercializadora Distriaseo de Nariño SAS | C26: All except payment | D26: TRADE | E26: COP | F26: TRADE | G26: Medical | H26: Medical Consumables | I26: Net30 | J26: 0 | K26: Leydi Yanira Eraso | L26: +573174960376 | M26: 45497.056 | N26: Expired | O26: distriaseodenarino.sas@gmail.com | P26: https://distriaseodenar.negocio.site/ | Q26: 999999999 | Y26: +573174960376 | AA26: No | AB26: No | AC26: Business 4COL | AD26: 000317893 | AH26: No | AI26: No | AN26: No | AO26: No | AQ26: No | AR26: No | AT26: No | AV26: Yes | AW26: No | AX26: Phone | AY26: brendaki | AZ26: 45547.399 | BX26: 0 | BY26: 0 | CA26: 0 | CG26: 0 | CI26: 0
A27: 10000338 | B27: Comercializadora Montes De Colombia SAS | C27: All except payment | D27: TRADE | E27: COP | F27: TRADE | G27: OfficeSupl | H27: Office Supplies | I27: Net30 | J27: 0 | K27: Gregorio Higinio Garzon Jaimes | L27: +0113215061585 | M27: 45566.247 | N27: Expired | O27: aerogarzo@hotmail.com | P27: https://www.superlosmontes.com/site/ | Q27: 999999999 | X27: 1283f04a-85e4-4b7e-b040-9ebdb852f2b1 | Y27: +0113215061585 | AA27: No | AB27: No | AC27: Business 4COL | AD27: 000317894 | AH27: No | AI27: No | AN27: No | AO27: No | AQ27: No | AR27: No | AT27: No | AV27: Yes | AW27: No | AX27: Phone | AY27: brendaki | AZ27: 45547.399 | BX27: 0 | BY27: 0 | CA27: 0 | CG27: 0 | CI27: 0
A28: 10000339 | B28: Comunidad de las Hermanas de la Caridad Dominicas de la Presentacion de la Santisima Virgen | C28: All except payment | D28: TRADE | E28: COP | F28: TRADE | G28: Facilities | H28: RealEstateLeaseRent | I28: Net30 | J28: 0 | K28: Hna. BlancaMargarita Duque Lopez | L28: +573168255459 | M28: 45465.997 | N28: Expired | O28: bmduque@hotmail.com | Q28: 999999999 | Y28: +573168255459 | AA28: No | AB28: No | AC28: Business 4COL | AD28: 000317895 | AH28: No | AI28: No | AN28: No | AO28: No | AQ28: No | AR28: No | AT28: No | AV28: Yes | AW28: No | AX28: Phone | AY28: brendaki | AZ28: 45547.399 | BR28: Oscar Valderrama | BS28: 146055 | BT28: UPagola | BU28: 43774.568 | BV28: UPagola | BW28: 43774.568 | BX28: 5706.73 | BY28: 0 | CA28: 0 | CG28: 0 | CI28: 0 | CL28: Oscar.Valderrama@rescue.org | CX28: en-US | DB28: Oscar Valderrama
A29: 10000340 | B29: Corporacion Parque Explora | C29: No | D29: TRADE | E29: COP | F29: TRADE | I29: Net30 | J29: 0 | K29: Monica Escobar | L29: +5715168300 | O29: monica.escobar@parqueexplora.org | P29: https://www.parqueexplora.org/ | Q29: 2400 | Y29: +5715168300 | AA29: No | AB29: No | AC29: Business 4COL | AD29: 000317896 | AH29: No | AI29: No | AN29: No | AO29: No | AQ29: No | AR29: No | AT29: No | AV29: Yes | AW29: No | AX29: Phone | AY29: brendaki | AZ29: 45547.399 | BX29: 0 | BY29: 0 | CA29: 0 | CG29: 0 | CI29: 0
A30: 10000341 | B30: Del Mar Abogados SAS | C30: No | D30: TRADE | E30: COP | F30: TRADE | G30: ProSvcs | H30: Legal Services | I30: Net30 | J30: 50012.98 | K30: Caroline Del Mar Gallardo Rojas | L30: +5713221386 | M30: 45846.268 | N30: Cleared | O30: caroline@grupodelmar.com | P30: https://www.grupodelmar.com/ | Q30: 999999999 | Y30: +5713221386 | AA30: No | AB30: No | AC30: Business 4COL | AD30: 000317897 | AH30: No | AI30: No | AN30: No | AO30: No | AQ30: No | AR30: No | AT30: No | AV30: Yes | AW30: No | AX30: Phone | AY30: brendaki | AZ30: 45547.399 | BR30: LuisGustavo CanizalesQuintero | BS30: 159071 | BT30: Admin | BU30: 44462.208 | BV30: Admin | BW30: 44462.208 | BX30: 5743.52 | BY30: 0 | CA30: 0 | CG30: 0 | CI30: 0 | CL30: Luis.Canizales@rescue.org | CX30: en-US | DB30: Luis Cañizales
A31: 10000342 | B31: Delicias Aguitas, CA | C31: All except payment | D31: TRADE | E31: COP | F31: TRADE | G31: ProSvcs | H31: Consultancy | I31: Net30 | J31: 0 | K31: Alexandra Reina Taurel Beracasa | L31: +582122329039 | M31: 45465.997 | N31: Expired | O31: deliciasaguitas@gmail.com | Q31: 999999999 | Y31: +582122329039 | AA31: No | AB31: No | AC31: Business 4COL | AD31: 000317898 | AH31: No | AI31: No | AN31: No | AO31: No | AQ31: No | AR31: No | AT31: No | AV31: Yes | AW31: No | AX31: Phone | AY31: brendaki | AZ31: 45547.399 | BR31: Oscar Valderrama | BS31: 146055 | BT31: UPagola | BU31: 43774.568 | BV31: UPagola | BW31: 43774.568 | BX31: 5706.73 | BY31: 0 | CA31: 0 | CG31: 0 | CI31: 0 | CL31: Oscar.Valderrama@rescue.org | CX31: en-US | DB31: Oscar Valderrama
A32: 10000343 | B32: Docuxer Sociedad por Acciones Simplificada | C32: No | D32: TRADE | E32: COP | F32: TRADE | G32: Technology | H32: Equipment or Devices | I32: Net30 | J32: 2188.47 | K32: Monica Patricia Lobo acuna | L32: +573167430292 | M32: 45853.667 | N32: Cleared | O32: monica.lobo@docuxer.com | P32: https://www.docuxer.com/ | Q32: 999999999 | Y32: +573167430292 | AA32: No | AB32: No | AC32: Primary Number 4COL | AD32: 000305976 | AH32: No | AI32: No | AN32: No | AO32: No | AQ32: No | AR32: No | AT32: No | AV32: Yes | AW32: No | AX32: Phone | AY32: MaxwellKi | AZ32: 45490.216 | BR32: Liliana Bernal | BS32: 150727 | BT32: Admin | BU32: 44094.387 | BV32: Admin | BW32: 44094.387 | BX32: 12076.32 | BY32: 0 | CA32: 0 | CG32: 0 | CI32: 0 | CL32: Liliana.Bernal@rescue.org | CX32: en-US | DB32: Liliana Bernal
A33: 10000344 | B33: Empresa Social Del Estado - Metrosalud | C33: All except payment | D33: TRADE | E33: COP | F33: TRADE | G33: Medical | H33: Medical Consumables | I33: Net30 | J33: 2978.24 | K33: Valentina Sosa Carvajal | L33: +5760455117505 | M33: 45497.059 | N33: Expired | O33: gerencia@metrosalud.gov.co | P33: http://www.metrosalud.gov.co/ | Q33: 999999999 | Y33: +5760455117505 | AA33: No | AB33: No | AC33: Primary Contact | AD33: 000317899 | AH33: No | AI33: No | AN33: No | AO33: No | AQ33: No | AR33: No | AT33: No | AV33: Yes | AW33: No | AX33: Phone | AY33: brendaki | AZ33: 45547.399 | BX33: 0 | BY33: 0 | CA33: 0 | CG33: 0 | CI33: 0
A34: 10000345 | B34: Fundacion Artesanos De Sueños | C34: No | D34: TRADE | E34: COP | F34: TRADE | G34: Food Items | H34: Misc Food Items | I34: Net30 | J34: 579.42 | K34: Marisol Alvarez Munevar | L34: +573142830180 | M34: 45847.268 | N34: Cleared | O34: fundacionartesanosdesuenos@gmail.com | P34: https://www.fundacionartesanosdesuenos.org/ | Q34: 999999999 | Y34: +573142830180 | AA34: No | AB34: No | AC34: Business 4COL | AD34: 000317900 | AH34: No | AI34: No | AN34: No | AO34: No | AQ34: No | AR34: No | AT34: No | AV34: Yes | AW34: No | AX34: Phone | AY34: brendaki | AZ34: 45547.399 | BR34: Oscar Valderrama | BS34: 146055 | BT34: UPagola | BU34: 43774.568 | BV34: UPagola | BW34: 43774.568 | BX34: 5706.73 | BY34: 0 | CA34: 0 | CG34: 0 | CI34: 0 | CL34: Oscar.Valderrama@rescue.org | CX34: en-US | DB34: Oscar Valderrama
A35: 10000346 | B35: Global Operadora Hotelera SAS | C35: No | D35: TRADE | E35: COP | F35: TRADE | G35: Travel Svc | H35: Food Services | I35: Net30 | J35: 599.5 | K35: Milena Mosquera | L35: +3102394883 | M35: 45862.413 | N35: Cleared | O35: ventas2@embassy-bogota.com.co | P35: www.bogota.embassysuites.com | Q35: 19000 | X35: ca6695fe-ba75-4d2c-81cd-68da272bdefe | Y35: +3102394883 | AA35: No | AB35: No | AC35: Business 4COL | AD35: 000317901 | AH35: No | AI35: No | AN35: No | AO35: No | AQ35: No | AR35: No | AT35: No | AV35: Yes | AW35: No | AX35: Phone | AY35: brendaki | AZ35: 45547.399 | BX35: 0 | BY35: 0 | CA35: 0 | CG35: 0 | CI35: 0
A36: 10000347 | B36: Integral Group MHL, CA | C36: All except payment | D36: TRADE | E36: USD | F36: TRADE | I36: Net30 | J36: 0 | K36: Michelle Maria Lemoine | L36: +584143211830 | M36: 44768.375 | N36: Expired | O36: michele.lemoine1@gmail.com | Q36: 19000 | Y36: +584143211830 | AA36: No | AB36: No | AC36: Business 4COL | AD36: 000317902 | AH36: No | AI36: No | AN36: No | AO36: No | AQ36: No | AR36: No | AT36: No | AV36: Yes | AW36: No | AX36: Phone | AY36: brendaki | AZ36: 45547.399 | BX36: 0 | BY36: 0 | CA36: 0 | CG36: 0 | CI36: 0
A37: 10000348 | B37: Inversiones Pikachu 77 CA | C37: No | D37: TRADE | E37: USD | F37: TRADE | G37: Construct | H37: Construction Svcs | I37: Net30 | J37: 19631.75 | K37: Carlos Jose Peña Brice | L37: +584142523171 | M37: 45615.636 | N37: Cleared | O37: bricecarlo@gmail.com | Q37: 999999999 | Y37: +584142523171 | AA37: No | AB37: No | AC37: Business 4COL | AD37: 000317903 | AH37: No | AI37: No | AN37: No | AO37: No | AQ37: No | AR37: No | AT37: No | AV37: Yes | AW37: No | AX37: Phone | AY37: brendaki | AZ37: 45547.399 | BR37: MelixCarolina AcevedoMoreno | BS37: 155600 | BT37: Admin | BU37: 44300.443 | BV37: Admin | BW37: 44300.443 | BX37: 7806.01 | BY37: 0 | CA37: 0 | CG37: 0 | CI37: 0 | CL37: Melix.Acevedo@rescue.org | CX37: en-US | DB37: Melix Acevedo
A38: 10000349 | B38: Muebles y Plasticos SAS | C38: All except payment | D38: TRADE | E38: COP | F38: TRADE | I38: Net30 | J38: 0 | K38: Hugo Fernando Garcia | L38: +5714030303 | M38: 44788.375 | N38: Expired | O38: compumuebles@compumuebles.com | P38: https://compumuebles.com/ | Q38: 19000 | Y38: +5714030303 | AA38: No | AB38: No | AC38: Business 4COL | AD38: 000317904 | AH38: No | AI38: No | AN38: No | AO38: No | AQ38: No | AR38: No | AT38: No | AV38: Yes | AW38: No | AX38: Phone | AY38: brendaki | AZ38: 45547.399 | BX38: 0 | BY38: 0 | CA38: 0 | CG38: 0 | CI38: 0
A39: 10000350 | B39: Multisuministros Nissi SAS | C39: All except payment | D39: TRADE | E39: COP | F39: TRADE | G39: OfficeSupl | H39: Misc Consumables | I39: Net30 | J39: 247.29 | K39: Hernan Camilo Escobar | L39: +573152869071 | M39: 45497.396 | N39: Expired | O39: multisuministrosnissi@gmail.com | Q39: 999999999 | Y39: +573152869071 | AA39: No | AB39: No | AC39: Primary Number 4COL | AD39: 000317905 | AH39: No | AI39: No | AN39: No | AO39: No | AQ39: No | AR39: No | AT39: No | AV39: Yes | AW39: No | AX39: Phone | AY39: brendaki | AZ39: 45547.399 | BX39: 0 | BY39: 0 | CA39: 0 | CG39: 0 | CI39: 0
A40: 10000351 | B40: Organización Terpel SA | C40: All except payment | D40: TRADE | E40: COP | F40: TRADE | G40: Travel Svc | H40: Transportation | I40: Net30 | J40: 1782.68 | K40: Carlos Arturo Prada Perez | L40: +573185215187 | M40: 45566.39 | N40: Pending | O40: carlos.prada@terpel.com | P40: https://www.terpel.com/ | Q40: 999999999 | Y40: +573185215187 | AA40: No | AB40: No | AC40: Business 4COL | AD40: 000343691 | AH40: No | AI40: No | AN40: No | AO40: No | AQ40: No | AR40: No | AT40: No | AV40: Yes | AW40: No | AX40: Phone | AY40: FelistusWa | AZ40: 45571.714 | BR40: DayanaCarolina MorontaCorrea | BS40: 150360 | BT40: Admin | BU40: 44076.287 | BV40: Admin | BW40: 44076.287 | BX40: 6278.92 | BY40: 0 | CA40: 0 | CG40: 0 | CI40: 0 | CL40: Dayana.Moronta@rescue.org | CX40: en-US | DB40: Dayana Moronta
A41: 10000352 | B41: Papeleria El Cid SAS | C41: No | D41: TRADE | E41: COP | F41: TRADE | G41: Equipment | H41: Equipment or Devices | I41: Net30 | J41: 786.6 | K41: Fabian Tamayo Carvajal | L41: +574489411 | M41: 45838.23 | N41: Cleared | O41: ventas3@papelcid.com | P41: https://www.elcidpapeleria.com/inicio | Q41: 19000 | Y41: +574489411 | AA41: No | AB41: No | AC41: Primary Contact | AD41: 000317907 | AH41: No | AI41: No | AN41: No | AO41: No | AQ41: No | AR41: No | AT41: No | AV41: Yes | AW41: No | AX41: Phone | AY41: brendaki | AZ41: 45547.399 | BR41: Jeimy Guerrero | BS41: 166795 | BT41: Admin | BU41: 44690.599 | BV41: Admin | BW41: 44690.599 | BX41: 943.54 | BY41: 0 | CA41: 0 | CG41: 0 | CI41: 0 | CL41: Jeimy.Guerrero@rescue.org | CP41: jeimy | CX41: en-US | CZ41: guerrero | DB41: jeimy guerrero
A42: 10000353 | B42: People Pass SA | C42: No | D42: TRADE | E42: COP | F42: TRADE | G42: Travel Svc | H42: Customs Clearance | I42: Net30 | J42: 1946.93 | K42: Edwin Alberto Parra Moncada Parra Moncada | L42: +573173836054 | M42: 45849.257 | N42: Cleared | O42: edwin.parra@peoplepass.com.co | P42: https://www.peoplepass.com.co/ | Q42: 999999999 | Y42: +573173836054 | AA42: No | AB42: No | AC42: Business 4COL | AD42: 000305071 | AH42: No | AI42: No | AN42: No | AO42: No | AQ42: No | AR42: No | AT42: No | AV42: Yes | AW42: No | AX42: Phone | AY42: faithmut | AZ42: 45485.173 | BR42: Liliana Bernal | BS42: 150727 | BT42: Admin | BU42: 44094.387 | BV42: Admin | BW42: 44094.387 | BX42: 12076.32 | BY42: 0 | CA42: 0 | CG42: 0 | CI42: 0 | CL42: Liliana.Bernal@rescue.org | CX42: en-US | DB42: Liliana Bernal
A43: 10000354 | B43: Prinntech SAS | C43: No | D43: TRADE | E43: COP | F43: TRADE | G43: OfficeSupl | H43: Office Supplies | I43: Net30 | J43: 225.35 | K43: Carolina Garcia | L43: +5717432931 | M43: 45833.337 | N43: Cleared | O43: carolina.garcia@prinntech.com | P43: http://www.prinntech.com/ | Q43: 5000 | Y43: +5717432931 | AA43: No | AB43: No | AC43: Business 4COL | AD43: 000317908 | AH43: No | AI43: No | AN43: No | AO43: No | AQ43: No | AR43: No | AT43: No | AV43: Yes | AW43: No | AX43: Phone | AY43: brendaki | AZ43: 45547.399 | BR43: Ronny Candelo | BS43: 155389 | BT43: Admin | BU43: 44285.452 | BV43: Admin | BW43: 44285.452 | BX43: 1334 | BY43: 0 | CA43: 0 | CG43: 0 | CI43: 0 | CL43: Ronny.Candelo@rescue.org | CX43: en-US | DB43: Ronny Candelo
A44: 10000355 | B44: Prosegur Vigilancia y Seguridad Privada LTDA | C44: No | D44: TRADE | E44: COP | F44: TRADE | I44: Net30 | J44: 397.9 | K44: Jonathan Cortes | L44: +573232202544 | O44: jonathan.cortes@prosegur.com | P44: https://www.prosegur.com/ | Q44: 2400 | Y44: +573232202544 | AA44: No | AB44: No | AC44: Business 4COL | AD44: 000317909 | AH44: No | AI44: No | AN44: No | AO44: No | AQ44: No | AR44: No | AT44: No | AV44: Yes | AW44: No | AX44: Phone | AY44: brendaki | AZ44: 45547.399 | BX44: 0 | BY44: 0 | CA44: 0 | CG44: 0 | CI44: 0
A45: 10000356 | B45: Prosuministros de Colombia SAS | C45: No | D45: TRADE | E45: COP | F45: TRADE | G45: Technology | H45: Value Added Reseller | I45: Net30 | J45: 43805.44 | K45: Daniel Felipe Valbuena Cubides | L45: +573204170057 | M45: 45845.098 | N45: Cleared | O45: gerencia@prosuministros.com | P45: https://prosuministros.com/ | Q45: 999999999 | Y45: +573204170057 | AA45: No | AB45: No | AC45: Business 4COL | AD45: 000317910 | AH45: No | AI45: No | AN45: No | AO45: No | AQ45: No | AR45: No | AT45: No | AV45: Yes | AW45: No | AX45: Phone | AY45: brendaki | AZ45: 45547.399 | BX45: 0 | BY45: 0 | CA45: 0 | CG45: 0 | CI45: 0
A46: 10000357 | B46: Rosero, Moscoso & Asociados | C46: All except payment | D46: TRADE | E46: COP | F46: TRADE | G46: ProSvcs | H46: Legal Services | I46: Net30 | J46: 0 | K46: Eduardo Rosero Alban | L46: +593995270410 | M46: 45921.833 | N46: Cleared | O46: erosero@rma.pro.ec | P46: https://rma.pro.ec/ | Q46: 999999999 | Y46: +593995270410 | AA46: No | AB46: No | AC46: Business 4COL | AD46: 000317911 | AH46: No | AI46: No | AN46: No | AO46: No | AQ46: No | AR46: No | AT46: No | AV46: Yes | AW46: No | AX46: Phone | AY46: brendaki | AZ46: 45547.399 | BX46: 0 | BY46: 0 | CA46: 0 | CG46: 0 | CI46: 0
A47: 10000358 | B47: SC Service Servicios De Confianza SAS | C47: No | D47: TRADE | E47: COP | F47: TRADE | G47: Vehicles | H47: Cars and Trucks | I47: Net30 | J47: 0 | K47: Rafael Eduardo Yanet Sanchez | L47: +573164031622 | M47: 45910.597 | N47: Cleared | O47: scserviciosdeconfianzasas@gmail.com | Q47: 19000 | Y47: +573164031622 | AA47: No | AB47: No | AC47: Business 4COL | AD47: 000317912 | AH47: No | AI47: No | AN47: No | AO47: No | AQ47: No | AR47: No | AT47: No | AV47: Yes | AW47: No | AX47: Phone | AY47: brendaki | AZ47: 45547.399 | BX47: 0 | BY47: 0 | CA47: 0 | CG47: 0 | CI47: 0
A48: 10000359 | B48: Servicios Integrales y Suministros Candelas | C48: All except payment | D48: TRADE | E48: USD | F48: TRADE | G48: Travel Svc | H48: Transportation | I48: Net30 | J48: 0 | K48: Jose Luis Chacon Candelas | L48: +542763442705 | M48: 45243.65 | N48: Expired | O48: siscan.ve@gmail.com | Q48: 999999999 | Y48: +542763442705 | AA48: No | AB48: No | AC48: Primary Contact | AD48: 000317913 | AH48: No | AI48: No | AN48: No | AO48: No | AQ48: No | AR48: No | AT48: No | AV48: Yes | AW48: No | AX48: Phone | AY48: brendaki | AZ48: 45547.399 | BX48: 0 | BY48: 0 | CA48: 0 | CG48: 0 | CI48: 0
A49: 10000360 | B49: Sodexho Pass Venezuela, CA | C49: All except payment | D49: CASH | E49: USD | F49: CASH | I49: Net30 | J49: 0 | K49: Lisbeth Mayra Alvarez | L49: +584141504277 | M49: 44788.375 | N49: Expired | O49: Lisbeth.ALVAREZ@sodexo.com | P49: https://www.sodexo.com.ve/ | Q49: 19000 | Y49: +584141504277 | AA49: No | AB49: No | AC49: Business 4COL | AD49: 000077852 | AH49: No | AI49: No | AN49: No | AO49: No | AQ49: No | AR49: No | AT49: No | AV49: Yes | AW49: No | AX49: Phone | AY49: iyanb | AZ49: 44743.981 | BX49: 0 | BY49: 0 | CA49: 0 | CG49: 0 | CI49: 0
A50: 10000361 | B50: Suministros Anvi, CA | C50: All except payment | D50: TRADE | E50: USD | F50: TRADE | I50: Net30 | J50: 0 | K50: Lisbeth Del Valle Amundarain | L50: +584123279060 | M50: 44768.375 | N50: Expired | O50: suministrosanvi@gmail.com | Q50: 19000 | Y50: +584123279060 | AA50: No | AB50: No | AC50: Business 4COL | AD50: 000317914 | AH50: No | AI50: No | AN50: No | AO50: No | AQ50: No | AR50: No | AT50: No | AV50: Yes | AW50: No | AX50: Phone | AY50: brendaki | AZ50: 45547.399 | BX50: 0 | BY50: 0 | CA50: 0 | CG50: 0 | CI50: 0
A51: 10000362 | B51: Surtidora Institucional SAS | C51: No | D51: TRADE | E51: COP | F51: TRADE | G51: Equipment | H51: Equipment or Devices | I51: Net30 | J51: 5949.64 | K51: Liliana Rocio Madariaga | L51: +573173696146 | M51: 45625.608 | N51: Cleared | O51: ventas7@surtidorainstitucional.com.co | P51: https://www.surtidorainstitucional.com.co/ | Q51: 999999999 | Y51: +573173696146 | AA51: No | AB51: No | AC51: Primary Contact | AD51: 000317915 | AH51: No | AI51: No | AN51: No | AO51: No | AQ51: No | AR51: No | AT51: No | AV51: Yes | AW51: No | AX51: Phone | AY51: brendaki | AZ51: 45547.399 | BR51: DayanaCarolina MorontaCorrea | BS51: 150360 | BT51: Admin | BU51: 44076.287 | BV51: Admin | BW51: 44076.287 | BX51: 6278.92 | BY51: 0 | CA51: 0 | CG51: 0 | CI51: 0 | CL51: Dayana.Moronta@rescue.org | CX51: en-US | DB51: Dayana Moronta
A52: 10000363 | B52: Tannus & Asociados SAS | C52: No | D52: TRADE | E52: COP | F52: TRADE | I52: Net30 | J52: 1029.53 | K52: Rodrigo Eduardo Tannus Serrano | L52: +573115069125 | O52: rtannus@tannus.co | P52: http://tannus.co/es/ | Q52: 2400 | Y52: +573115069125 | AA52: No | AB52: No | AC52: Business 4COL | AD52: 000317916 | AH52: No | AI52: No | AN52: No | AO52: No | AQ52: No | AR52: No | AT52: No | AV52: Yes | AW52: No | AX52: Phone | AY52: brendaki | AZ52: 45547.399 | BX52: 0 | BY52: 0 | CA52: 0 | CG52: 0 | CI52: 0
A53: 10000364 | B53: Cooperativa de Transportadores Tax Coopebombas LTDA | C53: No | D53: TRADE | E53: COP | F53: TRADE | G53: Travel Svc | H53: Transportation | I53: Net30 | J53: 12923.81 | K53: Sebastian Zapata Restrepo | L53: +57604514243 | M53: 45643.688 | N53: Cleared | P53: https://www.coopebombas.com/ | Q53: 999999999 | Y53: +57604514243 | AA53: No | AB53: No | AC53: Business 4COL | AD53: 000317917 | AH53: No | AI53: No | AN53: No | AO53: No | AQ53: No | AR53: No | AT53: No | AV53: Yes | AW53: No | AX53: Phone | AY53: brendaki | AZ53: 45547.399 | BX53: 0 | BY53: 0 | CA53: 0 | CG53: 0 | CI53: 0
A54: 10000365 | B54: Tornicentro Group SAS | C54: No | D54: TRADE | E54: COP | F54: TRADE | G54: Construct | H54: Construction Svcs | I54: Net30 | J54: 319.65 | K54: Julian David Madero Amado | L54: +573132935061 | M54: 45849.181 | N54: Cleared | O54: julianmadero@tornicentro.com.co | P54: https://www.tornicentro.com.co/ | Q54: 999999999 | Y54: +573132935061 | AA54: No | AB54: No | AC54: Business 4COL | AD54: 000340653 | AH54: No | AI54: No | AN54: No | AO54: No | AQ54: No | AR54: No | AT54: No | AV54: Yes | AW54: No | AX54: Phone | AY54: faithmut | AZ54: 45559.222 | BR54: Liliana Bernal | BS54: 150727 | BT54: Admin | BU54: 44094.387 | BV54: Admin | BW54: 44094.387 | BX54: 12076.32 | BY54: 0 | CA54: 0 | CG54: 0 | CI54: 0 | CL54: Liliana.Bernal@rescue.org | CX54: en-US | DB54: Liliana Bernal
A55: 10000366 | B55: Amparo Rangel De Castañeda | C55: All except payment | D55: TRADE | E55: COP | F55: TRADE | I55: Net30 | J55: 0 | K55: Amparo Rangel De Catañeda | L55: +573102661899 | M55: 44748.375 | N55: Expired | O55: amparito.ra@hotmail.com | Q55: 19000 | R55: De Castañeda | T55: Rangel | U55: iyanb | V55: iyanb | Y55: +573102661899 | AA55: No | AB55: No | AC55: Business 4COL | AD55: 000317918 | AH55: No | AI55: No | AN55: No | AO55: No | AQ55: No | AR55: No | AT55: No | AV55: Yes | AW55: No | AX55: Phone | AY55: brendaki | AZ55: 45547.399 | BG55: FirstMiddleLast | BH55: First name | BI55: Middle name | BJ55: Last name | BK55: None | BL55: 1 | BM55: 1 | BN55: 0 | BX55: 0 | BY55: 0 | CA55: 0 | CG55: 0 | CI55: 0
A56: 10000367 | B56: Armando Agustin Revelo Martinez | C56: All except payment | D56: TRADE | E56: COP | F56: TRADE | G56: ProSvcs | H56: Consultancy | I56: Net30 | J56: 0 | K56: Armando Agustin Revelo | L56: +573155029690 | M56: 45497.396 | N56: Expired | O56: armandoreplay@gmail.com | Q56: 999999999 | R56: Revelo Martinez | T56: Agustin | U56: iyanb | V56: iyanb | Y56: +573155029690 | AA56: No | AB56: No | AC56: Business 4COL | AD56: 000317919 | AH56: No | AI56: No | AN56: No | AO56: No | AQ56: No | AR56: No | AT56: No | AV56: Yes | AW56: No | AX56: Phone | AY56: brendaki | AZ56: 45547.399 | BG56: FirstMiddleLast | BH56: First name | BI56: Middle name | BJ56: Last name | BK56: None | BL56: 1 | BM56: 1 | BN56: 0 | BX56: 0 | BY56: 0 | CA56: 0 | CG56: 0 | CI56: 0
A57: 10000368 | B57: Camilo Andres Salamanca Alvarez | C57: All except payment | D57: TRADE | E57: COP | F57: TRADE | I57: Net30 | J57: 2.26 | K57: Camilo Andres Salamanca Alvarez | L57: +573153610772 | M57: 45243.653 | N57: Expired | O57: salamanca.camilo@gmail.com | Q57: 999999999 | R57: Salamanca Alvarez | T57: Andres | U57: iyanb | V57: iyanb | Y57: +573153610772 | AA57: No | AB57: No | AC57: Business 4COL | AD57: 000317920 | AH57: No | AI57: No | AN57: No | AO57: No | AQ57: No | AR57: No | AT57: No | AV57: Yes | AW57: No | AX57: Phone | AY57: brendaki | AZ57: 45547.399 | BG57: FirstMiddleLast | BH57: First name | BI57: Middle name | BJ57: Last name | BK57: None | BL57: 1 | BM57: 1 | BN57: 0 | BX57: 0 | BY57: 0 | CA57: 0 | CG57: 0 | CI57: 0
A58: 10000369 | B58: Carlos Alberto Molinares Rovira | C58: No | D58: TRADE | E58: COP | F58: TRADE | G58: Safety | H58: SystemsEquipDevices | I58: Net30 | J58: 0 | K58: Carlos Alberto Molinares Rovira | L58: +573102772300 | M58: 45855.171 | N58: Cleared | O58: carlosmolinares15@gmail.com | Q58: 999999999 | R58: Molinares Rovira | T58: Alberto | U58: iyanb | V58: iyanb | Y58: +573102772300 | AA58: No | AB58: No | AC58: Business 4COL | AD58: 000317921 | AH58: No | AI58: No | AN58: No | AO58: No | AQ58: No | AR58: No | AT58: No | AV58: Yes | AW58: No | AX58: Phone | AY58: brendaki | AZ58: 45547.399 | BG58: FirstMiddleLast | BH58: First name | BI58: Middle name | BJ58: Last name | BK58: None | BL58: 1 | BM58: 1 | BN58: 0 | BR58: Liliana Bernal | BS58: 150727 | BT58: Admin | BU58: 44094.387 | BV58: Admin | BW58: 44094.387 | BX58: 12076.32 | BY58: 0 | CA58: 0 | CG58: 0 | CI58: 0 | CL58: Liliana.Bernal@rescue.org | CX58: en-US | DB58: Liliana Bernal
